Workbook
Name lista_mun: OFFSET(INDIRECT(#REF!),,,#REF!)
Name resultados_2019: '[1]5'!$B$1:$G$60
Name resultados_2020: '[1]6'!$B$1:$G$60
Name resultados_2021: '[1]7'!$B$1:$G$60
Name niveles: #REF!
Name codmun: #REF!

Sheet Estructura
A1: FACTOR 1 | B1: CONDICIONES HABILITANTES | D1: Periodo | E1: Último | F1: Pilar | G1: Subpilar | H1: Subpilar en el pilar | I1: Variable en el subpilar | J1: Variable en el pilar
A2: PILAR 1: INSTITUCIONES | C2: INVERSA | D2: Corte | E2: Año | F2: =1/13 -> 0.076923077
A3: INS-1 | B3: Desempeño administrativo | G3: =$F$2/4 -> 0.019230769 | H3: =G3/$F$2 -> 0.25 | L3: 2019 | M3: =COUNTIF(E:E,L3) -> 0 | N3: =M3/98 -> 0
A4: INS-1-1 | B4: Gestión de recursos | C4: No | D4: 2019-2022 | E4: =IFERROR(MID(D4,6,4),"") -> 2022 | I4: =1/COUNTBLANK($H$4:$H$6) -> 0.33333333 | J4: =I4*$H$3 -> 0.083333333 | L4: 2020 | M4: =COUNTIF(E:E,L4) -> 0 | N4: =M4/98 -> 0
A5: INS-1-2 | B5: Actualización catastral | C5: Sí | D5: 2018-2022 | E5: =IFERROR(MID(D5,6,4),"") -> 2022 | I5: =1/COUNTBLANK($H$4:$H$6) -> 0.33333333 | J5: =I5*$H$3 -> 0.083333333 | L5: 2021 | M5: =COUNTIF(E:E,L5) -> 4 | N5: =M5/98 -> 0.040816327
A6: INS-1-3 | B6: Índice de Gobierno Digital para el Estado | C6: No | D6: 2022-2023 | E6: =IFERROR(MID(D6,6,4),"") -> 2023 | I6: =1/COUNTBLANK($H$4:$H$6) -> 0.33333333 | J6: =I6*$H$3 -> 0.083333333 | L6: 2022 | M6: =COUNTIF(E:E,L6) -> 36 | N6: =M6/98 -> 0.36734694
A7: INS-2 | B7: Gestión fiscal | E7: =IFERROR(MID(D7,6,4),"") | G7: =$F$2/4 -> 0.019230769 | H7: =G7/$F$2 -> 0.25 | L7: 2023 | M7: =COUNTIF(E:E,L7) -> 55 | N7: =M7/98 -> 0.56122449
A8: INS-2-1 | B8: Autonomía fiscal | C8: No | D8: 2017-2022 | E8: =IFERROR(MID(D8,6,4),"") -> 2022 | I8: =1/COUNTBLANK($H$8:$H$10) -> 0.33333333 | J8: =I8*$H$7 -> 0.083333333 | L8: 2024 | M8: =COUNTIF(E:E,L8) -> 3 | N8: =M8/98 -> 0.030612245
A9: INS-2-2 | B9: Capacidad local de recaudo | C9: No | D9: 2017-2022 | E9: =IFERROR(MID(D9,6,4),"") -> 2022 | I9: =1/COUNTBLANK($H$8:$H$10) -> 0.33333333 | J9: =I9*$H$7 -> 0.083333333
A10: INS-2-3 | B10: Capacidad de ahorro | C10: No | D10: 2017-2022 | E10: =IFERROR(MID(D10,6,4),"") -> 2022 | I10: =1/COUNTBLANK($H$8:$H$10) -> 0.33333333 | J10: =I10*$H$7 -> 0.083333333
A11: INS-3 | B11: Transparencia y contratación pública | E11: =IFERROR(MID(D11,6,4),"") | G11: =$F$2/4 -> 0.019230769 | H11: =G11/$F$2 -> 0.25
A12: INS-3-1 | B12: Índice de Gobierno Digital para la Sociedad | C12: No | D12: 2022-2023 | E12: =IFERROR(MID(D12,6,4),"") -> 2023 | I12: =1/COUNTBLANK($H$12:$H$13) -> 0.5 | J12: =I12*$H$11 -> 0.125
A13: INS-3-2 | B13: Procesos de contratación en SECOP II | C13: No | D13: 2020-2022 | E13: =IFERROR(MID(D13,6,4),"") -> 2022 | I13: =1/COUNTBLANK($H$12:$H$13) -> 0.5 | J13: =I13*$H$11 -> 0.125
A14: INS-4 | B14: Seguridad y justicia | E14: =IFERROR(MID(D14,6,4),"") | G14: =$F$2/4 -> 0.019230769 | H14: =G14/$F$2 -> 0.25
A15: INS-4-1 | B15: Tasa de homicidios | C15: Sí | D15: 2018-2023 | E15: =IFERROR(MID(D15,6,4),"") -> 2023 | I15: =1/COUNTBLANK($H$15:$H$20) -> 0.16666667 | J15: =I15*$H$14 -> 0.041666667
A16: INS-4-2 | B16: Tasa de hurtos | C16: Sí | D16: 2018-2023 | E16: =IFERROR(MID(D16,6,4),"") -> 2023 | I16: =1/COUNTBLANK($H$15:$H$20) -> 0.16666667 | J16: =I16*$H$14 -> 0.041666667
A17: INS-4-3 | B17: Tasa de extorsión | C17: Sí | D17: 2018-2023 | E17: =IFERROR(MID(D17,6,4),"") -> 2023 | I17: =1/COUNTBLANK($H$15:$H$20) -> 0.16666667 | J17: =I17*$H$14 -> 0.041666667
A18: INS-4-4 | B18: Eficiencia de la justicia | C18: No | D18: 2018-2023 | E18: =IFERROR(MID(D18,6,4),"") -> 2023 | I18: =1/COUNTBLANK($H$15:$H$20) -> 0.16666667 | J18: =I18*$H$14 -> 0.041666667
A19: INS-4-5 | B19: Productividad de jueces | C19: No | D19: 2017-2022 | E19: =IFERROR(MID(D19,6,4),"") -> 2022 | I19: =1/COUNTBLANK($H$15:$H$20) -> 0.16666667 | J19: =I19*$H$14 -> 0.041666667
A20: INS-4-6 | B20: Eficiencia de los métodos de resolución de conflictos | C20: No | D20: 2018-2023 | E20: =IFERROR(MID(D20,6,4),"") -> 2023 | I20: =1/COUNTBLANK($H$15:$H$20) -> 0.16666667 | J20: =I20*$H$14 -> 0.041666667
A21: PILAR 2: INFRAESTRUCTURA Y EQUIPAMIENTO | E21: =IFERROR(MID(D21,6,4),"") | F21: =F2 -> 0.076923077
A22: INF-1 | B22: Infraestructura de servicios | E22: =IFERROR(MID(D22,6,4),"") | G22: =$F$21/3 -> 0.025641026 | H22: =G22/$F$21 -> 0.33333333
A23: INF-1-1 | B23: Cobertura de acueducto | C23: No | D23: 2018-2022 | E23: =IFERROR(MID(D23,6,4),"") -> 2022 | I23: =1/COUNTBLANK($H$23:$H$27) -> 0.2 | J23: =I23*$H$22 -> 0.066666667
A24: INF-1-2 | B24: Cobertura efectiva de gas natural | C24: No | D24: 2018-2023 | E24: =IFERROR(MID(D24,6,4),"") -> 2023 | I24: =1/COUNTBLANK($H$23:$H$27) -> 0.2 | J24: =I24*$H$22 -> 0.066666667
A25: INF-1-3 | B25: Cobertura de la energía eléctrica | C25: No | D25: 2018-2023 | E25: =IFERROR(MID(D25,6,4),"") -> 2023 | I25: =1/COUNTBLANK($H$23:$H$27) -> 0.2 | J25: =I25*$H$22 -> 0.066666667
A26: INF-1-4 | B26: Costo de la energía eléctrica | C26: Sí | D26: 2018-2023 | E26: =IFERROR(MID(D26,6,4),"") -> 2023 | I26: =1/COUNTBLANK($H$23:$H$27) -> 0.2 | J26: =I26*$H$22 -> 0.066666667
A27: INF-1-5 | B27: Cobertura de alcantarillado | C27: No | D27: 2018-2022 | E27: =IFERROR(MID(D27,6,4),"") -> 2022 | I27: =1/COUNTBLANK($H$23:$H$27) -> 0.2 | J27: =I27*$H$22 -> 0.066666667
A28: INF-2 | B28: Conectividad | E28: =IFERROR(MID(D28,6,4),"") | G28: =G22 -> 0.025641026 | H28: =G28/$F$21 -> 0.33333333
A29: INF-2-1 | B29: Costo de transporte terrestre a mercado interno | C29: Sí | D29: 2018-2023 | E29: =IFERROR(MID(D29,6,4),"") -> 2023 | I29: =1/COUNTBLANK($H$29:$H$33) -> 0.2 | J29: =I29*$H$28 -> 0.066666667
A30: INF-2-2 | B30: Costo de transporte terrestre a aduanas | C30: Sí | D30: 2018-2023 | E30: =IFERROR(MID(D30,6,4),"") -> 2023 | I30: =1/COUNTBLANK($H$29:$H$33) -> 0.2 | J30: =I30*$H$28 -> 0.066666667
A31: INF-2-3 | B31: Pasajeros movilizados vía aérea | C31: No | D31: 2018-2023 | E31: =IFERROR(MID(D31,6,4),"") -> 2023 | I31: =1/COUNTBLANK($H$29:$H$33) -> 0.2 | J31: =I31*$H$28 -> 0.066666667
A32: INF-2-4 | B32: Índice de conectividad aérea | C32: No | D32: 2018-2023 | E32: =IFERROR(MID(D32,6,4),"") -> 2023 | I32: =1/COUNTBLANK($H$29:$H$33) -> 0.2 | J32: =I32*$H$28 -> 0.066666667
A33: INF-2-5 | B33: Pasajeros movilizados por transporte público | C33: No | D33: 2019-2024 | E33: =IFERROR(MID(D33,6,4),"") -> 2024 | I33: =1/COUNTBLANK($H$29:$H$33) -> 0.2 | J33: =I33*$H$28 -> 0.066666667
A34: INF-3 | B34: Oferta Cultural | E34: =IFERROR(MID(D34,6,4),"") | G34: =G22 -> 0.025641026 | H34: =G34/$F$21 -> 0.33333333
A35: INF-3-1 | B35: Ejemplares de biblioteca | C35: No | D35: 2018-2023 | E35: =IFERROR(MID(D35,6,4),"") -> 2023 | I35: =1/COUNTBLANK($H$35:$H$39) -> 0.2 | J35: =I35*$H$34 -> 0.066666667
A36: INF-3-2 | B36: Museos | C36: No | D36: 2019-2024 | E36: =IFERROR(MID(D36,6,4),"") -> 2024 | I36: =1/COUNTBLANK($H$35:$H$39) -> 0.2 | J36: =I36*$H$34 -> 0.066666667
A37: INF-3-3 | B37: Sillas de sala de cine | C37: No | D37: 2018-2022 | E37: =IFERROR(MID(D37,6,4),"") -> 2022 | I37: =1/COUNTBLANK($H$35:$H$39) -> 0.2 | J37: =I37*$H$34 -> 0.066666667
A38: INF-3-4 | B38: Escenarios culturales | C38: No | D38: 2018-2022 | E38: =IFERROR(MID(D38,6,4),"") -> 2022 | I38: =1/COUNTBLANK($H$35:$H$39) -> 0.2 | J38: =I38*$H$34 -> 0.066666667
A39: INF-3-5 | B39: Bienes de interés cultural | C39: No | D39: 2019-2024 | E39: =IFERROR(MID(D39,6,4),"") -> 2024 | I39: =1/COUNTBLANK($H$35:$H$39) -> 0.2 | J39: =I39*$H$34 -> 0.066666667
A40: PILAR 3: Adopción TIC | E40: =IFERROR(MID(D40,6,4),"") | F40: =F2 -> 0.076923077
A41: TIC-1 | B41: Infraestructura TIC | E41: =IFERROR(MID(D41,6,4),"") | G41: =F40/2 -> 0.038461538 | H41: =G41/$F$40 -> 0.5
A42: TIC-1-1 | B42: Penetración de internet banda ancha fijo | C42: No | D42: 2018-2023 | E42: =IFERROR(MID(D42,6,4),"") -> 2023 | I42: =1/COUNTBLANK($H$42:$H$45) -> 0.25 | J42: =I42*$H$41 -> 0.125
A43: TIC-1-2 | B43: Ancho de banda de internet | C43: No | D43: 2018-2023 | E43: =IFERROR(MID(D43,6,4),"") -> 2023 | I43: =1/COUNTBLANK($H$42:$H$45) -> 0.25 | J43: =I43*$H$41 -> 0.125
A44: TIC-1-3 | B44: Hogares con computador, portátil o tablet | C44: No | D44: 2020-2023 | E44: =IFERROR(MID(D44,6,4),"") -> 2023 | I44: =1/COUNTBLANK($H$42:$H$45) -> 0.25 | J44: =I44*$H$41 -> 0.125
A45: TIC-1-4 | B45: Uso de Internet | C45: No | D45: 2020-2023 | E45: =IFERROR(MID(D45,6,4),"") -> 2023 | I45: =1/COUNTBLANK($H$42:$H$45) -> 0.25 | J45: =I45*$H$41 -> 0.125
A46: TIC-2 | B46: Capacidades TIC | E46: =IFERROR(MID(D46,6,4),"") | G46: =G41 -> 0.038461538 | H46: =H41 -> 0.5
A47: TIC-2-1 | B47: Matriculados en programas TIC | C47: No | D47: 2018-2023 | E47: =IFERROR(MID(D47,6,4),"") -> 2023 | I47: =1/COUNTBLANK($H$47:$H$49) -> 0.33333333 | J47: =I47*$H$46 -> 0.16666667
A48: TIC-2-2 | B48: Graduados en programas TIC | C48: No | D48: 2018-2023 | E48: =IFERROR(MID(D48,6,4),"") -> 2023 | I48: =1/COUNTBLANK($H$47:$H$49) -> 0.33333333 | J48: =I48*$H$46 -> 0.16666667
A49: TIC-2-3 | B49: Programas TIC | C49: No | D49: 2018-2023 | E49: =IFERROR(MID(D49,6,4),"") -> 2023 | I49: =1/COUNTBLANK($H$47:$H$49) -> 0.33333333 | J49: =I49*$H$46 -> 0.16666667
A50: PILAR 4: SOSTENIBILIDAD AMBIENTAL | E50: =IFERROR(MID(D50,6,4),"") | F50: =F2 -> 0.076923077
A51: AMB-1 | B51: Activos naturales | E51: =IFERROR(MID(D51,6,4),"") | G51: =$F$50/2 -> 0.038461538 | H51: =G51/$F$50 -> 0.5
A52: AMB-1-1 | B52: Áreas protegidas | C52: No | D52: 2020-2023 | E52: =IFERROR(MID(D52,6,4),"") -> 2023 | I52: =1/COUNTBLANK($H$52:$H$55) -> 0.25 | J52: =I52*$H$51 -> 0.125
A53: AMB-1-2 | B53: Emisiones de CO2 de fuentes fijas | C53: Sí | D53: 2018-2022 | E53: =IFERROR(MID(D53,6,4),"") -> 2022 | I53: =1/COUNTBLANK($H$52:$H$55) -> 0.25 | J53: =I53*$H$51 -> 0.125
A54: AMB-1-3 | B54: Emisiones de CO2 de fuentes móviles | C54: Sí | D54: 2018-2023 | E54: =IFERROR(MID(D54,6,4),"") -> 2023 | I54: =1/COUNTBLANK($H$52:$H$55) -> 0.25 | J54: =I54*$H$51 -> 0.125
A55: AMB-1-4 | B55: Hectáreas de bosque deforestadas | C55: Sí | D55: 2018-2022 | E55: =IFERROR(MID(D55,6,4),"") -> 2022 | I55: =1/COUNTBLANK($H$52:$H$55) -> 0.25 | J55: =I55*$H$51 -> 0.125
A56: AMB-2 | B56: Gestión ambiental y del riesgo | E56: =IFERROR(MID(D56,6,4),"") | G56: =$F$50/2 -> 0.038461538 | H56: =G56/$F$50 -> 0.5
A57: AMB-2-1 | B57: Negocios verdes | C57: No | D57: 2018-2022 | E57: =IFERROR(MID(D57,6,4),"") -> 2022 | I57: =1/COUNTBLANK($H$57:$H$58) -> 0.5 | J57: =I57*$H$56 -> 0.25
A58: AMB-2-2 | B58: Vida útil del sitio de disposición final de residuos | C58: No | D58: 2018-2022 | E58: =IFERROR(MID(D58,6,4),"") -> 2022 | I58: =1/COUNTBLANK($H$57:$H$58) -> 0.5 | J58: =I58*$H$56 -> 0.25
A59: FACTOR 2 | B59: CAPITAL HUMANO | E59: =IFERROR(MID(D59,6,4),"")
A60: PILAR 5: SALUD | E60: =IFERROR(MID(D60,6,4),"") | F60: =F2 -> 0.076923077
A61: SAL-1 | B61: Acceso a salud | E61: =IFERROR(MID(D61,6,4),"") | G61: =$F$60/3 -> 0.025641026 | H61: =G61/$F$60 -> 0.33333333
A62: SAL-1-1 | B62: Cobertura de vacunación triple viral | C62: No | D62: 2017-2022 | E62: =IFERROR(MID(D62,6,4),"") -> 2022 | I62: =1/COUNTBLANK($H$62:$H$64) -> 0.33333333 | J62: =I62*$H$61 -> 0.11111111
A63: SAL-1-2 | B63: Cobertura de vacunación pentavalente (DTP) | C63: No | D63: 2017-2022 | E63: =IFERROR(MID(D63,6,4),"") -> 2022 | I63: =1/COUNTBLANK($H$62:$H$64) -> 0.33333333 | J63: =I63*$H$61 -> 0.11111111
A64: SAL-1-3 | B64: Controles prenatales | C64: No | D64: 2017-2022 | E64: =IFERROR(MID(D64,6,4),"") -> 2022 | I64: =1/COUNTBLANK($H$62:$H$64) -> 0.33333333 | J64: =I64*$H$61 -> 0.11111111
A65: SAL-2 | B65: Resultados en salud | E65: =IFERROR(MID(D65,6,4),"") | G65: =$F$60/3 -> 0.025641026 | H65: =G65/$F$60 -> 0.33333333
A66: SAL-2-1 | B66: Mortalidad infantil | C66: Sí | D66: 2018-2022 | E66: =IFERROR(MID(D66,6,4),"") -> 2022 | I66: =1/COUNTBLANK($H$66:$H$67) -> 0.5 | J66: =I66*$H$65 -> 0.16666667
A67: SAL-2-2 | B67: Mortalidad materna | C67: Sí | D67: 2018-2023 | E67: =IFERROR(MID(D67,6,4),"") -> 2023 | I67: =1/COUNTBLANK($H$66:$H$67) -> 0.5 | J67: =I67*$H$65 -> 0.16666667
A68: SAL-3 | B68: Capacidades en salud | E68: =IFERROR(MID(D68,6,4),"") | G68: =$F$60/3 -> 0.025641026 | H68: =G68/$F$60 -> 0.33333333
A69: SAL-3-1 | B69: Comunidad de la salud | C69: No | D69: 2018-2021 | E69: =IFERROR(MID(D69,6,4),"") -> 2021 | I69: =1/COUNTBLANK($H$69:$H$72) -> 0.25 | J69: =I69*$H$68 -> 0.083333333
A70: SAL-3-2 | B70: Médicos generales | C70: No | D70: 2018-2021 | E70: =IFERROR(MID(D70,6,4),"") -> 2021 | I70: =1/COUNTBLANK($H$69:$H$72) -> 0.25 | J70: =I70*$H$68 -> 0.083333333
A71: SAL-3-3 | B71: Médicos especialistas | C71: No | D71: 2018-2021 | E71: =IFERROR(MID(D71,6,4),"") -> 2021 | I71: =1/COUNTBLANK($H$69:$H$72) -> 0.25 | J71: =I71*$H$68 -> 0.083333333
A72: SAL-3-4 | B72: Camas generales y especializadas | C72: No | D72: 2018-2023 | E72: =IFERROR(MID(D72,6,4),"") -> 2023 | I72: =1/COUNTBLANK($H$69:$H$72) -> 0.25 | J72: =I72*$H$68 -> 0.083333333
A73: PILAR 6: EDUCACIÓN BÁSICA Y MEDIA | E73: =IFERROR(MID(D73,6,4),"") | F73: =F2 -> 0.076923077
A74: EDU-1 | B74: Cobertura en educación | E74: =IFERROR(MID(D74,6,4),"") | G74: =$F$73/2 -> 0.038461538 | H74: =G74/$F$73 -> 0.5
A75: EDU-1-1 | B75: Cobertura neta en preescolar | C75: No | D75: 2018-2022 | E75: =IFERROR(MID(D75,6,4),"") -> 2022 | I75: =1/COUNTBLANK($H$75:$H$79) -> 0.2 | J75: =I75*$H$74 -> 0.1
A76: EDU-1-2 | B76: Cobertura neta en educación primaria | C76: No | D76: 2018-2022 | E76: =IFERROR(MID(D76,6,4),"") -> 2022 | I76: =1/COUNTBLANK($H$75:$H$79) -> 0.2 | J76: =I76*$H$74 -> 0.1
A77: EDU-1-3 | B77: Cobertura neta en educación secundaria | C77: No | D77: 2018-2022 | E77: =IFERROR(MID(D77,6,4),"") -> 2022 | I77: =1/COUNTBLANK($H$75:$H$79) -> 0.2 | J77: =I77*$H$74 -> 0.1
A78: EDU-1-4 | B78: Cobertura neta en educación media | C78: No | D78: 2018-2022 | E78: =IFERROR(MID(D78,6,4),"") -> 2022 | I78: =1/COUNTBLANK($H$75:$H$79) -> 0.2 | J78: =I78*$H$74 -> 0.1
A79: EDU-1-5 | B79: Deserción escolar en educación básica y media | C79: Sí | D79: 2018-2022 | E79: =IFERROR(MID(D79,6,4),"") -> 2022 | I79: =1/COUNTBLANK($H$75:$H$79) -> 0.2 | J79: =I79*$H$74 -> 0.1
A80: EDU-2 | B80: Calidad en educación | E80: =IFERROR(MID(D80,6,4),"") | G80: =$F$73/2 -> 0.038461538 | H80: =G80/$F$73 -> 0.5
A81: EDU-2-1 | B81: Puntaje pruebas Saber 11 | C81: No | D81: 2019-2023 | E81: =IFERROR(MID(D81,6,4),"") -> 2023 | I81: =1/COUNTBLANK($H$81:$H$84) -> 0.25 | J81: =I81*$H$80 -> 0.125
A82: EDU-2-2 | B82: Puntaje pruebas Saber 11 en colegios oficiales | C82: No | D82: 2019-2023 | E82: =IFERROR(MID(D82,6,4),"") -> 2023 | I82: =1/COUNTBLANK($H$81:$H$84) -> 0.25 | J82: =I82*$H$80 -> 0.125
A83: EDU-2-3 | B83: Docentes de colegios oficiales con posgrado | C83: No | D83: 2018-2022 | E83: =IFERROR(MID(D83,6,4),"") -> 2022 | I83: =1/COUNTBLANK($H$81:$H$84) -> 0.25 | J83: =I83*$H$80 -> 0.125
A84: EDU-2-4 | B84: Relación estudiantes-docentes | C84: Sí | D84: 2018-2022 | E84: =IFERROR(MID(D84,6,4),"") -> 2022 | I84: =1/COUNTBLANK($H$81:$H$84) -> 0.25 | J84: =I84*$H$80 -> 0.125
A85: PILAR 7: EDUCACIÓN SUPERIOR Y FORMACIÓN PARA EL TRABAJO | E85: =IFERROR(MID(D85,6,4),"") | F85: =F2 -> 0.076923077
A86: EDS-1 | B86: Cobertura en educación superior | E86: =IFERROR(MID(D86,6,4),"") | G86: =$F$85/3 -> 0.025641026 | H86: =G86/$F$85 -> 0.33333333
A87: EDS-1-1 | B87: Cobertura bruta en formación universitaria | C87: No | D87: 2018-2023 | E87: =IFERROR(MID(D87,6,4),"") -> 2023 | I87: =1/COUNTBLANK($H$87:$H$89) -> 0.33333333 | J87: =I87*$H$86 -> 0.11111111
A88: EDS-1-2 | B88: Graduados en posgrado | C88: No | D88: 2018-2023 | E88: =IFERROR(MID(D88,6,4),"") -> 2023 | I88: =1/COUNTBLANK($H$87:$H$89) -> 0.33333333 | J88: =I88*$H$86 -> 0.11111111
A89: EDS-1-3 | B89: Cobertura bruta en formación técnica y tecnológica | C89: No | D89: 2018-2023 | E89: =IFERROR(MID(D89,6,4),"") -> 2023 | I89: =1/COUNTBLANK($H$87:$H$89) -> 0.33333333 | J89: =I89*$H$86 -> 0.11111111
A90: EDS-2 | B90: Calidad en educación superior | E90: =IFERROR(MID(D90,6,4),"") | G90: =$F$85/3 -> 0.025641026 | H90: =G90/$F$85 -> 0.33333333
A91: EDS-2-1 | B91: Puntaje pruebas Saber Pro | C91: No | D91: 2018-2022 | E91: =IFERROR(MID(D91,6,4),"") -> 2022 | I91: =1/COUNTBLANK($H$91:$H$94) -> 0.25 | J91: =I91*$H$90 -> 0.083333333
A92: EDS-2-2 | B92: Calidad de docentes de educación superior | C92: No | D92: 2018-2023 | E92: =IFERROR(MID(D92,6,4),"") -> 2023 | I92: =1/COUNTBLANK($H$91:$H$94) -> 0.25 | J92: =I92*$H$90 -> 0.083333333
A93: EDS-2-3 | B93: Cobertura instituciones de educación superior con acreditación de alta calidad | C93: No | D93: 2018-2023 | E93: =IFERROR(MID(D93,6,4),"") -> 2023 | I93: =1/COUNTBLANK($H$91:$H$94) -> 0.25 | J93: =I93*$H$90 -> 0.083333333
A94: EDS-2-4 | B94: Dominio de inglés | C94: No | D94: 2018-2022 | E94: =IFERROR(MID(D94,6,4),"") -> 2022 | I94: =1/COUNTBLANK($H$91:$H$94) -> 0.25 | J94: =I94*$H$90 -> 0.083333333
A95: EDS-3 | B95: Educación para el trabajo y el desarrollo humano | E95: =IFERROR(MID(D95,6,4),"") | G95: =$F$85/3 -> 0.025641026 | H95: =G95/$F$85 -> 0.33333333
A96: EDS-3-1 | B96: Proporción de estudiantes en IETDH matriculados en instituciones certificadas | C96: No | D96: 2018-2023 | E96: =IFERROR(MID(D96,6,4),"") -> 2023 | I96: =1/COUNTBLANK($H$96:$H$97) -> 0.5 | J96: =I96*$H$95 -> 0.16666667
A97: EDS-3-2 | B97: Egresados del SENA vinculados al mercado laboral | C97: No | D97: 2019-2023 | E97: =IFERROR(MID(D97,6,4),"") -> 2023 | I97: =1/COUNTBLANK($H$96:$H$97) -> 0.5 | J97: =I97*$H$95 -> 0.16666667
A98: FACTOR 3 | B98: EFICIENCIA DE LOS MERCADOS | E98: =IFERROR(MID(D98,6,4),"")
A99: PILAR 8: ENTORNO PARA LOS NEGOCIOS | E99: =IFERROR(MID(D99,6,4),"") | F99: =F2 -> 0.076923077
A100: NEG-1 | B100: Trámites y competencia | E100: =IFERROR(MID(D100,6,4),"") | G100: =$F$99/2 -> 0.038461538 | H100: =G100/$F$85 -> 0.5
...

Sheet INFO_MUN
A1: COD_MUN | B1: CATEGORIA_NUMB | C1: CATEGORIA | D1: POBLACION | E1: ACTIVIDAD_ECONOMICA_PRINCIPAL | F1: PARTICIPACION EN EL PIB

Sheet Valor_normalizado
A1: Ciudad o AM | B1: Año | C1: TIC-1-1 | D1: TIC-1-2 | E1: TIC-1-3 | F1: TIC-1-4 | G1: TIC-1 | H1: TIC-2-1 | I1: TIC-2-2 | J1: TIC-2-3 | K1: TIC-2 | L1: TIC | M1: INN-1-1 | N1: INN-1-2 | O1: INN-1-3 | P1: INN-1-4 | Q1: INN-1-5 | R1: INN-1 | S1: INN-2-1 | T1: INN-2-2 | U1: INN-2-3 | V1: INN-2-4 | W1: INN-2 | X1: INN | Y1: Puntaje general
A2: Bogotá D.C. | B2: 2019 | C2: 8.5442823 | D2: 0.64984122 | E2: 9.5688935 | F2: 9.513601 | G2: 7.0691545 | H2: 4.008368 | I2: 4.8570681 | J2: 8.1711281 | K2: 5.6788547 | L2: 6.3740046 | M2: 3.3282791 | N2: 6.5458141 | O2: 4.7275863 | P2: 9.5964126 | Q2: 2.6636441 | R2: 5.3723472 | S2: 4.7379928 | T2: 6.373097 | U2: 5.4843964 | V2: 7.9192384 | W2: 6.1286811 | X2: 5.7505142 | Y2: 7.0969839
A3: Armenia | B3: 2019 | C3: 8.3033593 | D3: 0.45331118 | E3: 5.5787721 | F3: 6.7736506 | G3: 5.2772733 | H3: 4.1631656 | I3: 3.509322 | J3: 3.5764935 | K3: 3.7496604 | L3: 4.5134668 | M3: 1.3058107 | N3: 0 | O3: 3.4561929 | P3: 7.2197309 | Q3: 3.5420799 | R3: 3.1047629 | S3: 3.2594324 | T3: 4.7066517 | U3: 2.4159861 | V3: 1.7910709 | W3: 3.0432853 | X3: 3.0740241 | Y3: 5.19449
A4: Medellín AM | B4: 2019 | C4: 8.1376696 | D4: 0.58823173 | E4: 7.0745346 | F4: 7.4152837 | G4: 5.8039299 | H4: 3.5794113 | I4: 3.5495899 | J4: 6.9062814 | K4: 4.6784275 | L4: 5.2411787 | M4: 3.5431715 | N4: 4.9254897 | O4: 4.8658925 | P4: 5.7399103 | Q4: 2.7684897 | R4: 4.3685907 | S4: 4.5582072 | T4: 3.3209661 | U4: 7.5559475 | V4: 7.4761023 | W4: 5.7278058 | X4: 5.0481983 | Y4: 6.3363828
A5: Tunja | B5: 2019 | C5: 8.0794028 | D5: 0.40860287 | E5: 6.6634328 | F5: 7.1261968 | G5: 5.5694088 | H5: 8.3119329 | I5: 7.9359201 | J5: 9.5455888 | K5: 8.5978139 | L5: 7.0836114 | M5: 4.7873108 | N5: 10 | O5: 10 | P5: 5.7399103 | Q5: 2.4397846 | R5: 6.5934012 | S5: 0.92941339 | T5: 4.0262456 | U5: 0.82668987 | V5: 1.7391961 | W5: 1.8803862 | X5: 4.2368937 | Y5: 6.199191
A6: Pereira AM | B6: 2019 | C6: 7.3023304 | D6: 0.48920088 | E6: 7.3163081 | F6: 8.9353571 | G6: 6.0107991 | H6: 5.4766318 | I6: 5.2141537 | J6: 4.3842699 | K6: 5.0250185 | L6: 5.5179088 | M6: 1.7780031 | N6: 1.2162941 | O6: 2.2555203 | P6: 5.9192825 | Q6: 4.2774157 | R6: 3.0893031 | S6: 3.1516738 | T6: 3.9008977 | U6: 2.6030966 | V6: 3.1527824 | W6: 3.2021126 | X6: 3.1457079 | Y6: 5.7723183
A7: Bucaramanga AM | B7: 2019 | C7: 7.1779128 | D7: 0.49169784 | E7: 7.0919271 | F7: 7.9844421 | G7: 5.686495 | H7: 3.8020869 | I7: 4.3338245 | J7: 7.8789222 | K7: 5.3382779 | L7: 5.5123864 | M7: 2.7898452 | N7: 3.5979422 | O7: 4.1967489 | P7: 6.0986547 | Q7: 3.2020402 | R7: 3.9770462 | S7: 2.2641633 | T7: 2.3078637 | U7: 2.1323821 | V7: 2.5555855 | W7: 2.3149986 | X7: 3.1460224 | Y7: 5.8728913
A8: Cali AM | B8: 2019 | C8: 7.1138579 | D8: 0.53030973 | E8: 7.23106 | F8: 8.592928 | G8: 5.8670389 | H8: 2.4776346 | I8: 2.8931955 | J8: 5.3908881 | K8: 3.5872394 | L8: 4.7271391 | M8: 3.0895781 | N8: 2.411988 | O8: 3.4681709 | P8: 6.7713004 | Q8: 3.2558799 | R8: 3.7993834 | S8: 2.6785579 | T8: 3.5703354 | U8: 1.89379 | V8: 4.7573384 | W8: 3.2250054 | X8: 3.5121944 | Y8: 6.0173282
A9: Neiva | B9: 2019 | C9: 7.0987445 | D9: 0.34862066 | E9: 5.4600287 | F9: 6.8555359 | G9: 4.9407324 | H9: 3.3449083 | I9: 3.5246472 | J9: 3.3398334 | K9: 3.4031297 | L9: 4.171931 | M9: 1.2326945 | N9: 0 | O9: 1.8882384 | P9: 7.2197309 | Q9: 2.3080193 | R9: 2.5297366 | S9: 2.6923113 | T9: 0 | U9: 0 | V9: 1.3194966 | W9: 1.002952 | X9: 1.7663443 | Y9: 5.0701436
A10: Ibagué | B10: 2019 | C10: 6.996946 | D10: 0.44074085 | E10: 5.9627141 | F10: 7.6113844 | G10: 5.2529463 | H10: 3.8098259 | I10: 6.7486452 | J10: 5.4869113 | K10: 5.3484608 | L10: 5.3007036 | M10: 1.1437374 | N10: 0 | O10: 2.4421457 | P10: 7.3542601 | Q10: 3.5279116 | R10: 2.8936109 | S10: 0.90837136 | T10: 1.311697 | U10: 2.154596 | V10: 1.7762674 | W10: 1.5377329 | X10: 2.2156719 | Y10: 5.2374751
A11: Pasto | B11: 2019 | C11: 6.6202918 | D11: 0.39744649 | E11: 5.7563657 | F11: 6.2261054 | G11: 4.7500523 | H11: 3.4141585 | I11: 4.0217836 | J11: 3.8536312 | K11: 3.7631911 | L11: 4.2566217 | M11: 0.56060259 | N11: 2.2051037 | O11: 3.721162 | P11: 2.9596413 | Q11: 2.71465 | R11: 2.4322319 | S11: 0 | T11: 0 | U11: 0 | V11: 0.69099927 | W11: 0.17274982 | X11: 1.3024909 | Y11: 5.075312
A12: Manizales AM | B12: 2019 | C12: 6.3544402 | D12: 0.42707313 | E12: 7.0595178 | F12: 7.3179389 | G12: 5.2897425 | H12: 4.5849509 | I12: 6.0327542 | J12: 10 | K12: 6.8725684 | L12: 6.0811554 | M12: 6.5104933 | N12: 7.8128289 | O12: 6.390936 | P12: 4.3497758 | Q12: 3.1864551 | R12: 5.6500978 | S12: 2.8920976 | T12: 4.8722529 | U12: 1.4291379 | V12: 3.5220529 | W12: 3.1788853 | X12: 4.4144916 | Y12: 5.7938513
A13: Popayán | B13: 2019 | C13: 6.0943332 | D13: 0.4336121 | E13: 6.0244227 | F13: 6.5637441 | G13: 4.779028 | H13: 6.7955678 | I13: 5.5734261 | J13: 5.170478 | K13: 5.8464907 | L13: 5.3127593 | M13: 1.9045628 | N13: 0 | O13: 3.7635783 | P13: 10 | Q13: 2.9540946 | R13: 3.7244471 | S13: 3.025258 | T13: 0 | U13: 0.44848184 | V13: 1.2804905 | W13: 1.1885576 | X13: 2.4565024 | Y13: 5.4864608
... A193: Leticia | B193: 2024 | C193: 0.32914829 | D193: 0.19056139 | E193: 2.2027723 | F193: 1.3036595 | G193: 1.0065354 | H193: 0.43126688 | I193: 0.056227109 | J193: 2.2159192 | K193: 0.90113772 | L193: 0.95383653 | M193: 4.1404781 | N193: 0 | O193: 3.3221961 | P193: 4.0807175 | Q193: 10 | R193: 4.3086783 | S193: 0 | T193: 0 | U193: 0 | V193: 0.22007991 | W193: 0.055019977 | X193: 2.1818492 | Y193: 3.1063371

Sheet Valor_original (winzo-imp)
A1: Ciudad o AM | B1: Año | C1: TIC-1-1 | D1: TIC-1-2 | E1: TIC-1-3 | F1: TIC-1-4 | G1: TIC-2-1 | H1: TIC-2-2 | I1: TIC-2-3 | J1: INN-1-1 | K1: INN-1-2 | L1: INN-1-3 | M1: INN-1-4 | N1: INN-1-5 | O1: INN-2-1 | P1: INN-2-2 | Q1: INN-2-3 | R1: INN-2-4
A2: Arauca | B2: 2019 | C2: 7.99 | D2: 5.5890582 | E2: 22.427528 | F2: 68.294633 | G2: 1312.722 | H2: 368.053 | I2: 0.5 | J2: 0 | K2: 0 | L2: 11.68429 | M2: 0 | N2: 0 | O2: 0 | P2: 0 | Q2: 0 | R2: 93.474324
A3: Armenia | B3: 2019 | C3: 24.6 | D3: 8.7742677 | E3: 41.797892 | F3: 74.634168 | G3: 10558.9 | H3: 1157.081 | I3: 1.2105 | J3: 2.3712095 | K3: 0 | L3: 430.20514 | M3: 1.61 | N3: 25 | O3: 20.324652 | P3: 13.549768 | Q3: 16.93721 | R3: 752.01214
A4: Barranquilla AM | B4: 2019 | C4: 13.838173 | D4: 11.521319 | E4: 44.982809 | F4: 77.643446 | G4: 7585.936 | H4: 907.957 | I4: 2.2895 | J4: 5.5238914 | K4: 0.60762805 | L4: 475.60705 | M4: 1.63 | N4: 21.6 | O4: 11.047783 | P4: 3.866724 | Q4: 3.3143348 | R4: 1083.7875
A5: Bogotá D.C. | B5: 2019 | C5: 25.31 | D5: 12.107394 | E5: 63.897082 | F5: 87.173928 | G5: 10166.292 | H5: 1601.455 | I5: 2.7656 | J5: 6.043791 | K5: 1.5109478 | L5: 588.46019 | M5: 2.14 | N5: 18.8 | O5: 29.544425 | P5: 18.347223 | Q5: 38.448224 | R5: 3325.0294
A6: Bucaramanga AM | B6: 2019 | C6: 21.283309 | D6: 9.425301 | E6: 50.178464 | F6: 80.175522 | G6: 9643.108 | H6: 1428.933 | I6: 2.6667 | J6: 5.0660539 | K6: 0.83050063 | L6: 522.3849 | M6: 1.36 | N6: 22.6 | O6: 14.118511 | P6: 6.6440051 | Q6: 14.949011 | R6: 1073.0068
A7: Cali AM | B7: 2019 | C7: 21.094539 | D7: 10.080154 | E7: 50.949048 | F7: 82.960341 | G7: 6283.943 | H7: 953.934 | I7: 1.8246 | J7: 5.610336 | K7: 0.5567509 | L7: 431.69609 | M7: 1.51 | N7: 22.98 | O7: 16.702527 | P7: 10.278478 | Q7: 13.276368 | R7: 1997.4509
A8: Cartagena | B8: 2019 | C8: 15.48 | D8: 9.9948442 | E8: 30.987781 | F8: 66.898285 | G8: 4942.26 | H8: 941.383 | I8: 1.5897 | J8: 3.9052665 | K8: 0.51385085 | L8: 350.44628 | M8: 0 | N8: 23.88 | O8: 2.0554034 | P8: 1.0277017 | Q8: 8.2216136 | R8: 612.51021
A9: Cúcuta AM | B9: 2019 | C9: 13.068041 | D9: 8.837763 | E9: 39.469189 | F9: 74.579021 | G9: 5727.211 | H9: 952.619 | I9: 1.7391 | J9: 0.86071668 | K9: 0.32276875 | L9: 145.24594 | M9: 1.12 | N9: 29.79 | O9: 2.1517917 | P9: 5.3794792 | Q9: 4.3035834 | R9: 568.07301
A10: Florencia | B10: 2019 | C10: 11.36 | D10: 6.1853125 | E10: 32.606844 | F10: 67.634542 | G10: 4545.18 | H10: 513.068 | I10: 2.4286 | J10: 0 | K10: 0 | L10: 279.18691 | M10: 1.4 | N10: 15.16 | O10: 5.9401471 | P10: 0 | Q10: 0 | R10: 160.38397
A11: Ibagué | B11: 2019 | C11: 20.75 | D11: 8.5610762 | E11: 43.924345 | F11: 78.468172 | G11: 9662.736 | H11: 2225.139 | I11: 1.8571 | J11: 2.076902 | K11: 0 | L11: 303.98293 | M11: 1.64 | N11: 24.9 | O11: 5.6642782 | P11: 3.7761855 | Q11: 15.104742 | R11: 745.79663
A12: Inírida | B12: 2019 | C12: 2.72 | D12: 1.1109908 | E12: 22.482312 | F12: 49.375557 | G12: 3212.496 | H12: 265.252 | I12: 2.6667 | J12: 0 | K12: 0 | L12: 0 | M12: 0 | N12: 0 | O12: 0 | P12: 0 | Q12: 0 | R12: 0
A13: Leticia | B13: 2019 | C13: 1.78 | D13: 1.7913721 | E13: 16.252225 | F13: 44.746427 | G13: 691.81 | H13: 66.949 | I13: 0.5556 | J13: 8.3084081 | K13: 0 | L13: 373.87836 | M13: 1.22 | N13: 63.64 | O13: 0 | P13: 0 | Q13: 0 | R13: 415.42041
... A193: Yopal | B193: 2024 | C193: 20.3 | D193: 113.29626 | E193: 27.5 | F193: 83 | G193: 5910.632 | H193: 998.459 | I193: 0.7222 | J193: 0.53204507 | K193: 0 | L193: 111.72947 | M193: 0 | N193: 0 | O193: 0 | P193: 5.2319589 | Q193: 57.551548 | R193: 690.61857

Sheet Valor_ranking
A1: Ciudad o AM | B1: Año | C1: =Valor_normalizado!C1 -> TIC-1-1 | D1: =Valor_normalizado!D1 -> TIC-1-2 | E1: =Valor_normalizado!E1 -> TIC-1-3 | F1: =Valor_normalizado!F1 -> TIC-1-4 | G1: =Valor_normalizado!G1 -> TIC-1 | H1: =Valor_normalizado!H1 -> TIC-2-1 | I1: =Valor_normalizado!I1 -> TIC-2-2 | J1: =Valor_normalizado!J1 -> TIC-2-3 | ... Y1: =Valor_normalizado!Y1 -> Puntaje general
A2: Arauca | B2: 2019 | C2: =IF(Valor_normalizado!C2=0,32,IFERROR(RANK(Valor_normalizado!C2,Valor_normalizado!C$2:C$33,0),"NA")) -> 1 | D2: =IF(Valor_normalizado!D2=0,32,IFERROR(RANK(Valor_normalizado!D2,Valor_normalizado!D$2:D$33,0),"NA")) -> 1 | E2: =IF(Valor_normalizado!E2=0,32,IFERROR(RANK(Valor_normalizado!E2,Valor_normalizado!E$2:E$33,0),"NA")) -> 1 | F2: =IF(Valor_normalizado!F2=0,32,IFERROR(RANK(Valor_normalizado!F2,Valor_normalizado!F$2:F$33,0),"NA")) -> 1 | G2: =IF(Valor_normalizado!G2=0,32,IFERROR(RANK(Valor_normalizado!G2,Valor_normalizado!G$2:G$33,0),"NA")) -> 1 | H2: =IF(Valor_normalizado!H2=0,32,IFERROR(RANK(Valor_normalizado!H2,Valor_normalizado!H$2:H$33,0),"NA")) -> 6 | I2: =IF(Valor_normalizado!I2=0,32,IFERROR(RANK(Valor_normalizado!I2,Valor_normalizado!I$2:I$33,0),"NA")) -> 6 | J2: =IF(Valor_normalizado!J2=0,32,IFERROR(RANK(Valor_normalizado!J2,Valor_normalizado!J$2:J$33,0),"NA")) -> 3 | ... Y2: =IF(Valor_normalizado!Y2=0,32,IFERROR(RANK(Valor_normalizado!Y2,Valor_normalizado!Y$2:Y$33,0),"NA")) -> 1
A3: Armenia | B3: 2019 | C3: =IF(Valor_normalizado!C3=0,32,IFERROR(RANK(Valor_normalizado!C3,Valor_normalizado!C$2:C$33,0),"NA")) -> 2 | D3: =IF(Valor_normalizado!D3=0,32,IFERROR(RANK(Valor_normalizado!D3,Valor_normalizado!D$2:D$33,0),"NA")) -> 12 | E3: =IF(Valor_normalizado!E3=0,32,IFERROR(RANK(Valor_normalizado!E3,Valor_normalizado!E$2:E$33,0),"NA")) -> 14 | F3: =IF(Valor_normalizado!F3=0,32,IFERROR(RANK(Valor_normalizado!F3,Valor_normalizado!F$2:F$33,0),"NA")) -> 14 | G3: =IF(Valor_normalizado!G3=0,32,IFERROR(RANK(Valor_normalizado!G3,Valor_normalizado!G$2:G$33,0),"NA")) -> 8 | H3: =IF(Valor_normalizado!H3=0,32,IFERROR(RANK(Valor_normalizado!H3,Valor_normalizado!H$2:H$33,0),"NA")) -> 5 | I3: =IF(Valor_normalizado!I3=0,32,IFERROR(RANK(Valor_normalizado!I3,Valor_normalizado!I$2:I$33,0),"NA")) -> 12 | J3: =IF(Valor_normalizado!J3=0,32,IFERROR(RANK(Valor_normalizado!J3,Valor_normalizado!J$2:J$33,0),"NA")) -> 21 | ... Y3: =IF(Valor_normalizado!Y3=0,32,IFERROR(RANK(Valor_normalizado!Y3,Valor_normalizado!Y$2:Y$33,0),"NA")) -> 12
A4: Barranquilla AM | B4: 2019 | C4: =IF(Valor_normalizado!C4=0,32,IFERROR(RANK(Valor_normalizado!C4,Valor_normalizado!C$2:C$33,0),"NA")) -> 3 | D4: =IF(Valor_normalizado!D4=0,32,IFERROR(RANK(Valor_normalizado!D4,Valor_normalizado!D$2:D$33,0),"NA")) -> 3 | E4: =IF(Valor_normalizado!E4=0,32,IFERROR(RANK(Valor_normalizado!E4,Valor_normalizado!E$2:E$33,0),"NA")) -> 5 | F4: =IF(Valor_normalizado!F4=0,32,IFERROR(RANK(Valor_normalizado!F4,Valor_normalizado!F$2:F$33,0),"NA")) -> 8 | G4: =IF(Valor_normalizado!G4=0,32,IFERROR(RANK(Valor_normalizado!G4,Valor_normalizado!G$2:G$33,0),"NA")) -> 4 | H4: =IF(Valor_normalizado!H4=0,32,IFERROR(RANK(Valor_normalizado!H4,Valor_normalizado!H$2:H$33,0),"NA")) -> 9 | I4: =IF(Valor_normalizado!I4=0,32,IFERROR(RANK(Valor_normalizado!I4,Valor_normalizado!I$2:I$33,0),"NA")) -> 10 | J4: =IF(Valor_normalizado!J4=0,32,IFERROR(RANK(Valor_normalizado!J4,Valor_normalizado!J$2:J$33,0),"NA")) -> 7 | ... Y4: =IF(Valor_normalizado!Y4=0,32,IFERROR(RANK(Valor_normalizado!Y4,Valor_normalizado!Y$2:Y$33,0),"NA")) -> 2
A5: Bogotá D.C. | B5: 2019 | C5: =IF(Valor_normalizado!C5=0,32,IFERROR(RANK(Valor_normalizado!C5,Valor_normalizado!C$2:C$33,0),"NA")) -> 4 | D5: =IF(Valor_normalizado!D5=0,32,IFERROR(RANK(Valor_normalizado!D5,Valor_normalizado!D$2:D$33,0),"NA")) -> 17 | E5: =IF(Valor_normalizado!E5=0,32,IFERROR(RANK(Valor_normalizado!E5,Valor_normalizado!E$2:E$33,0),"NA")) -> 7 | F5: =IF(Valor_normalizado!F5=0,32,IFERROR(RANK(Valor_normalizado!F5,Valor_normalizado!F$2:F$33,0),"NA")) -> 11 | G5: =IF(Valor_normalizado!G5=0,32,IFERROR(RANK(Valor_normalizado!G5,Valor_normalizado!G$2:G$33,0),"NA")) -> 6 | H5: =IF(Valor_normalizado!H5=0,32,IFERROR(RANK(Valor_normalizado!H5,Valor_normalizado!H$2:H$33,0),"NA")) -> 1 | I5: =IF(Valor_normalizado!I5=0,32,IFERROR(RANK(Valor_normalizado!I5,Valor_normalizado!I$2:I$33,0),"NA")) -> 1 | J5: =IF(Valor_normalizado!J5=0,32,IFERROR(RANK(Valor_normalizado!J5,Valor_normalizado!J$2:J$33,0),"NA")) -> 2 | ... Y5: =IF(Valor_normalizado!Y5=0,32,IFERROR(RANK(Valor_normalizado!Y5,Valor_normalizado!Y$2:Y$33,0),"NA")) -> 3
A6: Bucaramanga AM | B6: 2019 | C6: =IF(Valor_normalizado!C6=0,32,IFERROR(RANK(Valor_normalizado!C6,Valor_normalizado!C$2:C$33,0),"NA")) -> 5 | D6: =IF(Valor_normalizado!D6=0,32,IFERROR(RANK(Valor_normalizado!D6,Valor_normalizado!D$2:D$33,0),"NA")) -> 8 | E6: =IF(Valor_normalizado!E6=0,32,IFERROR(RANK(Valor_normalizado!E6,Valor_normalizado!E$2:E$33,0),"NA")) -> 2 | F6: =IF(Valor_normalizado!F6=0,32,IFERROR(RANK(Valor_normalizado!F6,Valor_normalizado!F$2:F$33,0),"NA")) -> 2 | G6: =IF(Valor_normalizado!G6=0,32,IFERROR(RANK(Valor_normalizado!G6,Valor_normalizado!G$2:G$33,0),"NA")) -> 2 | H6: =IF(Valor_normalizado!H6=0,32,IFERROR(RANK(Valor_normalizado!H6,Valor_normalizado!H$2:H$33,0),"NA")) -> 3 | I6: =IF(Valor_normalizado!I6=0,32,IFERROR(RANK(Valor_normalizado!I6,Valor_normalizado!I$2:I$33,0),"NA")) -> 5 | J6: =IF(Valor_normalizado!J6=0,32,IFERROR(RANK(Valor_normalizado!J6,Valor_normalizado!J$2:J$33,0),"NA")) -> 15 | ... Y6: =IF(Valor_normalizado!Y6=0,32,IFERROR(RANK(Valor_normalizado!Y6,Valor_normalizado!Y$2:Y$33,0),"NA")) -> 7
A7: Cali AM | B7: 2019 | C7: =IF(Valor_normalizado!C7=0,32,IFERROR(RANK(Valor_normalizado!C7,Valor_normalizado!C$2:C$33,0),"NA")) -> 6 | D7: =IF(Valor_normalizado!D7=0,32,IFERROR(RANK(Valor_normalizado!D7,Valor_normalizado!D$2:D$33,0),"NA")) -> 7 | E7: =IF(Valor_normalizado!E7=0,32,IFERROR(RANK(Valor_normalizado!E7,Valor_normalizado!E$2:E$33,0),"NA")) -> 4 | F7: =IF(Valor_normalizado!F7=0,32,IFERROR(RANK(Valor_normalizado!F7,Valor_normalizado!F$2:F$33,0),"NA")) -> 5 | G7: =IF(Valor_normalizado!G7=0,32,IFERROR(RANK(Valor_normalizado!G7,Valor_normalizado!G$2:G$33,0),"NA")) -> 5 | H7: =IF(Valor_normalizado!H7=0,32,IFERROR(RANK(Valor_normalizado!H7,Valor_normalizado!H$2:H$33,0),"NA")) -> 8 | I7: =IF(Valor_normalizado!I7=0,32,IFERROR(RANK(Valor_normalizado!I7,Valor_normalizado!I$2:I$33,0),"NA")) -> 7 | J7: =IF(Valor_normalizado!J7=0,32,IFERROR(RANK(Valor_normalizado!J7,Valor_normalizado!J$2:J$33,0),"NA")) -> 4 | ... Y7: =IF(Valor_normalizado!Y7=0,32,IFERROR(RANK(Valor_normalizado!Y7,Valor_normalizado!Y$2:Y$33,0),"NA")) -> 5
A8: Cartagena | B8: 2019 | C8: =IF(Valor_normalizado!C8=0,32,IFERROR(RANK(Valor_normalizado!C8,Valor_normalizado!C$2:C$33,0),"NA")) -> 7 | D8: =IF(Valor_normalizado!D8=0,32,IFERROR(RANK(Valor_normalizado!D8,Valor_normalizado!D$2:D$33,0),"NA")) -> 4 | E8: =IF(Valor_normalizado!E8=0,32,IFERROR(RANK(Valor_normalizado!E8,Valor_normalizado!E$2:E$33,0),"NA")) -> 3 | F8: =IF(Valor_normalizado!F8=0,32,IFERROR(RANK(Valor_normalizado!F8,Valor_normalizado!F$2:F$33,0),"NA")) -> 3 | G8: =IF(Valor_normalizado!G8=0,32,IFERROR(RANK(Valor_normalizado!G8,Valor_normalizado!G$2:G$33,0),"NA")) -> 3 | H8: =IF(Valor_normalizado!H8=0,32,IFERROR(RANK(Valor_normalizado!H8,Valor_normalizado!H$2:H$33,0),"NA")) -> 17 | I8: =IF(Valor_normalizado!I8=0,32,IFERROR(RANK(Valor_normalizado!I8,Valor_normalizado!I$2:I$33,0),"NA")) -> 13 | J8: =IF(Valor_normalizado!J8=0,32,IFERROR(RANK(Valor_normalizado!J8,Valor_normalizado!J$2:J$33,0),"NA")) -> 11 | ... Y8: =IF(Valor_normalizado!Y8=0,32,IFERROR(RANK(Valor_normalizado!Y8,Valor_normalizado!Y$2:Y$33,0),"NA")) -> 4
A9: Cúcuta AM | B9: 2019 | C9: =IF(Valor_normalizado!C9=0,32,IFERROR(RANK(Valor_normalizado!C9,Valor_normalizado!C$2:C$33,0),"NA")) -> 8 | D9: =IF(Valor_normalizado!D9=0,32,IFERROR(RANK(Valor_normalizado!D9,Valor_normalizado!D$2:D$33,0),"NA")) -> 22 | E9: =IF(Valor_normalizado!E9=0,32,IFERROR(RANK(Valor_normalizado!E9,Valor_normalizado!E$2:E$33,0),"NA")) -> 15 | F9: =IF(Valor_normalizado!F9=0,32,IFERROR(RANK(Valor_normalizado!F9,Valor_normalizado!F$2:F$33,0),"NA")) -> 13 | G9: =IF(Valor_normalizado!G9=0,32,IFERROR(RANK(Valor_normalizado!G9,Valor_normalizado!G$2:G$33,0),"NA")) -> 11 | H9: =IF(Valor_normalizado!H9=0,32,IFERROR(RANK(Valor_normalizado!H9,Valor_normalizado!H$2:H$33,0),"NA")) -> 11 | I9: =IF(Valor_normalizado!I9=0,32,IFERROR(RANK(Valor_normalizado!I9,Valor_normalizado!I$2:I$33,0),"NA")) -> 11 | J9: =IF(Valor_normalizado!J9=0,32,IFERROR(RANK(Valor_normalizado!J9,Valor_normalizado!J$2:J$33,0),"NA")) -> 23 | ... Y9: =IF(Valor_normalizado!Y9=0,32,IFERROR(RANK(Valor_normalizado!Y9,Valor_normalizado!Y$2:Y$33,0),"NA")) -> 14
A10: Florencia | B10: 2019 | C10: =IF(Valor_normalizado!C10=0,32,IFERROR(RANK(Valor_normalizado!C10,Valor_normalizado!C$2:C$33,0),"NA")) -> 9 | D10: =IF(Valor_normalizado!D10=0,32,IFERROR(RANK(Valor_normalizado!D10,Valor_normalizado!D$2:D$33,0),"NA")) -> 13 | E10: =IF(Valor_normalizado!E10=0,32,IFERROR(RANK(Valor_normalizado!E10,Valor_normalizado!E$2:E$33,0),"NA")) -> 10 | F10: =IF(Valor_normalizado!F10=0,32,IFERROR(RANK(Valor_normalizado!F10,Valor_normalizado!F$2:F$33,0),"NA")) -> 6 | G10: =IF(Valor_normalizado!G10=0,32,IFERROR(RANK(Valor_normalizado!G10,Valor_normalizado!G$2:G$33,0),"NA")) -> 9 | H10: =IF(Valor_normalizado!H10=0,32,IFERROR(RANK(Valor_normalizado!H10,Valor_normalizado!H$2:H$33,0),"NA")) -> 7 | I10: =IF(Valor_normalizado!I10=0,32,IFERROR(RANK(Valor_normalizado!I10,Valor_normalizado!I$2:I$33,0),"NA")) -> 2 | J10: =IF(Valor_normalizado!J10=0,32,IFERROR(RANK(Valor_normalizado!J10,Valor_normalizado!J$2:J$33,0),"NA")) -> 10 | ... Y10: =IF(Valor_normalizado!Y10=0,32,IFERROR(RANK(Valor_normalizado!Y10,Valor_normalizado!Y$2:Y$33,0),"NA")) -> 11
A11: Ibagué | B11: 2019 | C11: =IF(Valor_normalizado!C11=0,32,IFERROR(RANK(Valor_normalizado!C11,Valor_normalizado!C$2:C$33,0),"NA")) -> 10 | D11: =IF(Valor_normalizado!D11=0,32,IFERROR(RANK(Valor_normalizado!D11,Valor_normalizado!D$2:D$33,0),"NA")) -> 19 | E11: =IF(Valor_normalizado!E11=0,32,IFERROR(RANK(Valor_normalizado!E11,Valor_normalizado!E$2:E$33,0),"NA")) -> 12 | F11: =IF(Valor_normalizado!F11=0,32,IFERROR(RANK(Valor_normalizado!F11,Valor_normalizado!F$2:F$33,0),"NA")) -> 17 | G11: =IF(Valor_normalizado!G11=0,32,IFERROR(RANK(Valor_normalizado!G11,Valor_normalizado!G$2:G$33,0),"NA")) -> 13 | H11: =IF(Valor_normalizado!H11=0,32,IFERROR(RANK(Valor_normalizado!H11,Valor_normalizado!H$2:H$33,0),"NA")) -> 10 | I11: =IF(Valor_normalizado!I11=0,32,IFERROR(RANK(Valor_normalizado!I11,Valor_normalizado!I$2:I$33,0),"NA")) -> 8 | J11: =IF(Valor_normalizado!J11=0,32,IFERROR(RANK(Valor_normalizado!J11,Valor_normalizado!J$2:J$33,0),"NA")) -> 19 | ... Y11: =IF(Valor_normalizado!Y11=0,32,IFERROR(RANK(Valor_normalizado!Y11,Valor_normalizado!Y$2:Y$33,0),"NA")) -> 13
A12: Inírida | B12: 2019 | C12: =IF(Valor_normalizado!C12=0,32,IFERROR(RANK(Valor_normalizado!C12,Valor_normalizado!C$2:C$33,0),"NA")) -> 11 | D12: =IF(Valor_normalizado!D12=0,32,IFERROR(RANK(Valor_normalizado!D12,Valor_normalizado!D$2:D$33,0),"NA")) -> 16 | E12: =IF(Valor_normalizado!E12=0,32,IFERROR(RANK(Valor_normalizado!E12,Valor_normalizado!E$2:E$33,0),"NA")) -> 6 | F12: =IF(Valor_normalizado!F12=0,32,IFERROR(RANK(Valor_normalizado!F12,Valor_normalizado!F$2:F$33,0),"NA")) -> 10 | G12: =IF(Valor_normalizado!G12=0,32,IFERROR(RANK(Valor_normalizado!G12,Valor_normalizado!G$2:G$33,0),"NA")) -> 7 | H12: =IF(Valor_normalizado!H12=0,32,IFERROR(RANK(Valor_normalizado!H12,Valor_normalizado!H$2:H$33,0),"NA")) -> 4 | I12: =IF(Valor_normalizado!I12=0,32,IFERROR(RANK(Valor_normalizado!I12,Valor_normalizado!I$2:I$33,0),"NA")) -> 3 | J12: =IF(Valor_normalizado!J12=0,32,IFERROR(RANK(Valor_normalizado!J12,Valor_normalizado!J$2:J$33,0),"NA")) -> 1 | ... Y12: =IF(Valor_normalizado!Y12=0,32,IFERROR(RANK(Valor_normalizado!Y12,Valor_normalizado!Y$2:Y$33,0),"NA")) -> 6
A13: Leticia | B13: 2019 | C13: =IF(Valor_normalizado!C13=0,32,IFERROR(RANK(Valor_normalizado!C13,Valor_normalizado!C$2:C$33,0),"NA")) -> 12 | D13: =IF(Valor_normalizado!D13=0,32,IFERROR(RANK(Valor_normalizado!D13,Valor_normalizado!D$2:D$33,0),"NA")) -> 15 | E13: =IF(Valor_normalizado!E13=0,32,IFERROR(RANK(Valor_normalizado!E13,Valor_normalizado!E$2:E$33,0),"NA")) -> 9 | F13: =IF(Valor_normalizado!F13=0,32,IFERROR(RANK(Valor_normalizado!F13,Valor_normalizado!F$2:F$33,0),"NA")) -> 16 | G13: =IF(Valor_normalizado!G13=0,32,IFERROR(RANK(Valor_normalizado!G13,Valor_normalizado!G$2:G$33,0),"NA")) -> 12 | H13: =IF(Valor_normalizado!H13=0,32,IFERROR(RANK(Valor_normalizado!H13,Valor_normalizado!H$2:H$33,0),"NA")) -> 2 | I13: =IF(Valor_normalizado!I13=0,32,IFERROR(RANK(Valor_normalizado!I13,Valor_normalizado!I$2:I$33,0),"NA")) -> 4 | J13: =IF(Valor_normalizado!J13=0,32,IFERROR(RANK(Valor_normalizado!J13,Valor_normalizado!J$2:J$33,0),"NA")) -> 12 | ... Y13: =IF(Valor_normalizado!Y13=0,32,IFERROR(RANK(Valor_normalizado!Y13,Valor_normalizado!Y$2:Y$33,0),"NA")) -> 9
... A33: Yopal | B33: 2019 | C33: =IF(Valor_normalizado!C33=0,32,IFERROR(RANK(Valor_normalizado!C33,Valor_normalizado!C$2:C$33,0),"NA")) -> 32 | D33: =IF(Valor_normalizado!D33=0,32,IFERROR(RANK(Valor_normalizado!D33,Valor_normalizado!D$2:D$33,0),"NA")) -> 28 | E33: =IF(Valor_normalizado!E33=0,32,IFERROR(RANK(Valor_normalizado!E33,Valor_normalizado!E$2:E$33,0),"NA")) -> 24 | F33: =IF(Valor_normalizado!F33=0,32,IFERROR(RANK(Valor_normalizado!F33,Valor_normalizado!F$2:F$33,0),"NA")) -> 32 | G33: =IF(Valor_normalizado!G33=0,32,IFERROR(RANK(Valor_normalizado!G33,Valor_normalizado!G$2:G$33,0),"NA")) -> 31 | H33: =IF(Valor_normalizado!H33=0,32,IFERROR(RANK(Valor_normalizado!H33,Valor_normalizado!H$2:H$33,0),"NA")) -> 32 | I33: =IF(Valor_normalizado!I33=0,32,IFERROR(RANK(Valor_normalizado!I33,Valor_normalizado!I$2:I$33,0),"NA")) -> 32 | J33: =IF(Valor_normalizado!J33=0,32,IFERROR(RANK(Valor_normalizado!J33,Valor_normalizado!J$2:J$33,0),"NA")) -> 32 | ... Y33: =IF(Valor_normalizado!Y33=0,32,IFERROR(RANK(Valor_normalizado!Y33,Valor_normalizado!Y$2:Y$33,0),"NA")) -> 32
A34: Arauca | B34: 2020 | C34: =IF(Valor_normalizado!C34=0,32,IFERROR(RANK(Valor_normalizado!C34,Valor_normalizado!C$34:C$65,0),"NA")) -> 25 | D34: =IF(Valor_normalizado!D34=0,32,IFERROR(RANK(Valor_normalizado!D34,Valor_normalizado!D$34:D$65,0),"NA")) -> 25 | E34: =IF(Valor_normalizado!E34=0,32,IFERROR(RANK(Valor_normalizado!E34,Valor_normalizado!E$34:E$65,0),"NA")) -> 30 | F34: =IF(Valor_normalizado!F34=0,32,IFERROR(RANK(Valor_normalizado!F34,Valor_normalizado!F$34:F$65,0),"NA")) -> 20 | G34: =IF(Valor_normalizado!G34=0,32,IFERROR(RANK(Valor_normalizado!G34,Valor_normalizado!G$34:G$65,0),"NA")) -> 27 | H34: =IF(Valor_normalizado!H34=0,32,IFERROR(RANK(Valor_normalizado!H34,Valor_normalizado!H$34:H$65,0),"NA")) -> 30 | I34: =IF(Valor_normalizado!I34=0,32,IFERROR(RANK(Valor_normalizado!I34,Valor_normalizado!I$34:I$65,0),"NA")) -> 26 | J34: =IF(Valor_normalizado!J34=0,32,IFERROR(RANK(Valor_normalizado!J34,Valor_normalizado!J$34:J$65,0),"NA")) -> 31 | ... Y34: =IF(Valor_normalizado!Y34=0,32,IFERROR(RANK(Valor_normalizado!Y34,Valor_normalizado!Y$34:Y$65,0),"NA")) -> 27
A35: Armenia | B35: 2020 | C35: =IF(Valor_normalizado!C35=0,32,IFERROR(RANK(Valor_normalizado!C35,Valor_normalizado!C$34:C$65,0),"NA")) -> 2 | D35: =IF(Valor_normalizado!D35=0,32,IFERROR(RANK(Valor_normalizado!D35,Valor_normalizado!D$34:D$65,0),"NA")) -> 20 | E35: =IF(Valor_normalizado!E35=0,32,IFERROR(RANK(Valor_normalizado!E35,Valor_normalizado!E$34:E$65,0),"NA")) -> 14 | F35: =IF(Valor_normalizado!F35=0,32,IFERROR(RANK(Valor_normalizado!F35,Valor_normalizado!F$34:F$65,0),"NA")) -> 14 | G35: =IF(Valor_normalizado!G35=0,32,IFERROR(RANK(Valor_normalizado!G35,Valor_normalizado!G$34:G$65,0),"NA")) -> 9 | H35: =IF(Valor_normalizado!H35=0,32,IFERROR(RANK(Valor_normalizado!H35,Valor_normalizado!H$34:H$65,0),"NA")) -> 4 | I35: =IF(Valor_normalizado!I35=0,32,IFERROR(RANK(Valor_normalizado!I35,Valor_normalizado!I$34:I$65,0),"NA")) -> 10 | J35: =IF(Valor_normalizado!J35=0,32,IFERROR(RANK(Valor_normalizado!J35,Valor_normalizado!J$34:J$65,0),"NA")) -> 20 | ... Y35: =IF(Valor_normalizado!Y35=0,32,IFERROR(RANK(Valor_normalizado!Y35,Valor_normalizado!Y$34:Y$65,0),"NA")) -> 10
A36: Barranquilla AM | B36: 2020 | C36: =IF(Valor_normalizado!C36=0,32,IFERROR(RANK(Valor_normalizado!C36,Valor_normalizado!C$34:C$65,0),"NA")) -> 14 | D36: =IF(Valor_normalizado!D36=0,32,IFERROR(RANK(Valor_normalizado!D36,Valor_normalizado!D$34:D$65,0),"NA")) -> 3 | E36: =IF(Valor_normalizado!E36=0,32,IFERROR(RANK(Valor_normalizado!E36,Valor_normalizado!E$34:E$65,0),"NA")) -> 8 | F36: =IF(Valor_normalizado!F36=0,32,IFERROR(RANK(Valor_normalizado!F36,Valor_normalizado!F$34:F$65,0),"NA")) -> 7 | G36: =IF(Valor_normalizado!G36=0,32,IFERROR(RANK(Valor_normalizado!G36,Valor_normalizado!G$34:G$65,0),"NA")) -> 11 | H36: =IF(Valor_normalizado!H36=0,32,IFERROR(RANK(Valor_normalizado!H36,Valor_normalizado!H$34:H$65,0),"NA")) -> 13 | I36: =IF(Valor_normalizado!I36=0,32,IFERROR(RANK(Valor_normalizado!I36,Valor_normalizado!I$34:I$65,0),"NA")) -> 12 | J36: =IF(Valor_normalizado!J36=0,32,IFERROR(RANK(Valor_normalizado!J36,Valor_normalizado!J$34:J$65,0),"NA")) -> 6 | ... Y36: =IF(Valor_normalizado!Y36=0,32,IFERROR(RANK(Valor_normalizado!Y36,Valor_normalizado!Y$34:Y$65,0),"NA")) -> 8
A37: Bogotá D.C. | B37: 2020 | C37: =IF(Valor_normalizado!C37=0,32,IFERROR(RANK(Valor_normalizado!C37,Valor_normalizado!C$34:C$65,0),"NA")) -> 1 | D37: =IF(Valor_normalizado!D37=0,32,IFERROR(RANK(Valor_normalizado!D37,Valor_normalizado!D$34:D$65,0),"NA")) -> 1 | E37: =IF(Valor_normalizado!E37=0,32,IFERROR(RANK(Valor_normalizado!E37,Valor_normalizado!E$34:E$65,0),"NA")) -> 1 | F37: =IF(Valor_normalizado!F37=0,32,IFERROR(RANK(Valor_normalizado!F37,Valor_normalizado!F$34:F$65,0),"NA")) -> 1 | G37: =IF(Valor_normalizado!G37=0,32,IFERROR(RANK(Valor_normalizado!G37,Valor_normalizado!G$34:G$65,0),"NA")) -> 1 | H37: =IF(Valor_normalizado!H37=0,32,IFERROR(RANK(Valor_normalizado!H37,Valor_normalizado!H$34:H$65,0),"NA")) -> 6 | I37: =IF(Valor_normalizado!I37=0,32,IFERROR(RANK(Valor_normalizado!I37,Valor_normalizado!I$34:I$65,0),"NA")) -> 6 | J37: =IF(Valor_normalizado!J37=0,32,IFERROR(RANK(Valor_normalizado!J37,Valor_normalizado!J$34:J$65,0),"NA")) -> 1 | ... Y37: =IF(Valor_normalizado!Y37=0,32,IFERROR(RANK(Valor_normalizado!Y37,Valor_normalizado!Y$34:Y$65,0),"NA")) -> 1
A38: Bucaramanga AM | B38: 2020 | C38: =IF(Valor_normalizado!C38=0,32,IFERROR(RANK(Valor_normalizado!C38,Valor_normalizado!C$34:C$65,0),"NA")) -> 8 | D38: =IF(Valor_normalizado!D38=0,32,IFERROR(RANK(Valor_normalizado!D38,Valor_normalizado!D$34:D$65,0),"NA")) -> 8 | E38: =IF(Valor_normalizado!E38=0,32,IFERROR(RANK(Valor_normalizado!E38,Valor_normalizado!E$34:E$65,0),"NA")) -> 4 | F38: =IF(Valor_normalizado!F38=0,32,IFERROR(RANK(Valor_normalizado!F38,Valor_normalizado!F$34:F$65,0),"NA")) -> 5 | G38: =IF(Valor_normalizado!G38=0,32,IFERROR(RANK(Valor_normalizado!G38,Valor_normalizado!G$34:G$65,0),"NA")) -> 5 | H38: =IF(Valor_normalizado!H38=0,32,IFERROR(RANK(Valor_normalizado!H38,Valor_normalizado!H$34:H$65,0),"NA")) -> 7 | I38: =IF(Valor_normalizado!I38=0,32,IFERROR(RANK(Valor_normalizado!I38,Valor_normalizado!I$34:I$65,0),"NA")) -> 7 | J38: =IF(Valor_normalizado!J38=0,32,IFERROR(RANK(Valor_normalizado!J38,Valor_normalizado!J$34:J$65,0),"NA")) -> 4 | ... Y38: =IF(Valor_normalizado!Y38=0,32,IFERROR(RANK(Valor_normalizado!Y38,Valor_normalizado!Y$34:Y$65,0),"NA")) -> 5
A39: Cali AM | B39: 2020 | C39: =IF(Valor_normalizado!C39=0,32,IFERROR(RANK(Valor_normalizado!C39,Valor_normalizado!C$34:C$65,0),"NA")) -> 6 | D39: =IF(Valor_normalizado!D39=0,32,IFERROR(RANK(Valor_normalizado!D39,Valor_normalizado!D$34:D$65,0),"NA")) -> 4 | E39: =IF(Valor_normalizado!E39=0,32,IFERROR(RANK(Valor_normalizado!E39,Valor_normalizado!E$34:E$65,0),"NA")) -> 3 | F39: =IF(Valor_normalizado!F39=0,32,IFERROR(RANK(Valor_normalizado!F39,Valor_normalizado!F$34:F$65,0),"NA")) -> 3 | G39: =IF(Valor_normalizado!G39=0,32,IFERROR(RANK(Valor_normalizado!G39,Valor_normalizado!G$34:G$65,0),"NA")) -> 3 | H39: =IF(Valor_normalizado!H39=0,32,IFERROR(RANK(Valor_normalizado!H39,Valor_normalizado!H$34:H$65,0),"NA")) -> 17 | I39: =IF(Valor_normalizado!I39=0,32,IFERROR(RANK(Valor_normalizado!I39,Valor_normalizado!I$34:I$65,0),"NA")) -> 14 | J39: =IF(Valor_normalizado!J39=0,32,IFERROR(RANK(Valor_normalizado!J39,Valor_normalizado!J$34:J$65,0),"NA")) -> 11 | ... Y39: =IF(Valor_normalizado!Y39=0,32,IFERROR(RANK(Valor_normalizado!Y39,Valor_normalizado!Y$34:Y$65,0),"NA")) -> 4
A40: Cartagena | B40: 2020 | C40: =IF(Valor_normalizado!C40=0,32,IFERROR(RANK(Valor_normalizado!C40,Valor_normalizado!C$34:C$65,0),"NA")) -> 17 | D40: =IF(Valor_normalizado!D40=0,32,IFERROR(RANK(Valor_normalizado!D40,Valor_normalizado!D$34:D$65,0),"NA")) -> 2 | E40: =IF(Valor_normalizado!E40=0,32,IFERROR(RANK(Valor_normalizado!E40,Valor_normalizado!E$34:E$65,0),"NA")) -> 23 | F40: =IF(Valor_normalizado!F40=0,32,IFERROR(RANK(Valor_normalizado!F40,Valor_normalizado!F$34:F$65,0),"NA")) -> 22 | G40: =IF(Valor_normalizado!G40=0,32,IFERROR(RANK(Valor_normalizado!G40,Valor_normalizado!G$34:G$65,0),"NA")) -> 18 | H40: =IF(Valor_normalizado!H40=0,32,IFERROR(RANK(Valor_normalizado!H40,Valor_normalizado!H$34:H$65,0),"NA")) -> 24 | I40: =IF(Valor_normalizado!I40=0,32,IFERROR(RANK(Valor_normalizado!I40,Valor_normalizado!I$34:I$65,0),"NA")) -> 17 | J40: =IF(Valor_normalizado!J40=0,32,IFERROR(RANK(Valor_normalizado!J40,Valor_normalizado!J$34:J$65,0),"NA")) -> 16 | ... Y40: =IF(Valor_normalizado!Y40=0,32,IFERROR(RANK(Valor_normalizado!Y40,Valor_normalizado!Y$34:Y$65,0),"NA")) -> 11
A41: Cúcuta AM | B41: 2020 | C41: =IF(Valor_normalizado!C41=0,32,IFERROR(RANK(Valor_normalizado!C41,Valor_normalizado!C$34:C$65,0),"NA")) -> 19 | D41: =IF(Valor_normalizado!D41=0,32,IFERROR(RANK(Valor_normalizado!D41,Valor_normalizado!D$34:D$65,0),"NA")) -> 5 | E41: =IF(Valor_normalizado!E41=0,32,IFERROR(RANK(Valor_normalizado!E41,Valor_normalizado!E$34:E$65,0),"NA")) -> 16 | F41: =IF(Valor_normalizado!F41=0,32,IFERROR(RANK(Valor_normalizado!F41,Valor_normalizado!F$34:F$65,0),"NA")) -> 15 | G41: =IF(Valor_normalizado!G41=0,32,IFERROR(RANK(Valor_normalizado!G41,Valor_normalizado!G$34:G$65,0),"NA")) -> 16 | H41: =IF(Valor_normalizado!H41=0,32,IFERROR(RANK(Valor_normalizado!H41,Valor_normalizado!H$34:H$65,0),"NA")) -> 21 | I41: =IF(Valor_normalizado!I41=0,32,IFERROR(RANK(Valor_normalizado!I41,Valor_normalizado!I$34:I$65,0),"NA")) -> 16 | J41: =IF(Valor_normalizado!J41=0,32,IFERROR(RANK(Valor_normalizado!J41,Valor_normalizado!J$34:J$65,0),"NA")) -> 15 | ... Y41: =IF(Valor_normalizado!Y41=0,32,IFERROR(RANK(Valor_normalizado!Y41,Valor_normalizado!Y$34:Y$65,0),"NA")) -> 17
A42: Florencia | B42: 2020 | C42: =IF(Valor_normalizado!C42=0,32,IFERROR(RANK(Valor_normalizado!C42,Valor_normalizado!C$34:C$65,0),"NA")) -> 22 | D42: =IF(Valor_normalizado!D42=0,32,IFERROR(RANK(Valor_normalizado!D42,Valor_normalizado!D$34:D$65,0),"NA")) -> 23 | E42: =IF(Valor_normalizado!E42=0,32,IFERROR(RANK(Valor_normalizado!E42,Valor_normalizado!E$34:E$65,0),"NA")) -> 19 | F42: =IF(Valor_normalizado!F42=0,32,IFERROR(RANK(Valor_normalizado!F42,Valor_normalizado!F$34:F$65,0),"NA")) -> 21 | G42: =IF(Valor_normalizado!G42=0,32,IFERROR(RANK(Valor_normalizado!G42,Valor_normalizado!G$34:G$65,0),"NA")) -> 21 | H42: =IF(Valor_normalizado!H42=0,32,IFERROR(RANK(Valor_normalizado!H42,Valor_normalizado!H$34:H$65,0),"NA")) -> 23 | I42: =IF(Valor_normalizado!I42=0,32,IFERROR(RANK(Valor_normalizado!I42,Valor_normalizado!I$34:I$65,0),"NA")) -> 29 | J42: =IF(Valor_normalizado!J42=0,32,IFERROR(RANK(Valor_normalizado!J42,Valor_normalizado!J$34:J$65,0),"NA")) -> 7 | ... Y42: =IF(Valor_normalizado!Y42=0,32,IFERROR(RANK(Valor_normalizado!Y42,Valor_normalizado!Y$34:Y$65,0),"NA")) -> 23
A43: Ibagué | B43: 2020 | C43: =IF(Valor_normalizado!C43=0,32,IFERROR(RANK(Valor_normalizado!C43,Valor_normalizado!C$34:C$65,0),"NA")) -> 9 | D43: =IF(Valor_normalizado!D43=0,32,IFERROR(RANK(Valor_normalizado!D43,Valor_normalizado!D$34:D$65,0),"NA")) -> 9 | E43: =IF(Valor_normalizado!E43=0,32,IFERROR(RANK(Valor_normalizado!E43,Valor_normalizado!E$34:E$65,0),"NA")) -> 10 | F43: =IF(Valor_normalizado!F43=0,32,IFERROR(RANK(Valor_normalizado!F43,Valor_normalizado!F$34:F$65,0),"NA")) -> 6 | G43: =IF(Valor_normalizado!G43=0,32,IFERROR(RANK(Valor_normalizado!G43,Valor_normalizado!G$34:G$65,0),"NA")) -> 7 | H43: =IF(Valor_normalizado!H43=0,32,IFERROR(RANK(Valor_normalizado!H43,Valor_normalizado!H$34:H$65,0),"NA")) -> 8 | I43: =IF(Valor_normalizado!I43=0,32,IFERROR(RANK(Valor_normalizado!I43,Valor_normalizado!I$34:I$65,0),"NA")) -> 5 | J43: =IF(Valor_normalizado!J43=0,32,IFERROR(RANK(Valor_normalizado!J43,Valor_normalizado!J$34:J$65,0),"NA")) -> 8 | ... Y43: =IF(Valor_normalizado!Y43=0,32,IFERROR(RANK(Valor_normalizado!Y43,Valor_normalizado!Y$34:Y$65,0),"NA")) -> 12
A44: Inírida | B44: 2020 | C44: =IF(Valor_normalizado!C44=0,32,IFERROR(RANK(Valor_normalizado!C44,Valor_normalizado!C$34:C$65,0),"NA")) -> 30 | D44: =IF(Valor_normalizado!D44=0,32,IFERROR(RANK(Valor_normalizado!D44,Valor_normalizado!D$34:D$65,0),"NA")) -> 31 | E44: =IF(Valor_normalizado!E44=0,32,IFERROR(RANK(Valor_normalizado!E44,Valor_normalizado!E$34:E$65,0),"NA")) -> 29 | F44: =IF(Valor_normalizado!F44=0,32,IFERROR(RANK(Valor_normalizado!F44,Valor_normalizado!F$34:F$65,0),"NA")) -> 30 | G44: =IF(Valor_normalizado!G44=0,32,IFERROR(RANK(Valor_normalizado!G44,Valor_normalizado!G$34:G$65,0),"NA")) -> 30 | H44: =IF(Valor_normalizado!H44=0,32,IFERROR(RANK(Valor_normalizado!H44,Valor_normalizado!H$34:H$65,0),"NA")) -> 20 | I44: =IF(Valor_normalizado!I44=0,32,IFERROR(RANK(Valor_normalizado!I44,Valor_normalizado!I$34:I$65,0),"NA")) -> 27 | J44: =IF(Valor_normalizado!J44=0,32,IFERROR(RANK(Valor_normalizado!J44,Valor_normalizado!J$34:J$65,0),"NA")) -> 10 | ... Y44: =IF(Valor_normalizado!Y44=0,32,IFERROR(RANK(Valor_normalizado!Y44,Valor_normalizado!Y$34:Y$65,0),"NA")) -> 32
A45: Leticia | B45: 2020 | C45: =IF(Valor_normalizado!C45=0,32,IFERROR(RANK(Valor_normalizado!C45,Valor_normalizado!C$34:C$65,0),"NA")) -> 31 | D45: =IF(Valor_normalizado!D45=0,32,IFERROR(RANK(Valor_normalizado!D45,Valor_normalizado!D$34:D$65,0),"NA")) -> 29 | E45: =IF(Valor_normalizado!E45=0,32,IFERROR(RANK(Valor_normalizado!E45,Valor_normalizado!E$34:E$65,0),"NA")) -> 32 | F45: =IF(Valor_normalizado!F45=0,32,IFERROR(RANK(Valor_normalizado!F45,Valor_normalizado!F$34:F$65,0),"NA")) -> 31 | G45: =IF(Valor_normalizado!G45=0,32,IFERROR(RANK(Valor_normalizado!G45,Valor_normalizado!G$34:G$65,0),"NA")) -> 32 | H45: =IF(Valor_normalizado!H45=0,32,IFERROR(RANK(Valor_normalizado!H45,Valor_normalizado!H$34:H$65,0),"NA")) -> 31 | I45: =IF(Valor_normalizado!I45=0,32,IFERROR(RANK(Valor_normalizado!I45,Valor_normalizado!I$34:I$65,0),"NA")) -> 31 | J45: =IF(Valor_normalizado!J45=0,32,IFERROR(RANK(Valor_normalizado!J45,Valor_normalizado!J$34:J$65,0),"NA")) -> 28 | ... Y45: =IF(Valor_normalizado!Y45=0,32,IFERROR(RANK(Valor_normalizado!Y45,Valor_normalizado!Y$34:Y$65,0),"NA")) -> 28
... A65: Yopal | B65: 2020 | C65: =IF(Valor_normalizado!C65=0,32,IFERROR(RANK(Valor_normalizado!C65,Valor_normalizado!C$34:C$65,0),"NA")) -> 15 | D65: =IF(Valor_normalizado!D65=0,32,IFERROR(RANK(Valor_normalizado!D65,Valor_normalizado!D$34:D$65,0),"NA")) -> 21 | E65: =IF(Valor_normalizado!E65=0,32,IFERROR(RANK(Valor_normalizado!E65,Valor_normalizado!E$34:E$65,0),"NA")) -> 11 | F65: =IF(Valor_normalizado!F65=0,32,IFERROR(RANK(Valor_normalizado!F65,Valor_normalizado!F$34:F$65,0),"NA")) -> 12 | G65: =IF(Valor_normalizado!G65=0,32,IFERROR(RANK(Valor_normalizado!G65,Valor_normalizado!G$34:G$65,0),"NA")) -> 15 | H65: =IF(Valor_normalizado!H65=0,32,IFERROR(RANK(Valor_normalizado!H65,Valor_normalizado!H$34:H$65,0),"NA")) -> 22 | I65: =IF(Valor_normalizado!I65=0,32,IFERROR(RANK(Valor_normalizado!I65,Valor_normalizado!I$34:I$65,0),"NA")) -> 25 | J65: =IF(Valor_normalizado!J65=0,32,IFERROR(RANK(Valor_normalizado!J65,Valor_normalizado!J$34:J$65,0),"NA")) -> 26 | ... Y65: =IF(Valor_normalizado!Y65=0,32,IFERROR(RANK(Valor_normalizado!Y65,Valor_normalizado!Y$34:Y$65,0),"NA")) -> 21
A66: Arauca | B66: 2021 | C66: =IF(Valor_normalizado!C66=0,32,IFERROR(RANK(Valor_normalizado!C66,Valor_normalizado!C$66:C$97,0),"NA")) -> 25 | D66: =IF(Valor_normalizado!D66=0,32,IFERROR(RANK(Valor_normalizado!D66,Valor_normalizado!D$66:D$97,0),"NA")) -> 25 | E66: =IF(Valor_normalizado!E66=0,32,IFERROR(RANK(Valor_normalizado!E66,Valor_normalizado!E$66:E$97,0),"NA")) -> 30 | F66: =IF(Valor_normalizado!F66=0,32,IFERROR(RANK(Valor_normalizado!F66,Valor_normalizado!F$66:F$97,0),"NA")) -> 20 | G66: =IF(Valor_normalizado!G66=0,32,IFERROR(RANK(Valor_normalizado!G66,Valor_normalizado!G$66:G$97,0),"NA")) -> 27 | H66: =IF(Valor_normalizado!H66=0,32,IFERROR(RANK(Valor_normalizado!H66,Valor_normalizado!H$66:H$97,0),"NA")) -> 31 | I66: =IF(Valor_normalizado!I66=0,32,IFERROR(RANK(Valor_normalizado!I66,Valor_normalizado!I$66:I$97,0),"NA")) -> 29 | J66: =IF(Valor_normalizado!J66=0,32,IFERROR(RANK(Valor_normalizado!J66,Valor_normalizado!J$66:J$97,0),"NA")) -> 31 | ... Y66: =IF(Valor_normalizado!Y66=0,32,IFERROR(RANK(Valor_normalizado!Y66,Valor_normalizado!Y$66:Y$97,0),"NA")) -> 27
A67: Armenia | B67: 2021 | C67: =IF(Valor_normalizado!C67=0,32,IFERROR(RANK(Valor_normalizado!C67,Valor_normalizado!C$66:C$97,0),"NA")) -> 1 | D67: =IF(Valor_normalizado!D67=0,32,IFERROR(RANK(Valor_normalizado!D67,Valor_normalizado!D$66:D$97,0),"NA")) -> 19 | E67: =IF(Valor_normalizado!E67=0,32,IFERROR(RANK(Valor_normalizado!E67,Valor_normalizado!E$66:E$97,0),"NA")) -> 14 | F67: =IF(Valor_normalizado!F67=0,32,IFERROR(RANK(Valor_normalizado!F67,Valor_normalizado!F$66:F$97,0),"NA")) -> 14 | G67: =IF(Valor_normalizado!G67=0,32,IFERROR(RANK(Valor_normalizado!G67,Valor_normalizado!G$66:G$97,0),"NA")) -> 7 | H67: =IF(Valor_normalizado!H67=0,32,IFERROR(RANK(Valor_normalizado!H67,Valor_normalizado!H$66:H$97,0),"NA")) -> 4 | I67: =IF(Valor_normalizado!I67=0,32,IFERROR(RANK(Valor_normalizado!I67,Valor_normalizado!I$66:I$97,0),"NA")) -> 10 | J67: =IF(Valor_normalizado!J67=0,32,IFERROR(RANK(Valor_normalizado!J67,Valor_normalizado!J$66:J$97,0),"NA")) -> 19 | ... Y67: =IF(Valor_normalizado!Y67=0,32,IFERROR(RANK(Valor_normalizado!Y67,Valor_normalizado!Y$66:Y$97,0),"NA")) -> 11
A68: Barranquilla AM | B68: 2021 | C68: =IF(Valor_normalizado!C68=0,32,IFERROR(RANK(Valor_normalizado!C68,Valor_normalizado!C$66:C$97,0),"NA")) -> 15 | D68: =IF(Valor_normalizado!D68=0,32,IFERROR(RANK(Valor_normalizado!D68,Valor_normalizado!D$66:D$97,0),"NA")) -> 5 | E68: =IF(Valor_normalizado!E68=0,32,IFERROR(RANK(Valor_normalizado!E68,Valor_normalizado!E$66:E$97,0),"NA")) -> 8 | F68: =IF(Valor_normalizado!F68=0,32,IFERROR(RANK(Valor_normalizado!F68,Valor_normalizado!F$66:F$97,0),"NA")) -> 7 | G68: =IF(Valor_normalizado!G68=0,32,IFERROR(RANK(Valor_normalizado!G68,Valor_normalizado!G$66:G$97,0),"NA")) -> 12 | H68: =IF(Valor_normalizado!H68=0,32,IFERROR(RANK(Valor_normalizado!H68,Valor_normalizado!H$66:H$97,0),"NA")) -> 15 | I68: =IF(Valor_normalizado!I68=0,32,IFERROR(RANK(Valor_normalizado!I68,Valor_normalizado!I$66:I$97,0),"NA")) -> 11 | J68: =IF(Valor_normalizado!J68=0,32,IFERROR(RANK(Valor_normalizado!J68,Valor_normalizado!J$66:J$97,0),"NA")) -> 8 | ... Y68: =IF(Valor_normalizado!Y68=0,32,IFERROR(RANK(Valor_normalizado!Y68,Valor_normalizado!Y$66:Y$97,0),"NA")) -> 8
A69: Bogotá D.C. | B69: 2021 | C69: =IF(Valor_normalizado!C69=0,32,IFERROR(RANK(Valor_normalizado!C69,Valor_normalizado!C$66:C$97,0),"NA")) -> 2 | D69: =IF(Valor_normalizado!D69=0,32,IFERROR(RANK(Valor_normalizado!D69,Valor_normalizado!D$66:D$97,0),"NA")) -> 1 | E69: =IF(Valor_normalizado!E69=0,32,IFERROR(RANK(Valor_normalizado!E69,Valor_normalizado!E$66:E$97,0),"NA")) -> 1 | F69: =IF(Valor_normalizado!F69=0,32,IFERROR(RANK(Valor_normalizado!F69,Valor_normalizado!F$66:F$97,0),"NA")) -> 1 | G69: =IF(Valor_normalizado!G69=0,32,IFERROR(RANK(Valor_normalizado!G69,Valor_normalizado!G$66:G$97,0),"NA")) -> 1 | H69: =IF(Valor_normalizado!H69=0,32,IFERROR(RANK(Valor_normalizado!H69,Valor_normalizado!H$66:H$97,0),"NA")) -> 7 | I69: =IF(Valor_normalizado!I69=0,32,IFERROR(RANK(Valor_normalizado!I69,Valor_normalizado!I$66:I$97,0),"NA")) -> 4 | J69: =IF(Valor_normalizado!J69=0,32,IFERROR(RANK(Valor_normalizado!J69,Valor_normalizado!J$66:J$97,0),"NA")) -> 3 | ... Y69: =IF(Valor_normalizado!Y69=0,32,IFERROR(RANK(Valor_normalizado!Y69,Valor_normalizado!Y$66:Y$97,0),"NA")) -> 1
A70: Bucaramanga AM | B70: 2021 | C70: =IF(Valor_normalizado!C70=0,32,IFERROR(RANK(Valor_normalizado!C70,Valor_normalizado!C$66:C$97,0),"NA")) -> 8 | D70: =IF(Valor_normalizado!D70=0,32,IFERROR(RANK(Valor_normalizado!D70,Valor_normalizado!D$66:D$97,0),"NA")) -> 6 | E70: =IF(Valor_normalizado!E70=0,32,IFERROR(RANK(Valor_normalizado!E70,Valor_normalizado!E$66:E$97,0),"NA")) -> 4 | F70: =IF(Valor_normalizado!F70=0,32,IFERROR(RANK(Valor_normalizado!F70,Valor_normalizado!F$66:F$97,0),"NA")) -> 5 | G70: =IF(Valor_normalizado!G70=0,32,IFERROR(RANK(Valor_normalizado!G70,Valor_normalizado!G$66:G$97,0),"NA")) -> 5 | H70: =IF(Valor_normalizado!H70=0,32,IFERROR(RANK(Valor_normalizado!H70,Valor_normalizado!H$66:H$97,0),"NA")) -> 8 | I70: =IF(Valor_normalizado!I70=0,32,IFERROR(RANK(Valor_normalizado!I70,Valor_normalizado!I$66:I$97,0),"NA")) -> 6 | J70: =IF(Valor_normalizado!J70=0,32,IFERROR(RANK(Valor_normalizado!J70,Valor_normalizado!J$66:J$97,0),"NA")) -> 5 | ... Y70: =IF(Valor_normalizado!Y70=0,32,IFERROR(RANK(Valor_normalizado!Y70,Valor_normalizado!Y$66:Y$97,0),"NA")) -> 5
A71: Cali AM | B71: 2021 | C71: =IF(Valor_normalizado!C71=0,32,IFERROR(RANK(Valor_normalizado!C71,Valor_normalizado!C$66:C$97,0),"NA")) -> 7 | D71: =IF(Valor_normalizado!D71=0,32,IFERROR(RANK(Valor_normalizado!D71,Valor_normalizado!D$66:D$97,0),"NA")) -> 4 | E71: =IF(Valor_normalizado!E71=0,32,IFERROR(RANK(Valor_normalizado!E71,Valor_normalizado!E$66:E$97,0),"NA")) -> 3 | F71: =IF(Valor_normalizado!F71=0,32,IFERROR(RANK(Valor_normalizado!F71,Valor_normalizado!F$66:F$97,0),"NA")) -> 3 | G71: =IF(Valor_normalizado!G71=0,32,IFERROR(RANK(Valor_normalizado!G71,Valor_normalizado!G$66:G$97,0),"NA")) -> 3 | H71: =IF(Valor_normalizado!H71=0,32,IFERROR(RANK(Valor_normalizado!H71,Valor_normalizado!H$66:H$97,0),"NA")) -> 20 | I71: =IF(Valor_normalizado!I71=0,32,IFERROR(RANK(Valor_normalizado!I71,Valor_normalizado!I$66:I$97,0),"NA")) -> 15 | J71: =IF(Valor_normalizado!J71=0,32,IFERROR(RANK(Valor_normalizado!J71,Valor_normalizado!J$66:J$97,0),"NA")) -> 10 | ... Y71: =IF(Valor_normalizado!Y71=0,32,IFERROR(RANK(Valor_normalizado!Y71,Valor_normalizado!Y$66:Y$97,0),"NA")) -> 4
A72: Cartagena | B72: 2021 | C72: =IF(Valor_normalizado!C72=0,32,IFERROR(RANK(Valor_normalizado!C72,Valor_normalizado!C$66:C$97,0),"NA")) -> 17 | D72: =IF(Valor_normalizado!D72=0,32,IFERROR(RANK(Valor_normalizado!D72,Valor_normalizado!D$66:D$97,0),"NA")) -> 2 | E72: =IF(Valor_normalizado!E72=0,32,IFERROR(RANK(Valor_normalizado!E72,Valor_normalizado!E$66:E$97,0),"NA")) -> 23 | F72: =IF(Valor_normalizado!F72=0,32,IFERROR(RANK(Valor_normalizado!F72,Valor_normalizado!F$66:F$97,0),"NA")) -> 22 | G72: =IF(Valor_normalizado!G72=0,32,IFERROR(RANK(Valor_normalizado!G72,Valor_normalizado!G$66:G$97,0),"NA")) -> 18 | H72: =IF(Valor_normalizado!H72=0,32,IFERROR(RANK(Valor_normalizado!H72,Valor_normalizado!H$66:H$97,0),"NA")) -> 23 | I72: =IF(Valor_normalizado!I72=0,32,IFERROR(RANK(Valor_normalizado!I72,Valor_normalizado!I$66:I$97,0),"NA")) -> 16 | J72: =IF(Valor_normalizado!J72=0,32,IFERROR(RANK(Valor_normalizado!J72,Valor_normalizado!J$66:J$97,0),"NA")) -> 16 | ... Y72: =IF(Valor_normalizado!Y72=0,32,IFERROR(RANK(Valor_normalizado!Y72,Valor_normalizado!Y$66:Y$97,0),"NA")) -> 12
A73: Cúcuta AM | B73: 2021 | C73: =IF(Valor_normalizado!C73=0,32,IFERROR(RANK(Valor_normalizado!C73,Valor_normalizado!C$66:C$97,0),"NA")) -> 19 | D73: =IF(Valor_normalizado!D73=0,32,IFERROR(RANK(Valor_normalizado!D73,Valor_normalizado!D$66:D$97,0),"NA")) -> 9 | E73: =IF(Valor_normalizado!E73=0,32,IFERROR(RANK(Valor_normalizado!E73,Valor_normalizado!E$66:E$97,0),"NA")) -> 16 | F73: =IF(Valor_normalizado!F73=0,32,IFERROR(RANK(Valor_normalizado!F73,Valor_normalizado!F$66:F$97,0),"NA")) -> 15 | G73: =IF(Valor_normalizado!G73=0,32,IFERROR(RANK(Valor_normalizado!G73,Valor_normalizado!G$66:G$97,0),"NA")) -> 16 | H73: =IF(Valor_normalizado!H73=0,32,IFERROR(RANK(Valor_normalizado!H73,Valor_normalizado!H$66:H$97,0),"NA")) -> 19 | I73: =IF(Valor_normalizado!I73=0,32,IFERROR(RANK(Valor_normalizado!I73,Valor_normalizado!I$66:I$97,0),"NA")) -> 18 | J73: =IF(Valor_normalizado!J73=0,32,IFERROR(RANK(Valor_normalizado!J73,Valor_normalizado!J$66:J$97,0),"NA")) -> 20 | ... Y73: =IF(Valor_normalizado!Y73=0,32,IFERROR(RANK(Valor_normalizado!Y73,Valor_normalizado!Y$66:Y$97,0),"NA")) -> 17
A74: Florencia | B74: 2021 | C74: =IF(Valor_normalizado!C74=0,32,IFERROR(RANK(Valor_normalizado!C74,Valor_normalizado!C$66:C$97,0),"NA")) -> 21 | D74: =IF(Valor_normalizado!D74=0,32,IFERROR(RANK(Valor_normalizado!D74,Valor_normalizado!D$66:D$97,0),"NA")) -> 23 | E74: =IF(Valor_normalizado!E74=0,32,IFERROR(RANK(Valor_normalizado!E74,Valor_normalizado!E$66:E$97,0),"NA")) -> 19 | F74: =IF(Valor_normalizado!F74=0,32,IFERROR(RANK(Valor_normalizado!F74,Valor_normalizado!F$66:F$97,0),"NA")) -> 21 | G74: =IF(Valor_normalizado!G74=0,32,IFERROR(RANK(Valor_normalizado!G74,Valor_normalizado!G$66:G$97,0),"NA")) -> 20 | H74: =IF(Valor_normalizado!H74=0,32,IFERROR(RANK(Valor_normalizado!H74,Valor_normalizado!H$66:H$97,0),"NA")) -> 21 | I74: =IF(Valor_normalizado!I74=0,32,IFERROR(RANK(Valor_normalizado!I74,Valor_normalizado!I$66:I$97,0),"NA")) -> 25 | J74: =IF(Valor_normalizado!J74=0,32,IFERROR(RANK(Valor_normalizado!J74,Valor_normalizado!J$66:J$97,0),"NA")) -> 6 | ... Y74: =IF(Valor_normalizado!Y74=0,32,IFERROR(RANK(Valor_normalizado!Y74,Valor_normalizado!Y$66:Y$97,0),"NA")) -> 19
A75: Ibagué | B75: 2021 | C75: =IF(Valor_normalizado!C75=0,32,IFERROR(RANK(Valor_normalizado!C75,Valor_normalizado!C$66:C$97,0),"NA")) -> 9 | D75: =IF(Valor_normalizado!D75=0,32,IFERROR(RANK(Valor_normalizado!D75,Valor_normalizado!D$66:D$97,0),"NA")) -> 8 | E75: =IF(Valor_normalizado!E75=0,32,IFERROR(RANK(Valor_normalizado!E75,Valor_normalizado!E$66:E$97,0),"NA")) -> 10 | F75: =IF(Valor_normalizado!F75=0,32,IFERROR(RANK(Valor_normalizado!F75,Valor_normalizado!F$66:F$97,0),"NA")) -> 6 | G75: =IF(Valor_normalizado!G75=0,32,IFERROR(RANK(Valor_normalizado!G75,Valor_normalizado!G$66:G$97,0),"NA")) -> 9 | H75: =IF(Valor_normalizado!H75=0,32,IFERROR(RANK(Valor_normalizado!H75,Valor_normalizado!H$66:H$97,0),"NA")) -> 5 | I75: =IF(Valor_normalizado!I75=0,32,IFERROR(RANK(Valor_normalizado!I75,Valor_normalizado!I$66:I$97,0),"NA")) -> 5 | J75: =IF(Valor_normalizado!J75=0,32,IFERROR(RANK(Valor_normalizado!J75,Valor_normalizado!J$66:J$97,0),"NA")) -> 11 | ... Y75: =IF(Valor_normalizado!Y75=0,32,IFERROR(RANK(Valor_normalizado!Y75,Valor_normalizado!Y$66:Y$97,0),"NA")) -> 10
A76: Inírida | B76: 2021 | C76: =IF(Valor_normalizado!C76=0,32,IFERROR(RANK(Valor_normalizado!C76,Valor_normalizado!C$66:C$97,0),"NA")) -> 29 | D76: =IF(Valor_normalizado!D76=0,32,IFERROR(RANK(Valor_normalizado!D76,Valor_normalizado!D$66:D$97,0),"NA")) -> 31 | E76: =IF(Valor_normalizado!E76=0,32,IFERROR(RANK(Valor_normalizado!E76,Valor_normalizado!E$66:E$97,0),"NA")) -> 29 | F76: =IF(Valor_normalizado!F76=0,32,IFERROR(RANK(Valor_normalizado!F76,Valor_normalizado!F$66:F$97,0),"NA")) -> 30 | G76: =IF(Valor_normalizado!G76=0,32,IFERROR(RANK(Valor_normalizado!G76,Valor_normalizado!G$66:G$97,0),"NA")) -> 30 | H76: =IF(Valor_normalizado!H76=0,32,IFERROR(RANK(Valor_normalizado!H76,Valor_normalizado!H$66:H$97,0),"NA")) -> 24 | I76: =IF(Valor_normalizado!I76=0,32,IFERROR(RANK(Valor_normalizado!I76,Valor_normalizado!I$66:I$97,0),"NA")) -> 27 | J76: =IF(Valor_normalizado!J76=0,32,IFERROR(RANK(Valor_normalizado!J76,Valor_normalizado!J$66:J$97,0),"NA")) -> 6 | ... Y76: =IF(Valor_normalizado!Y76=0,32,IFERROR(RANK(Valor_normalizado!Y76,Valor_normalizado!Y$66:Y$97,0),"NA")) -> 31
A77: Leticia | B77: 2021 | C77: =IF(Valor_normalizado!C77=0,32,IFERROR(RANK(Valor_normalizado!C77,Valor_normalizado!C$66:C$97,0),"NA")) -> 31 | D77: =IF(Valor_normalizado!D77=0,32,IFERROR(RANK(Valor_normalizado!D77,Valor_normalizado!D$66:D$97,0),"NA")) -> 29 | E77: =IF(Valor_normalizado!E77=0,32,IFERROR(RANK(Valor_normalizado!E77,Valor_normalizado!E$66:E$97,0),"NA")) -> 32 | F77: =IF(Valor_normalizado!F77=0,32,IFERROR(RANK(Valor_normalizado!F77,Valor_normalizado!F$66:F$97,0),"NA")) -> 31 | G77: =IF(Valor_normalizado!G77=0,32,IFERROR(RANK(Valor_normalizado!G77,Valor_normalizado!G$66:G$97,0),"NA")) -> 32 | H77: =IF(Valor_normalizado!H77=0,32,IFERROR(RANK(Valor_normalizado!H77,Valor_normalizado!H$66:H$97,0),"NA")) -> 29 | I77: =IF(Valor_normalizado!I77=0,32,IFERROR(RANK(Valor_normalizado!I77,Valor_normalizado!I$66:I$97,0),"NA")) -> 30 | J77: =IF(Valor_normalizado!J77=0,32,IFERROR(RANK(Valor_normalizado!J77,Valor_normalizado!J$66:J$97,0),"NA")) -> 28 | ... Y77: =IF(Valor_normalizado!Y77=0,32,IFERROR(RANK(Valor_normalizado!Y77,Valor_normalizado!Y$66:Y$97,0),"NA")) -> 29
... A97: Yopal | B97: 2021 | C97: =IF(Valor_normalizado!C97=0,32,IFERROR(RANK(Valor_normalizado!C97,Valor_normalizado!C$66:C$97,0),"NA")) -> 12 | D97: =IF(Valor_normalizado!D97=0,32,IFERROR(RANK(Valor_normalizado!D97,Valor_normalizado!D$66:D$97,0),"NA")) -> 21 | E97: =IF(Valor_normalizado!E97=0,32,IFERROR(RANK(Valor_normalizado!E97,Valor_normalizado!E$66:E$97,0),"NA")) -> 11 | F97: =IF(Valor_normalizado!F97=0,32,IFERROR(RANK(Valor_normalizado!F97,Valor_normalizado!F$66:F$97,0),"NA")) -> 12 | G97: =IF(Valor_normalizado!G97=0,32,IFERROR(RANK(Valor_normalizado!G97,Valor_normalizado!G$66:G$97,0),"NA")) -> 13 | H97: =IF(Valor_normalizado!H97=0,32,IFERROR(RANK(Valor_normalizado!H97,Valor_normalizado!H$66:H$97,0),"NA")) -> 18 | I97: =IF(Valor_normalizado!I97=0,32,IFERROR(RANK(Valor_normalizado!I97,Valor_normalizado!I$66:I$97,0),"NA")) -> 20 | J97: =IF(Valor_normalizado!J97=0,32,IFERROR(RANK(Valor_normalizado!J97,Valor_normalizado!J$66:J$97,0),"NA")) -> 25 | ... Y97: =IF(Valor_normalizado!Y97=0,32,IFERROR(RANK(Valor_normalizado!Y97,Valor_normalizado!Y$66:Y$97,0),"NA")) -> 22
A98: Arauca | B98: 2022 | C98: =IF(Valor_normalizado!C98=0,32,IFERROR(RANK(Valor_normalizado!C98,Valor_normalizado!C$98:C$129,0),"NA")) -> 25 | D98: =IF(Valor_normalizado!D98=0,32,IFERROR(RANK(Valor_normalizado!D98,Valor_normalizado!D$98:D$129,0),"NA")) -> 25 | E98: =IF(Valor_normalizado!E98=0,32,IFERROR(RANK(Valor_normalizado!E98,Valor_normalizado!E$98:E$129,0),"NA")) -> 28 | F98: =IF(Valor_normalizado!F98=0,32,IFERROR(RANK(Valor_normalizado!F98,Valor_normalizado!F$98:F$129,0),"NA")) -> 19 | G98: =IF(Valor_normalizado!G98=0,32,IFERROR(RANK(Valor_normalizado!G98,Valor_normalizado!G$98:G$129,0),"NA")) -> 25 | H98: =IF(Valor_normalizado!H98=0,32,IFERROR(RANK(Valor_normalizado!H98,Valor_normalizado!H$98:H$129,0),"NA")) -> 31 | I98: =IF(Valor_normalizado!I98=0,32,IFERROR(RANK(Valor_normalizado!I98,Valor_normalizado!I$98:I$129,0),"NA")) -> 28 | J98: =IF(Valor_normalizado!J98=0,32,IFERROR(RANK(Valor_normalizado!J98,Valor_normalizado!J$98:J$129,0),"NA")) -> 30 | ... Y98: =IF(Valor_normalizado!Y98=0,32,IFERROR(RANK(Valor_normalizado!Y98,Valor_normalizado!Y$98:Y$129,0),"NA")) -> 26
A99: Armenia | B99: 2022 | C99: =IF(Valor_normalizado!C99=0,32,IFERROR(RANK(Valor_normalizado!C99,Valor_normalizado!C$98:C$129,0),"NA")) -> 1 | D99: =IF(Valor_normalizado!D99=0,32,IFERROR(RANK(Valor_normalizado!D99,Valor_normalizado!D$98:D$129,0),"NA")) -> 15 | E99: =IF(Valor_normalizado!E99=0,32,IFERROR(RANK(Valor_normalizado!E99,Valor_normalizado!E$98:E$129,0),"NA")) -> 6 | F99: =IF(Valor_normalizado!F99=0,32,IFERROR(RANK(Valor_normalizado!F99,Valor_normalizado!F$98:F$129,0),"NA")) -> 13 | G99: =IF(Valor_normalizado!G99=0,32,IFERROR(RANK(Valor_normalizado!G99,Valor_normalizado!G$98:G$129,0),"NA")) -> 6 | H99: =IF(Valor_normalizado!H99=0,32,IFERROR(RANK(Valor_normalizado!H99,Valor_normalizado!H$98:H$129,0),"NA")) -> 5 | I99: =IF(Valor_normalizado!I99=0,32,IFERROR(RANK(Valor_normalizado!I99,Valor_normalizado!I$98:I$129,0),"NA")) -> 7 | J99: =IF(Valor_normalizado!J99=0,32,IFERROR(RANK(Valor_normalizado!J99,Valor_normalizado!J$98:J$129,0),"NA")) -> 26 | ... Y99: =IF(Valor_normalizado!Y99=0,32,IFERROR(RANK(Valor_normalizado!Y99,Valor_normalizado!Y$98:Y$129,0),"NA")) -> 10
A100: Barranquilla AM | B100: 2022 | C100: =IF(Valor_normalizado!C100=0,32,IFERROR(RANK(Valor_normalizado!C100,Valor_normalizado!C$98:C$129,0),"NA")) -> 16 | D100: =IF(Valor_normalizado!D100=0,32,IFERROR(RANK(Valor_normalizado!D100,Valor_normalizado!D$98:D$129,0),"NA")) -> 8 | E100: =IF(Valor_normalizado!E100=0,32,IFERROR(RANK(Valor_normalizado!E100,Valor_normalizado!E$98:E$129,0),"NA")) -> 11 | F100: =IF(Valor_normalizado!F100=0,32,IFERROR(RANK(Valor_normalizado!F100,Valor_normalizado!F$98:F$129,0),"NA")) -> 12 | G100: =IF(Valor_normalizado!G100=0,32,IFERROR(RANK(Valor_normalizado!G100,Valor_normalizado!G$98:G$129,0),"NA")) -> 13 | H100: =IF(Valor_normalizado!H100=0,32,IFERROR(RANK(Valor_normalizado!H100,Valor_normalizado!H$98:H$129,0),"NA")) -> 14 | I100: =IF(Valor_normalizado!I100=0,32,IFERROR(RANK(Valor_normalizado!I100,Valor_normalizado!I$98:I$129,0),"NA")) -> 9 | J100: =IF(Valor_normalizado!J100=0,32,IFERROR(RANK(Valor_normalizado!J100,Valor_normalizado!J$98:J$129,0),"NA")) -> 8 | ... Y100: =IF(Valor_normalizado!Y100=0,32,IFERROR(RANK(Valor_normalizado!Y100,Valor_normalizado!Y$98:Y$129,0),"NA")) -> 8
A101: Bogotá D.C. | B101: 2022 | C101: =IF(Valor_normalizado!C101=0,32,IFERROR(RANK(Valor_normalizado!C101,Valor_normalizado!C$98:C$129,0),"NA")) -> 2 | D101: =IF(Valor_normalizado!D101=0,32,IFERROR(RANK(Valor_normalizado!D101,Valor_normalizado!D$98:D$129,0),"NA")) -> 1 | E101: =IF(Valor_normalizado!E101=0,32,IFERROR(RANK(Valor_normalizado!E101,Valor_normalizado!E$98:E$129,0),"NA")) -> 1 | F101: =IF(Valor_normalizado!F101=0,32,IFERROR(RANK(Valor_normalizado!F101,Valor_normalizado!F$98:F$129,0),"NA")) -> 2 | G101: =IF(Valor_normalizado!G101=0,32,IFERROR(RANK(Valor_normalizado!G101,Valor_normalizado!G$98:G$129,0),"NA")) -> 1 | H101: =IF(Valor_normalizado!H101=0,32,IFERROR(RANK(Valor_normalizado!H101,Valor_normalizado!H$98:H$129,0),"NA")) -> 3 | I101: =IF(Valor_normalizado!I101=0,32,IFERROR(RANK(Valor_normalizado!I101,Valor_normalizado!I$98:I$129,0),"NA")) -> 4 | J101: =IF(Valor_normalizado!J101=0,32,IFERROR(RANK(Valor_normalizado!J101,Valor_normalizado!J$98:J$129,0),"NA")) -> 3 | ... Y101: =IF(Valor_normalizado!Y101=0,32,IFERROR(RANK(Valor_normalizado!Y101,Valor_normalizado!Y$98:Y$129,0),"NA")) -> 1
A102: Bucaramanga AM | B102: 2022 | C102: =IF(Valor_normalizado!C102=0,32,IFERROR(RANK(Valor_normalizado!C102,Valor_normalizado!C$98:C$129,0),"NA")) -> 8 | D102: =IF(Valor_normalizado!D102=0,32,IFERROR(RANK(Valor_normalizado!D102,Valor_normalizado!D$98:D$129,0),"NA")) -> 5 | E102: =IF(Valor_normalizado!E102=0,32,IFERROR(RANK(Valor_normalizado!E102,Valor_normalizado!E$98:E$129,0),"NA")) -> 9 | F102: =IF(Valor_normalizado!F102=0,32,IFERROR(RANK(Valor_normalizado!F102,Valor_normalizado!F$98:F$129,0),"NA")) -> 7 | G102: =IF(Valor_normalizado!G102=0,32,IFERROR(RANK(Valor_normalizado!G102,Valor_normalizado!G$98:G$129,0),"NA")) -> 7 | H102: =IF(Valor_normalizado!H102=0,32,IFERROR(RANK(Valor_normalizado!H102,Valor_normalizado!H$98:H$129,0),"NA")) -> 8 | I102: =IF(Valor_normalizado!I102=0,32,IFERROR(RANK(Valor_normalizado!I102,Valor_normalizado!I$98:I$129,0),"NA")) -> 8 | J102: =IF(Valor_normalizado!J102=0,32,IFERROR(RANK(Valor_normalizado!J102,Valor_normalizado!J$98:J$129,0),"NA")) -> 7 | ... Y102: =IF(Valor_normalizado!Y102=0,32,IFERROR(RANK(Valor_normalizado!Y102,Valor_normalizado!Y$98:Y$129,0),"NA")) -> 5
A103: Cali AM | B103: 2022 | C103: =IF(Valor_normalizado!C103=0,32,IFERROR(RANK(Valor_normalizado!C103,Valor_normalizado!C$98:C$129,0),"NA")) -> 9 | D103: =IF(Valor_normalizado!D103=0,32,IFERROR(RANK(Valor_normalizado!D103,Valor_normalizado!D$98:D$129,0),"NA")) -> 3 | E103: =IF(Valor_normalizado!E103=0,32,IFERROR(RANK(Valor_normalizado!E103,Valor_normalizado!E$98:E$129,0),"NA")) -> 7 | F103: =IF(Valor_normalizado!F103=0,32,IFERROR(RANK(Valor_normalizado!F103,Valor_normalizado!F$98:F$129,0),"NA")) -> 3 | G103: =IF(Valor_normalizado!G103=0,32,IFERROR(RANK(Valor_normalizado!G103,Valor_normalizado!G$98:G$129,0),"NA")) -> 3 | H103: =IF(Valor_normalizado!H103=0,32,IFERROR(RANK(Valor_normalizado!H103,Valor_normalizado!H$98:H$129,0),"NA")) -> 16 | I103: =IF(Valor_normalizado!I103=0,32,IFERROR(RANK(Valor_normalizado!I103,Valor_normalizado!I$98:I$129,0),"NA")) -> 16 | J103: =IF(Valor_normalizado!J103=0,32,IFERROR(RANK(Valor_normalizado!J103,Valor_normalizado!J$98:J$129,0),"NA")) -> 6 | ... Y103: =IF(Valor_normalizado!Y103=0,32,IFERROR(RANK(Valor_normalizado!Y103,Valor_normalizado!Y$98:Y$129,0),"NA")) -> 4
A104: Cartagena | B104: 2022 | C104: =IF(Valor_normalizado!C104=0,32,IFERROR(RANK(Valor_normalizado!C104,Valor_normalizado!C$98:C$129,0),"NA")) -> 17 | D104: =IF(Valor_normalizado!D104=0,32,IFERROR(RANK(Valor_normalizado!D104,Valor_normalizado!D$98:D$129,0),"NA")) -> 9 | E104: =IF(Valor_normalizado!E104=0,32,IFERROR(RANK(Valor_normalizado!E104,Valor_normalizado!E$98:E$129,0),"NA")) -> 20 | F104: =IF(Valor_normalizado!F104=0,32,IFERROR(RANK(Valor_normalizado!F104,Valor_normalizado!F$98:F$129,0),"NA")) -> 20 | G104: =IF(Valor_normalizado!G104=0,32,IFERROR(RANK(Valor_normalizado!G104,Valor_normalizado!G$98:G$129,0),"NA")) -> 17 | H104: =IF(Valor_normalizado!H104=0,32,IFERROR(RANK(Valor_normalizado!H104,Valor_normalizado!H$98:H$129,0),"NA")) -> 21 | I104: =IF(Valor_normalizado!I104=0,32,IFERROR(RANK(Valor_normalizado!I104,Valor_normalizado!I$98:I$129,0),"NA")) -> 15 | J104: =IF(Valor_normalizado!J104=0,32,IFERROR(RANK(Valor_normalizado!J104,Valor_normalizado!J$98:J$129,0),"NA")) -> 18 | ... Y104: =IF(Valor_normalizado!Y104=0,32,IFERROR(RANK(Valor_normalizado!Y104,Valor_normalizado!Y$98:Y$129,0),"NA")) -> 13
A105: Cúcuta AM | B105: 2022 | C105: =IF(Valor_normalizado!C105=0,32,IFERROR(RANK(Valor_normalizado!C105,Valor_normalizado!C$98:C$129,0),"NA")) -> 18 | D105: =IF(Valor_normalizado!D105=0,32,IFERROR(RANK(Valor_normalizado!D105,Valor_normalizado!D$98:D$129,0),"NA")) -> 11 | E105: =IF(Valor_normalizado!E105=0,32,IFERROR(RANK(Valor_normalizado!E105,Valor_normalizado!E$98:E$129,0),"NA")) -> 17 | F105: =IF(Valor_normalizado!F105=0,32,IFERROR(RANK(Valor_normalizado!F105,Valor_normalizado!F$98:F$129,0),"NA")) -> 14 | G105: =IF(Valor_normalizado!G105=0,32,IFERROR(RANK(Valor_normalizado!G105,Valor_normalizado!G$98:G$129,0),"NA")) -> 16 | H105: =IF(Valor_normalizado!H105=0,32,IFERROR(RANK(Valor_normalizado!H105,Valor_normalizado!H$98:H$129,0),"NA")) -> 13 | I105: =IF(Valor_normalizado!I105=0,32,IFERROR(RANK(Valor_normalizado!I105,Valor_normalizado!I$98:I$129,0),"NA")) -> 17 | J105: =IF(Valor_normalizado!J105=0,32,IFERROR(RANK(Valor_normalizado!J105,Valor_normalizado!J$98:J$129,0),"NA")) -> 17 | ... Y105: =IF(Valor_normalizado!Y105=0,32,IFERROR(RANK(Valor_normalizado!Y105,Valor_normalizado!Y$98:Y$129,0),"NA")) -> 18
A106: Florencia | B106: 2022 | C106: =IF(Valor_normalizado!C106=0,32,IFERROR(RANK(Valor_normalizado!C106,Valor_normalizado!C$98:C$129,0),"NA")) -> 20 | D106: =IF(Valor_normalizado!D106=0,32,IFERROR(RANK(Valor_normalizado!D106,Valor_normalizado!D$98:D$129,0),"NA")) -> 23 | E106: =IF(Valor_normalizado!E106=0,32,IFERROR(RANK(Valor_normalizado!E106,Valor_normalizado!E$98:E$129,0),"NA")) -> 23 | F106: =IF(Valor_normalizado!F106=0,32,IFERROR(RANK(Valor_normalizado!F106,Valor_normalizado!F$98:F$129,0),"NA")) -> 21 | G106: =IF(Valor_normalizado!G106=0,32,IFERROR(RANK(Valor_normalizado!G106,Valor_normalizado!G$98:G$129,0),"NA")) -> 22 | H106: =IF(Valor_normalizado!H106=0,32,IFERROR(RANK(Valor_normalizado!H106,Valor_normalizado!H$98:H$129,0),"NA")) -> 18 | I106: =IF(Valor_normalizado!I106=0,32,IFERROR(RANK(Valor_normalizado!I106,Valor_normalizado!I$98:I$129,0),"NA")) -> 27 | J106: =IF(Valor_normalizado!J106=0,32,IFERROR(RANK(Valor_normalizado!J106,Valor_normalizado!J$98:J$129,0),"NA")) -> 4 | ... Y106: =IF(Valor_normalizado!Y106=0,32,IFERROR(RANK(Valor_normalizado!Y106,Valor_normalizado!Y$98:Y$129,0),"NA")) -> 22
A107: Ibagué | B107: 2022 | C107: =IF(Valor_normalizado!C107=0,32,IFERROR(RANK(Valor_normalizado!C107,Valor_normalizado!C$98:C$129,0),"NA")) -> 6 | D107: =IF(Valor_normalizado!D107=0,32,IFERROR(RANK(Valor_normalizado!D107,Valor_normalizado!D$98:D$129,0),"NA")) -> 10 | E107: =IF(Valor_normalizado!E107=0,32,IFERROR(RANK(Valor_normalizado!E107,Valor_normalizado!E$98:E$129,0),"NA")) -> 8 | F107: =IF(Valor_normalizado!F107=0,32,IFERROR(RANK(Valor_normalizado!F107,Valor_normalizado!F$98:F$129,0),"NA")) -> 9 | G107: =IF(Valor_normalizado!G107=0,32,IFERROR(RANK(Valor_normalizado!G107,Valor_normalizado!G$98:G$129,0),"NA")) -> 8 | H107: =IF(Valor_normalizado!H107=0,32,IFERROR(RANK(Valor_normalizado!H107,Valor_normalizado!H$98:H$129,0),"NA")) -> 10 | I107: =IF(Valor_normalizado!I107=0,32,IFERROR(RANK(Valor_normalizado!I107,Valor_normalizado!I$98:I$129,0),"NA")) -> 6 | J107: =IF(Valor_normalizado!J107=0,32,IFERROR(RANK(Valor_normalizado!J107,Valor_normalizado!J$98:J$129,0),"NA")) -> 15 | ... Y107: =IF(Valor_normalizado!Y107=0,32,IFERROR(RANK(Valor_normalizado!Y107,Valor_normalizado!Y$98:Y$129,0),"NA")) -> 11
A108: Inírida | B108: 2022 | C108: =IF(Valor_normalizado!C108=0,32,IFERROR(RANK(Valor_normalizado!C108,Valor_normalizado!C$98:C$129,0),"NA")) -> 30 | D108: =IF(Valor_normalizado!D108=0,32,IFERROR(RANK(Valor_normalizado!D108,Valor_normalizado!D$98:D$129,0),"NA")) -> 31 | E108: =IF(Valor_normalizado!E108=0,32,IFERROR(RANK(Valor_normalizado!E108,Valor_normalizado!E$98:E$129,0),"NA")) -> 29 | F108: =IF(Valor_normalizado!F108=0,32,IFERROR(RANK(Valor_normalizado!F108,Valor_normalizado!F$98:F$129,0),"NA")) -> 29 | G108: =IF(Valor_normalizado!G108=0,32,IFERROR(RANK(Valor_normalizado!G108,Valor_normalizado!G$98:G$129,0),"NA")) -> 29 | H108: =IF(Valor_normalizado!H108=0,32,IFERROR(RANK(Valor_normalizado!H108,Valor_normalizado!H$98:H$129,0),"NA")) -> 29 | I108: =IF(Valor_normalizado!I108=0,32,IFERROR(RANK(Valor_normalizado!I108,Valor_normalizado!I$98:I$129,0),"NA")) -> 24 | J108: =IF(Valor_normalizado!J108=0,32,IFERROR(RANK(Valor_normalizado!J108,Valor_normalizado!J$98:J$129,0),"NA")) -> 23 | ... Y108: =IF(Valor_normalizado!Y108=0,32,IFERROR(RANK(Valor_normalizado!Y108,Valor_normalizado!Y$98:Y$129,0),"NA")) -> 31
A109: Leticia | B109: 2022 | C109: =IF(Valor_normalizado!C109=0,32,IFERROR(RANK(Valor_normalizado!C109,Valor_normalizado!C$98:C$129,0),"NA")) -> 31 | D109: =IF(Valor_normalizado!D109=0,32,IFERROR(RANK(Valor_normalizado!D109,Valor_normalizado!D$98:D$129,0),"NA")) -> 30 | E109: =IF(Valor_normalizado!E109=0,32,IFERROR(RANK(Valor_normalizado!E109,Valor_normalizado!E$98:E$129,0),"NA")) -> 32 | F109: =IF(Valor_normalizado!F109=0,32,IFERROR(RANK(Valor_normalizado!F109,Valor_normalizado!F$98:F$129,0),"NA")) -> 32 | G109: =IF(Valor_normalizado!G109=0,32,IFERROR(RANK(Valor_normalizado!G109,Valor_normalizado!G$98:G$129,0),"NA")) -> 32 | H109: =IF(Valor_normalizado!H109=0,32,IFERROR(RANK(Valor_normalizado!H109,Valor_normalizado!H$98:H$129,0),"NA")) -> 30 | I109: =IF(Valor_normalizado!I109=0,32,IFERROR(RANK(Valor_normalizado!I109,Valor_normalizado!I$98:I$129,0),"NA")) -> 31 | J109: =IF(Valor_normalizado!J109=0,32,IFERROR(RANK(Valor_normalizado!J109,Valor_normalizado!J$98:J$129,0),"NA")) -> 28 | ... Y109: =IF(Valor_normalizado!Y109=0,32,IFERROR(RANK(Valor_normalizado!Y109,Valor_normalizado!Y$98:Y$129,0),"NA")) -> 28
... A129: Yopal | B129: 2022 | C129: =IF(Valor_normalizado!C129=0,32,IFERROR(RANK(Valor_normalizado!C129,Valor_normalizado!C$98:C$129,0),"NA")) -> 12 | D129: =IF(Valor_normalizado!D129=0,32,IFERROR(RANK(Valor_normalizado!D129,Valor_normalizado!D$98:D$129,0),"NA")) -> 22 | E129: =IF(Valor_normalizado!E129=0,32,IFERROR(RANK(Valor_normalizado!E129,Valor_normalizado!E$98:E$129,0),"NA")) -> 16 | F129: =IF(Valor_normalizado!F129=0,32,IFERROR(RANK(Valor_normalizado!F129,Valor_normalizado!F$98:F$129,0),"NA")) -> 18 | G129: =IF(Valor_normalizado!G129=0,32,IFERROR(RANK(Valor_normalizado!G129,Valor_normalizado!G$98:G$129,0),"NA")) -> 15 | H129: =IF(Valor_normalizado!H129=0,32,IFERROR(RANK(Valor_normalizado!H129,Valor_normalizado!H$98:H$129,0),"NA")) -> 20 | I129: =IF(Valor_normalizado!I129=0,32,IFERROR(RANK(Valor_normalizado!I129,Valor_normalizado!I$98:I$129,0),"NA")) -> 20 | J129: =IF(Valor_normalizado!J129=0,32,IFERROR(RANK(Valor_normalizado!J129,Valor_normalizado!J$98:J$129,0),"NA")) -> 27 | ... Y129: =IF(Valor_normalizado!Y129=0,32,IFERROR(RANK(Valor_normalizado!Y129,Valor_normalizado!Y$98:Y$129,0),"NA")) -> 20
A130: Bogotá D.C. | B130: 2023 | C130: =IF(Valor_normalizado!C133=0,32,IFERROR(RANK(Valor_normalizado!C133,Valor_normalizado!C$130:C$161,0),"NA")) -> 4 | D130: =IF(Valor_normalizado!D133=0,32,IFERROR(RANK(Valor_normalizado!D133,Valor_normalizado!D$130:D$161,0),"NA")) -> 11 | E130: =IF(Valor_normalizado!E133=0,32,IFERROR(RANK(Valor_normalizado!E133,Valor_normalizado!E$130:E$161,0),"NA")) -> 10 | F130: =IF(Valor_normalizado!F133=0,32,IFERROR(RANK(Valor_normalizado!F133,Valor_normalizado!F$130:F$161,0),"NA")) -> 13 | G130: =IF(Valor_normalizado!G133=0,32,IFERROR(RANK(Valor_normalizado!G133,Valor_normalizado!G$130:G$161,0),"NA")) -> 9 | H130: =IF(Valor_normalizado!H133=0,32,IFERROR(RANK(Valor_normalizado!H133,Valor_normalizado!H$130:H$161,0),"NA")) -> 1 | I130: =IF(Valor_normalizado!I133=0,32,IFERROR(RANK(Valor_normalizado!I133,Valor_normalizado!I$130:I$161,0),"NA")) -> 1 | J130: =IF(Valor_normalizado!J133=0,32,IFERROR(RANK(Valor_normalizado!J133,Valor_normalizado!J$130:J$161,0),"NA")) -> 1 | ... Y130: =IF(Valor_normalizado!Y133=0,32,IFERROR(RANK(Valor_normalizado!Y133,Valor_normalizado!Y$130:Y$161,0),"NA")) -> 3
A131: Tunja | B131: 2023 | C131: =IF(Valor_normalizado!C158=0,32,IFERROR(RANK(Valor_normalizado!C158,Valor_normalizado!C$130:C$161,0),"NA")) -> 26 | D131: =IF(Valor_normalizado!D158=0,32,IFERROR(RANK(Valor_normalizado!D158,Valor_normalizado!D$130:D$161,0),"NA")) -> 27 | E131: =IF(Valor_normalizado!E158=0,32,IFERROR(RANK(Valor_normalizado!E158,Valor_normalizado!E$130:E$161,0),"NA")) -> 31 | F131: =IF(Valor_normalizado!F158=0,32,IFERROR(RANK(Valor_normalizado!F158,Valor_normalizado!F$130:F$161,0),"NA")) -> 22 | G131: =IF(Valor_normalizado!G158=0,32,IFERROR(RANK(Valor_normalizado!G158,Valor_normalizado!G$130:G$161,0),"NA")) -> 26 | H131: =IF(Valor_normalizado!H158=0,32,IFERROR(RANK(Valor_normalizado!H158,Valor_normalizado!H$130:H$161,0),"NA")) -> 30 | I131: =IF(Valor_normalizado!I158=0,32,IFERROR(RANK(Valor_normalizado!I158,Valor_normalizado!I$130:I$161,0),"NA")) -> 30 | J131: =IF(Valor_normalizado!J158=0,32,IFERROR(RANK(Valor_normalizado!J158,Valor_normalizado!J$130:J$161,0),"NA")) -> 29 | ... Y131: =IF(Valor_normalizado!Y158=0,32,IFERROR(RANK(Valor_normalizado!Y158,Valor_normalizado!Y$130:Y$161,0),"NA")) -> 26
A132: Manizales AM | B132: 2023 | C132: =IF(Valor_normalizado!C142=0,32,IFERROR(RANK(Valor_normalizado!C142,Valor_normalizado!C$130:C$161,0),"NA")) -> 16 | D132: =IF(Valor_normalizado!D142=0,32,IFERROR(RANK(Valor_normalizado!D142,Valor_normalizado!D$130:D$161,0),"NA")) -> 14 | E132: =IF(Valor_normalizado!E142=0,32,IFERROR(RANK(Valor_normalizado!E142,Valor_normalizado!E$130:E$161,0),"NA")) -> 27 | F132: =IF(Valor_normalizado!F142=0,32,IFERROR(RANK(Valor_normalizado!F142,Valor_normalizado!F$130:F$161,0),"NA")) -> 24 | G132: =IF(Valor_normalizado!G142=0,32,IFERROR(RANK(Valor_normalizado!G142,Valor_normalizado!G$130:G$161,0),"NA")) -> 20 | H132: =IF(Valor_normalizado!H142=0,32,IFERROR(RANK(Valor_normalizado!H142,Valor_normalizado!H$130:H$161,0),"NA")) -> 20 | I132: =IF(Valor_normalizado!I142=0,32,IFERROR(RANK(Valor_normalizado!I142,Valor_normalizado!I$130:I$161,0),"NA")) -> 19 | J132: =IF(Valor_normalizado!J142=0,32,IFERROR(RANK(Valor_normalizado!J142,Valor_normalizado!J$130:J$161,0),"NA")) -> 13 | ... Y132: =IF(Valor_normalizado!Y142=0,32,IFERROR(RANK(Valor_normalizado!Y142,Valor_normalizado!Y$130:Y$161,0),"NA")) -> 15
A133: Medellín AM | B133: 2023 | C133: =IF(Valor_normalizado!C143=0,32,IFERROR(RANK(Valor_normalizado!C143,Valor_normalizado!C$130:C$161,0),"NA")) -> 17 | D133: =IF(Valor_normalizado!D143=0,32,IFERROR(RANK(Valor_normalizado!D143,Valor_normalizado!D$130:D$161,0),"NA")) -> 9 | E133: =IF(Valor_normalizado!E143=0,32,IFERROR(RANK(Valor_normalizado!E143,Valor_normalizado!E$130:E$161,0),"NA")) -> 20 | F133: =IF(Valor_normalizado!F143=0,32,IFERROR(RANK(Valor_normalizado!F143,Valor_normalizado!F$130:F$161,0),"NA")) -> 18 | G133: =IF(Valor_normalizado!G143=0,32,IFERROR(RANK(Valor_normalizado!G143,Valor_normalizado!G$130:G$161,0),"NA")) -> 15 | H133: =IF(Valor_normalizado!H143=0,32,IFERROR(RANK(Valor_normalizado!H143,Valor_normalizado!H$130:H$161,0),"NA")) -> 19 | I133: =IF(Valor_normalizado!I143=0,32,IFERROR(RANK(Valor_normalizado!I143,Valor_normalizado!I$130:I$161,0),"NA")) -> 14 | J133: =IF(Valor_normalizado!J143=0,32,IFERROR(RANK(Valor_normalizado!J143,Valor_normalizado!J$130:J$161,0),"NA")) -> 15 | ... Y133: =IF(Valor_normalizado!Y143=0,32,IFERROR(RANK(Valor_normalizado!Y143,Valor_normalizado!Y$130:Y$161,0),"NA")) -> 11
A134: Pereira AM | B134: 2023 | C134: =IF(Valor_normalizado!C149=0,32,IFERROR(RANK(Valor_normalizado!C149,Valor_normalizado!C$130:C$161,0),"NA")) -> 12 | D134: =IF(Valor_normalizado!D149=0,32,IFERROR(RANK(Valor_normalizado!D149,Valor_normalizado!D$130:D$161,0),"NA")) -> 4 | E134: =IF(Valor_normalizado!E149=0,32,IFERROR(RANK(Valor_normalizado!E149,Valor_normalizado!E$130:E$161,0),"NA")) -> 13 | F134: =IF(Valor_normalizado!F149=0,32,IFERROR(RANK(Valor_normalizado!F149,Valor_normalizado!F$130:F$161,0),"NA")) -> 1 | G134: =IF(Valor_normalizado!G149=0,32,IFERROR(RANK(Valor_normalizado!G149,Valor_normalizado!G$130:G$161,0),"NA")) -> 10 | H134: =IF(Valor_normalizado!H149=0,32,IFERROR(RANK(Valor_normalizado!H149,Valor_normalizado!H$130:H$161,0),"NA")) -> 23 | I134: =IF(Valor_normalizado!I149=0,32,IFERROR(RANK(Valor_normalizado!I149,Valor_normalizado!I$130:I$161,0),"NA")) -> 23 | J134: =IF(Valor_normalizado!J149=0,32,IFERROR(RANK(Valor_normalizado!J149,Valor_normalizado!J$130:J$161,0),"NA")) -> 22 | ... Y134: =IF(Valor_normalizado!Y149=0,32,IFERROR(RANK(Valor_normalizado!Y149,Valor_normalizado!Y$130:Y$161,0),"NA")) -> 16
A135: Bucaramanga AM | B135: 2023 | C135: =IF(Valor_normalizado!C134=0,32,IFERROR(RANK(Valor_normalizado!C134,Valor_normalizado!C$130:C$161,0),"NA")) -> 1 | D135: =IF(Valor_normalizado!D134=0,32,IFERROR(RANK(Valor_normalizado!D134,Valor_normalizado!D$130:D$161,0),"NA")) -> 8 | E135: =IF(Valor_normalizado!E134=0,32,IFERROR(RANK(Valor_normalizado!E134,Valor_normalizado!E$130:E$161,0),"NA")) -> 5 | F135: =IF(Valor_normalizado!F134=0,32,IFERROR(RANK(Valor_normalizado!F134,Valor_normalizado!F$130:F$161,0),"NA")) -> 8 | G135: =IF(Valor_normalizado!G134=0,32,IFERROR(RANK(Valor_normalizado!G134,Valor_normalizado!G$130:G$161,0),"NA")) -> 5 | H135: =IF(Valor_normalizado!H134=0,32,IFERROR(RANK(Valor_normalizado!H134,Valor_normalizado!H$130:H$161,0),"NA")) -> 4 | I135: =IF(Valor_normalizado!I134=0,32,IFERROR(RANK(Valor_normalizado!I134,Valor_normalizado!I$130:I$161,0),"NA")) -> 6 | J135: =IF(Valor_normalizado!J134=0,32,IFERROR(RANK(Valor_normalizado!J134,Valor_normalizado!J$130:J$161,0),"NA")) -> 25 | ... Y135: =IF(Valor_normalizado!Y134=0,32,IFERROR(RANK(Valor_normalizado!Y134,Valor_normalizado!Y$130:Y$161,0),"NA")) -> 10
A136: Armenia | B136: 2023 | C136: =IF(Valor_normalizado!C131=0,32,IFERROR(RANK(Valor_normalizado!C131,Valor_normalizado!C$130:C$161,0),"NA")) -> 3 | D136: =IF(Valor_normalizado!D131=0,32,IFERROR(RANK(Valor_normalizado!D131,Valor_normalizado!D$130:D$161,0),"NA")) -> 2 | E136: =IF(Valor_normalizado!E131=0,32,IFERROR(RANK(Valor_normalizado!E131,Valor_normalizado!E$130:E$161,0),"NA")) -> 1 | F136: =IF(Valor_normalizado!F131=0,32,IFERROR(RANK(Valor_normalizado!F131,Valor_normalizado!F$130:F$161,0),"NA")) -> 2 | G136: =IF(Valor_normalizado!G131=0,32,IFERROR(RANK(Valor_normalizado!G131,Valor_normalizado!G$130:G$161,0),"NA")) -> 1 | H136: =IF(Valor_normalizado!H131=0,32,IFERROR(RANK(Valor_normalizado!H131,Valor_normalizado!H$130:H$161,0),"NA")) -> 2 | I136: =IF(Valor_normalizado!I131=0,32,IFERROR(RANK(Valor_normalizado!I131,Valor_normalizado!I$130:I$161,0),"NA")) -> 2 | J136: =IF(Valor_normalizado!J131=0,32,IFERROR(RANK(Valor_normalizado!J131,Valor_normalizado!J$130:J$161,0),"NA")) -> 2 | ... Y136: =IF(Valor_normalizado!Y131=0,32,IFERROR(RANK(Valor_normalizado!Y131,Valor_normalizado!Y$130:Y$161,0),"NA")) -> 1
A137: Popayán | B137: 2023 | C137: =IF(Valor_normalizado!C150=0,32,IFERROR(RANK(Valor_normalizado!C150,Valor_normalizado!C$130:C$161,0),"NA")) -> 21 | D137: =IF(Valor_normalizado!D150=0,32,IFERROR(RANK(Valor_normalizado!D150,Valor_normalizado!D$130:D$161,0),"NA")) -> 21 | E137: =IF(Valor_normalizado!E150=0,32,IFERROR(RANK(Valor_normalizado!E150,Valor_normalizado!E$130:E$161,0),"NA")) -> 21 | F137: =IF(Valor_normalizado!F150=0,32,IFERROR(RANK(Valor_normalizado!F150,Valor_normalizado!F$130:F$161,0),"NA")) -> 25 | G137: =IF(Valor_normalizado!G150=0,32,IFERROR(RANK(Valor_normalizado!G150,Valor_normalizado!G$130:G$161,0),"NA")) -> 21 | H137: =IF(Valor_normalizado!H150=0,32,IFERROR(RANK(Valor_normalizado!H150,Valor_normalizado!H$130:H$161,0),"NA")) -> 21 | I137: =IF(Valor_normalizado!I150=0,32,IFERROR(RANK(Valor_normalizado!I150,Valor_normalizado!I$130:I$161,0),"NA")) -> 17 | J137: =IF(Valor_normalizado!J150=0,32,IFERROR(RANK(Valor_normalizado!J150,Valor_normalizado!J$130:J$161,0),"NA")) -> 16 | ... Y137: =IF(Valor_normalizado!Y150=0,32,IFERROR(RANK(Valor_normalizado!Y150,Valor_normalizado!Y$130:Y$161,0),"NA")) -> 22
A138: Ibagué | B138: 2023 | C138: =IF(Valor_normalizado!C139=0,32,IFERROR(RANK(Valor_normalizado!C139,Valor_normalizado!C$130:C$161,0),"NA")) -> 14 | D138: =IF(Valor_normalizado!D139=0,32,IFERROR(RANK(Valor_normalizado!D139,Valor_normalizado!D$130:D$161,0),"NA")) -> 10 | E138: =IF(Valor_normalizado!E139=0,32,IFERROR(RANK(Valor_normalizado!E139,Valor_normalizado!E$130:E$161,0),"NA")) -> 11 | F138: =IF(Valor_normalizado!F139=0,32,IFERROR(RANK(Valor_normalizado!F139,Valor_normalizado!F$130:F$161,0),"NA")) -> 15 | G138: =IF(Valor_normalizado!G139=0,32,IFERROR(RANK(Valor_normalizado!G139,Valor_normalizado!G$130:G$161,0),"NA")) -> 11 | H138: =IF(Valor_normalizado!H139=0,32,IFERROR(RANK(Valor_normalizado!H139,Valor_normalizado!H$130:H$161,0),"NA")) -> 13 | I138: =IF(Valor_normalizado!I139=0,32,IFERROR(RANK(Valor_normalizado!I139,Valor_normalizado!I$130:I$161,0),"NA")) -> 11 | J138: =IF(Valor_normalizado!J139=0,32,IFERROR(RANK(Valor_normalizado!J139,Valor_normalizado!J$130:J$161,0),"NA")) -> 7 | ... Y138: =IF(Valor_normalizado!Y139=0,32,IFERROR(RANK(Valor_normalizado!Y139,Valor_normalizado!Y$130:Y$161,0),"NA")) -> 8
A139: Cali AM | B139: 2023 | C139: =IF(Valor_normalizado!C135=0,32,IFERROR(RANK(Valor_normalizado!C135,Valor_normalizado!C$130:C$161,0),"NA")) -> 7 | D139: =IF(Valor_normalizado!D135=0,32,IFERROR(RANK(Valor_normalizado!D135,Valor_normalizado!D$130:D$161,0),"NA")) -> 3 | E139: =IF(Valor_normalizado!E135=0,32,IFERROR(RANK(Valor_normalizado!E135,Valor_normalizado!E$130:E$161,0),"NA")) -> 3 | F139: =IF(Valor_normalizado!F135=0,32,IFERROR(RANK(Valor_normalizado!F135,Valor_normalizado!F$130:F$161,0),"NA")) -> 4 | G139: =IF(Valor_normalizado!G135=0,32,IFERROR(RANK(Valor_normalizado!G135,Valor_normalizado!G$130:G$161,0),"NA")) -> 3 | H139: =IF(Valor_normalizado!H135=0,32,IFERROR(RANK(Valor_normalizado!H135,Valor_normalizado!H$130:H$161,0),"NA")) -> 8 | I139: =IF(Valor_normalizado!I135=0,32,IFERROR(RANK(Valor_normalizado!I135,Valor_normalizado!I$130:I$161,0),"NA")) -> 10 | J139: =IF(Valor_normalizado!J135=0,32,IFERROR(RANK(Valor_normalizado!J135,Valor_normalizado!J$130:J$161,0),"NA")) -> 8 | ... Y139: =IF(Valor_normalizado!Y135=0,32,IFERROR(RANK(Valor_normalizado!Y135,Valor_normalizado!Y$130:Y$161,0),"NA")) -> 6
A140: Barranquilla AM | B140: 2023 | C140: =IF(Valor_normalizado!C132=0,32,IFERROR(RANK(Valor_normalizado!C132,Valor_normalizado!C$130:C$161,0),"NA")) -> 2 | D140: =IF(Valor_normalizado!D132=0,32,IFERROR(RANK(Valor_normalizado!D132,Valor_normalizado!D$130:D$161,0),"NA")) -> 1 | E140: =IF(Valor_normalizado!E132=0,32,IFERROR(RANK(Valor_normalizado!E132,Valor_normalizado!E$130:E$161,0),"NA")) -> 6 | F140: =IF(Valor_normalizado!F132=0,32,IFERROR(RANK(Valor_normalizado!F132,Valor_normalizado!F$130:F$161,0),"NA")) -> 10 | G140: =IF(Valor_normalizado!G132=0,32,IFERROR(RANK(Valor_normalizado!G132,Valor_normalizado!G$130:G$161,0),"NA")) -> 2 | H140: =IF(Valor_normalizado!H132=0,32,IFERROR(RANK(Valor_normalizado!H132,Valor_normalizado!H$130:H$161,0),"NA")) -> 7 | I140: =IF(Valor_normalizado!I132=0,32,IFERROR(RANK(Valor_normalizado!I132,Valor_normalizado!I$130:I$161,0),"NA")) -> 9 | J140: =IF(Valor_normalizado!J132=0,32,IFERROR(RANK(Valor_normalizado!J132,Valor_normalizado!J$130:J$161,0),"NA")) -> 4 | ... Y140: =IF(Valor_normalizado!Y132=0,32,IFERROR(RANK(Valor_normalizado!Y132,Valor_normalizado!Y$130:Y$161,0),"NA")) -> 2
A141: Pasto | B141: 2023 | C141: =IF(Valor_normalizado!C148=0,32,IFERROR(RANK(Valor_normalizado!C148,Valor_normalizado!C$130:C$161,0),"NA")) -> 20 | D141: =IF(Valor_normalizado!D148=0,32,IFERROR(RANK(Valor_normalizado!D148,Valor_normalizado!D$130:D$161,0),"NA")) -> 19 | E141: =IF(Valor_normalizado!E148=0,32,IFERROR(RANK(Valor_normalizado!E148,Valor_normalizado!E$130:E$161,0),"NA")) -> 16 | F141: =IF(Valor_normalizado!F148=0,32,IFERROR(RANK(Valor_normalizado!F148,Valor_normalizado!F$130:F$161,0),"NA")) -> 11 | G141: =IF(Valor_normalizado!G148=0,32,IFERROR(RANK(Valor_normalizado!G148,Valor_normalizado!G$130:G$161,0),"NA")) -> 18 | H141: =IF(Valor_normalizado!H148=0,32,IFERROR(RANK(Valor_normalizado!H148,Valor_normalizado!H$130:H$161,0),"NA")) -> 14 | I141: =IF(Valor_normalizado!I148=0,32,IFERROR(RANK(Valor_normalizado!I148,Valor_normalizado!I$130:I$161,0),"NA")) -> 18 | J141: =IF(Valor_normalizado!J148=0,32,IFERROR(RANK(Valor_normalizado!J148,Valor_normalizado!J$130:J$161,0),"NA")) -> 17 | ... Y141: =IF(Valor_normalizado!Y148=0,32,IFERROR(RANK(Valor_normalizado!Y148,Valor_normalizado!Y$130:Y$161,0),"NA")) -> 17
A142: Neiva | B142: 2023 | C142: =IF(Valor_normalizado!C147=0,32,IFERROR(RANK(Valor_normalizado!C147,Valor_normalizado!C$130:C$161,0),"NA")) -> 22 | D142: =IF(Valor_normalizado!D147=0,32,IFERROR(RANK(Valor_normalizado!D147,Valor_normalizado!D$130:D$161,0),"NA")) -> 20 | E142: =IF(Valor_normalizado!E147=0,32,IFERROR(RANK(Valor_normalizado!E147,Valor_normalizado!E$130:E$161,0),"NA")) -> 26 | F142: =IF(Valor_normalizado!F147=0,32,IFERROR(RANK(Valor_normalizado!F147,Valor_normalizado!F$130:F$161,0),"NA")) -> 23 | G142: =IF(Valor_normalizado!G147=0,32,IFERROR(RANK(Valor_normalizado!G147,Valor_normalizado!G$130:G$161,0),"NA")) -> 23 | H142: =IF(Valor_normalizado!H147=0,32,IFERROR(RANK(Valor_normalizado!H147,Valor_normalizado!H$130:H$161,0),"NA")) -> 24 | I142: =IF(Valor_normalizado!I147=0,32,IFERROR(RANK(Valor_normalizado!I147,Valor_normalizado!I$130:I$161,0),"NA")) -> 21 | J142: =IF(Valor_normalizado!J147=0,32,IFERROR(RANK(Valor_normalizado!J147,Valor_normalizado!J$130:J$161,0),"NA")) -> 19 | ... Y142: =IF(Valor_normalizado!Y147=0,32,IFERROR(RANK(Valor_normalizado!Y147,Valor_normalizado!Y$130:Y$161,0),"NA")) -> 24
A143: Villavicencio | B143: 2023 | C143: =IF(Valor_normalizado!C160=0,32,IFERROR(RANK(Valor_normalizado!C160,Valor_normalizado!C$130:C$161,0),"NA")) -> 29 | D143: =IF(Valor_normalizado!D160=0,32,IFERROR(RANK(Valor_normalizado!D160,Valor_normalizado!D$130:D$161,0),"NA")) -> 26 | E143: =IF(Valor_normalizado!E160=0,32,IFERROR(RANK(Valor_normalizado!E160,Valor_normalizado!E$130:E$161,0),"NA")) -> 19 | F143: =IF(Valor_normalizado!F160=0,32,IFERROR(RANK(Valor_normalizado!F160,Valor_normalizado!F$130:F$161,0),"NA")) -> 26 | G143: =IF(Valor_normalizado!G160=0,32,IFERROR(RANK(Valor_normalizado!G160,Valor_normalizado!G$130:G$161,0),"NA")) -> 27 | H143: =IF(Valor_normalizado!H160=0,32,IFERROR(RANK(Valor_normalizado!H160,Valor_normalizado!H$130:H$161,0),"NA")) -> 26 | I143: =IF(Valor_normalizado!I160=0,32,IFERROR(RANK(Valor_normalizado!I160,Valor_normalizado!I$130:I$161,0),"NA")) -> 28 | J143: =IF(Valor_normalizado!J160=0,32,IFERROR(RANK(Valor_normalizado!J160,Valor_normalizado!J$130:J$161,0),"NA")) -> 9 | ... Y143: =IF(Valor_normalizado!Y160=0,32,IFERROR(RANK(Valor_normalizado!Y160,Valor_normalizado!Y$130:Y$161,0),"NA")) -> 28
A144: Cartagena | B144: 2023 | C144: =IF(Valor_normalizado!C136=0,32,IFERROR(RANK(Valor_normalizado!C136,Valor_normalizado!C$130:C$161,0),"NA")) -> 13 | D144: =IF(Valor_normalizado!D136=0,32,IFERROR(RANK(Valor_normalizado!D136,Valor_normalizado!D$130:D$161,0),"NA")) -> 18 | E144: =IF(Valor_normalizado!E136=0,32,IFERROR(RANK(Valor_normalizado!E136,Valor_normalizado!E$130:E$161,0),"NA")) -> 12 | F144: =IF(Valor_normalizado!F136=0,32,IFERROR(RANK(Valor_normalizado!F136,Valor_normalizado!F$130:F$161,0),"NA")) -> 14 | G144: =IF(Valor_normalizado!G136=0,32,IFERROR(RANK(Valor_normalizado!G136,Valor_normalizado!G$130:G$161,0),"NA")) -> 14 | H144: =IF(Valor_normalizado!H136=0,32,IFERROR(RANK(Valor_normalizado!H136,Valor_normalizado!H$130:H$161,0),"NA")) -> 3 | I144: =IF(Valor_normalizado!I136=0,32,IFERROR(RANK(Valor_normalizado!I136,Valor_normalizado!I$130:I$161,0),"NA")) -> 5 | J144: =IF(Valor_normalizado!J136=0,32,IFERROR(RANK(Valor_normalizado!J136,Valor_normalizado!J$130:J$161,0),"NA")) -> 11 | ... Y144: =IF(Valor_normalizado!Y136=0,32,IFERROR(RANK(Valor_normalizado!Y136,Valor_normalizado!Y$130:Y$161,0),"NA")) -> 9
A145: Cúcuta AM | B145: 2023 | C145: =IF(Valor_normalizado!C137=0,32,IFERROR(RANK(Valor_normalizado!C137,Valor_normalizado!C$130:C$161,0),"NA")) -> 9 | D145: =IF(Valor_normalizado!D137=0,32,IFERROR(RANK(Valor_normalizado!D137,Valor_normalizado!D$130:D$161,0),"NA")) -> 6 | E145: =IF(Valor_normalizado!E137=0,32,IFERROR(RANK(Valor_normalizado!E137,Valor_normalizado!E$130:E$161,0),"NA")) -> 4 | F145: =IF(Valor_normalizado!F137=0,32,IFERROR(RANK(Valor_normalizado!F137,Valor_normalizado!F$130:F$161,0),"NA")) -> 3 | G145: =IF(Valor_normalizado!G137=0,32,IFERROR(RANK(Valor_normalizado!G137,Valor_normalizado!G$130:G$161,0),"NA")) -> 4 | H145: =IF(Valor_normalizado!H137=0,32,IFERROR(RANK(Valor_normalizado!H137,Valor_normalizado!H$130:H$161,0),"NA")) -> 16 | I145: =IF(Valor_normalizado!I137=0,32,IFERROR(RANK(Valor_normalizado!I137,Valor_normalizado!I$130:I$161,0),"NA")) -> 16 | J145: =IF(Valor_normalizado!J137=0,32,IFERROR(RANK(Valor_normalizado!J137,Valor_normalizado!J$130:J$161,0),"NA")) -> 10 | ... Y145: =IF(Valor_normalizado!Y137=0,32,IFERROR(RANK(Valor_normalizado!Y137,Valor_normalizado!Y$130:Y$161,0),"NA")) -> 4
A146: Santa Marta | B146: 2023 | C146: =IF(Valor_normalizado!C156=0,32,IFERROR(RANK(Valor_normalizado!C156,Valor_normalizado!C$130:C$161,0),"NA")) -> 19 | D146: =IF(Valor_normalizado!D156=0,32,IFERROR(RANK(Valor_normalizado!D156,Valor_normalizado!D$130:D$161,0),"NA")) -> 24 | E146: =IF(Valor_normalizado!E156=0,32,IFERROR(RANK(Valor_normalizado!E156,Valor_normalizado!E$130:E$161,0),"NA")) -> 18 | F146: =IF(Valor_normalizado!F156=0,32,IFERROR(RANK(Valor_normalizado!F156,Valor_normalizado!F$130:F$161,0),"NA")) -> 20 | G146: =IF(Valor_normalizado!G156=0,32,IFERROR(RANK(Valor_normalizado!G156,Valor_normalizado!G$130:G$161,0),"NA")) -> 22 | H146: =IF(Valor_normalizado!H156=0,32,IFERROR(RANK(Valor_normalizado!H156,Valor_normalizado!H$130:H$161,0),"NA")) -> 15 | I146: =IF(Valor_normalizado!I156=0,32,IFERROR(RANK(Valor_normalizado!I156,Valor_normalizado!I$130:I$161,0),"NA")) -> 26 | J146: =IF(Valor_normalizado!J156=0,32,IFERROR(RANK(Valor_normalizado!J156,Valor_normalizado!J$130:J$161,0),"NA")) -> 5 | ... Y146: =IF(Valor_normalizado!Y156=0,32,IFERROR(RANK(Valor_normalizado!Y156,Valor_normalizado!Y$130:Y$161,0),"NA")) -> 23
A147: Yopal | B147: 2023 | C147: =IF(Valor_normalizado!C161=0,32,IFERROR(RANK(Valor_normalizado!C161,Valor_normalizado!C$130:C$161,0),"NA")) -> 28 | D147: =IF(Valor_normalizado!D161=0,32,IFERROR(RANK(Valor_normalizado!D161,Valor_normalizado!D$130:D$161,0),"NA")) -> 31 | E147: =IF(Valor_normalizado!E161=0,32,IFERROR(RANK(Valor_normalizado!E161,Valor_normalizado!E$130:E$161,0),"NA")) -> 32 | F147: =IF(Valor_normalizado!F161=0,32,IFERROR(RANK(Valor_normalizado!F161,Valor_normalizado!F$130:F$161,0),"NA")) -> 32 | G147: =IF(Valor_normalizado!G161=0,32,IFERROR(RANK(Valor_normalizado!G161,Valor_normalizado!G$130:G$161,0),"NA")) -> 32 | H147: =IF(Valor_normalizado!H161=0,32,IFERROR(RANK(Valor_normalizado!H161,Valor_normalizado!H$130:H$161,0),"NA")) -> 27 | I147: =IF(Valor_normalizado!I161=0,32,IFERROR(RANK(Valor_normalizado!I161,Valor_normalizado!I$130:I$161,0),"NA")) -> 25 | J147: =IF(Valor_normalizado!J161=0,32,IFERROR(RANK(Valor_normalizado!J161,Valor_normalizado!J$130:J$161,0),"NA")) -> 22 | ... Y147: =IF(Valor_normalizado!Y161=0,32,IFERROR(RANK(Valor_normalizado!Y161,Valor_normalizado!Y$130:Y$161,0),"NA")) -> 30
A148: Florencia | B148: 2023 | C148: =IF(Valor_normalizado!C138=0,32,IFERROR(RANK(Valor_normalizado!C138,Valor_normalizado!C$130:C$161,0),"NA")) -> 8 | D148: =IF(Valor_normalizado!D138=0,32,IFERROR(RANK(Valor_normalizado!D138,Valor_normalizado!D$130:D$161,0),"NA")) -> 12 | E148: =IF(Valor_normalizado!E138=0,32,IFERROR(RANK(Valor_normalizado!E138,Valor_normalizado!E$130:E$161,0),"NA")) -> 7 | F148: =IF(Valor_normalizado!F138=0,32,IFERROR(RANK(Valor_normalizado!F138,Valor_normalizado!F$130:F$161,0),"NA")) -> 9 | G148: =IF(Valor_normalizado!G138=0,32,IFERROR(RANK(Valor_normalizado!G138,Valor_normalizado!G$130:G$161,0),"NA")) -> 8 | H148: =IF(Valor_normalizado!H138=0,32,IFERROR(RANK(Valor_normalizado!H138,Valor_normalizado!H$130:H$161,0),"NA")) -> 5 | I148: =IF(Valor_normalizado!I138=0,32,IFERROR(RANK(Valor_normalizado!I138,Valor_normalizado!I$130:I$161,0),"NA")) -> 4 | J148: =IF(Valor_normalizado!J138=0,32,IFERROR(RANK(Valor_normalizado!J138,Valor_normalizado!J$130:J$161,0),"NA")) -> 14 | ... Y148: =IF(Valor_normalizado!Y138=0,32,IFERROR(RANK(Valor_normalizado!Y138,Valor_normalizado!Y$130:Y$161,0),"NA")) -> 7
A149: Valledupar | B149: 2023 | C149: =IF(Valor_normalizado!C159=0,32,IFERROR(RANK(Valor_normalizado!C159,Valor_normalizado!C$130:C$161,0),"NA")) -> 32 | D149: =IF(Valor_normalizado!D159=0,32,IFERROR(RANK(Valor_normalizado!D159,Valor_normalizado!D$130:D$161,0),"NA")) -> 25 | E149: =IF(Valor_normalizado!E159=0,32,IFERROR(RANK(Valor_normalizado!E159,Valor_normalizado!E$130:E$161,0),"NA")) -> 22 | F149: =IF(Valor_normalizado!F159=0,32,IFERROR(RANK(Valor_normalizado!F159,Valor_normalizado!F$130:F$161,0),"NA")) -> 31 | G149: =IF(Valor_normalizado!G159=0,32,IFERROR(RANK(Valor_normalizado!G159,Valor_normalizado!G$130:G$161,0),"NA")) -> 29 | H149: =IF(Valor_normalizado!H159=0,32,IFERROR(RANK(Valor_normalizado!H159,Valor_normalizado!H$130:H$161,0),"NA")) -> 32 | I149: =IF(Valor_normalizado!I159=0,32,IFERROR(RANK(Valor_normalizado!I159,Valor_normalizado!I$130:I$161,0),"NA")) -> 32 | J149: =IF(Valor_normalizado!J159=0,32,IFERROR(RANK(Valor_normalizado!J159,Valor_normalizado!J$130:J$161,0),"NA")) -> 32 | ... Y149: =IF(Valor_normalizado!Y159=0,32,IFERROR(RANK(Valor_normalizado!Y159,Valor_normalizado!Y$130:Y$161,0),"NA")) -> 31
A150: Sincelejo | B150: 2023 | C150: =IF(Valor_normalizado!C157=0,32,IFERROR(RANK(Valor_normalizado!C157,Valor_normalizado!C$130:C$161,0),"NA")) -> 27 | D150: =IF(Valor_normalizado!D157=0,32,IFERROR(RANK(Valor_normalizado!D157,Valor_normalizado!D$130:D$161,0),"NA")) -> 28 | E150: =IF(Valor_normalizado!E157=0,32,IFERROR(RANK(Valor_normalizado!E157,Valor_normalizado!E$130:E$161,0),"NA")) -> 24 | F150: =IF(Valor_normalizado!F157=0,32,IFERROR(RANK(Valor_normalizado!F157,Valor_normalizado!F$130:F$161,0),"NA")) -> 28 | G150: =IF(Valor_normalizado!G157=0,32,IFERROR(RANK(Valor_normalizado!G157,Valor_normalizado!G$130:G$161,0),"NA")) -> 28 | H150: =IF(Valor_normalizado!H157=0,32,IFERROR(RANK(Valor_normalizado!H157,Valor_normalizado!H$130:H$161,0),"NA")) -> 25 | I150: =IF(Valor_normalizado!I157=0,32,IFERROR(RANK(Valor_normalizado!I157,Valor_normalizado!I$130:I$161,0),"NA")) -> 20 | J150: =IF(Valor_normalizado!J157=0,32,IFERROR(RANK(Valor_normalizado!J157,Valor_normalizado!J$130:J$161,0),"NA")) -> 29 | ... Y150: =IF(Valor_normalizado!Y157=0,32,IFERROR(RANK(Valor_normalizado!Y157,Valor_normalizado!Y$130:Y$161,0),"NA")) -> 27
A151: Montería | B151: 2023 | C151: =IF(Valor_normalizado!C146=0,32,IFERROR(RANK(Valor_normalizado!C146,Valor_normalizado!C$130:C$161,0),"NA")) -> 31 | D151: =IF(Valor_normalizado!D146=0,32,IFERROR(RANK(Valor_normalizado!D146,Valor_normalizado!D$130:D$161,0),"NA")) -> 29 | E151: =IF(Valor_normalizado!E146=0,32,IFERROR(RANK(Valor_normalizado!E146,Valor_normalizado!E$130:E$161,0),"NA")) -> 25 | F151: =IF(Valor_normalizado!F146=0,32,IFERROR(RANK(Valor_normalizado!F146,Valor_normalizado!F$130:F$161,0),"NA")) -> 30 | G151: =IF(Valor_normalizado!G146=0,32,IFERROR(RANK(Valor_normalizado!G146,Valor_normalizado!G$130:G$161,0),"NA")) -> 30 | H151: =IF(Valor_normalizado!H146=0,32,IFERROR(RANK(Valor_normalizado!H146,Valor_normalizado!H$130:H$161,0),"NA")) -> 29 | I151: =IF(Valor_normalizado!I146=0,32,IFERROR(RANK(Valor_normalizado!I146,Valor_normalizado!I$130:I$161,0),"NA")) -> 31 | J151: =IF(Valor_normalizado!J146=0,32,IFERROR(RANK(Valor_normalizado!J146,Valor_normalizado!J$130:J$161,0),"NA")) -> 28 | ... Y151: =IF(Valor_normalizado!Y146=0,32,IFERROR(RANK(Valor_normalizado!Y146,Valor_normalizado!Y$130:Y$161,0),"NA")) -> 29
A152: Riohacha | B152: 2023 | C152: =IF(Valor_normalizado!C153=0,32,IFERROR(RANK(Valor_normalizado!C153,Valor_normalizado!C$130:C$161,0),"NA")) -> 24 | D152: =IF(Valor_normalizado!D153=0,32,IFERROR(RANK(Valor_normalizado!D153,Valor_normalizado!D$130:D$161,0),"NA")) -> 5 | E152: =IF(Valor_normalizado!E153=0,32,IFERROR(RANK(Valor_normalizado!E153,Valor_normalizado!E$130:E$161,0),"NA")) -> 15 | F152: =IF(Valor_normalizado!F153=0,32,IFERROR(RANK(Valor_normalizado!F153,Valor_normalizado!F$130:F$161,0),"NA")) -> 21 | G152: =IF(Valor_normalizado!G153=0,32,IFERROR(RANK(Valor_normalizado!G153,Valor_normalizado!G$130:G$161,0),"NA")) -> 17 | H152: =IF(Valor_normalizado!H153=0,32,IFERROR(RANK(Valor_normalizado!H153,Valor_normalizado!H$130:H$161,0),"NA")) -> 31 | I152: =IF(Valor_normalizado!I153=0,32,IFERROR(RANK(Valor_normalizado!I153,Valor_normalizado!I$130:I$161,0),"NA")) -> 27 | J152: =IF(Valor_normalizado!J153=0,32,IFERROR(RANK(Valor_normalizado!J153,Valor_normalizado!J$130:J$161,0),"NA")) -> 31 | ... Y152: =IF(Valor_normalizado!Y153=0,32,IFERROR(RANK(Valor_normalizado!Y153,Valor_normalizado!Y$130:Y$161,0),"NA")) -> 21
A153: San Andrés | B153: 2023 | C153: =IF(Valor_normalizado!C154=0,32,IFERROR(RANK(Valor_normalizado!C154,Valor_normalizado!C$130:C$161,0),"NA")) -> 18 | D153: =IF(Valor_normalizado!D154=0,32,IFERROR(RANK(Valor_normalizado!D154,Valor_normalizado!D$130:D$161,0),"NA")) -> 15 | E153: =IF(Valor_normalizado!E154=0,32,IFERROR(RANK(Valor_normalizado!E154,Valor_normalizado!E$130:E$161,0),"NA")) -> 23 | F153: =IF(Valor_normalizado!F154=0,32,IFERROR(RANK(Valor_normalizado!F154,Valor_normalizado!F$130:F$161,0),"NA")) -> 17 | G153: =IF(Valor_normalizado!G154=0,32,IFERROR(RANK(Valor_normalizado!G154,Valor_normalizado!G$130:G$161,0),"NA")) -> 19 | H153: =IF(Valor_normalizado!H154=0,32,IFERROR(RANK(Valor_normalizado!H154,Valor_normalizado!H$130:H$161,0),"NA")) -> 17 | I153: =IF(Valor_normalizado!I154=0,32,IFERROR(RANK(Valor_normalizado!I154,Valor_normalizado!I$130:I$161,0),"NA")) -> 24 | J153: =IF(Valor_normalizado!J154=0,32,IFERROR(RANK(Valor_normalizado!J154,Valor_normalizado!J$130:J$161,0),"NA")) -> 18 | ... Y153: =IF(Valor_normalizado!Y154=0,32,IFERROR(RANK(Valor_normalizado!Y154,Valor_normalizado!Y$130:Y$161,0),"NA")) -> 20
A154: Quibdó | B154: 2023 | C154: =IF(Valor_normalizado!C152=0,32,IFERROR(RANK(Valor_normalizado!C152,Valor_normalizado!C$130:C$161,0),"NA")) -> 29 | D154: =IF(Valor_normalizado!D152=0,32,IFERROR(RANK(Valor_normalizado!D152,Valor_normalizado!D$130:D$161,0),"NA")) -> 32 | E154: =IF(Valor_normalizado!E152=0,32,IFERROR(RANK(Valor_normalizado!E152,Valor_normalizado!E$130:E$161,0),"NA")) -> 30 | F154: =IF(Valor_normalizado!F152=0,32,IFERROR(RANK(Valor_normalizado!F152,Valor_normalizado!F$130:F$161,0),"NA")) -> 29 | G154: =IF(Valor_normalizado!G152=0,32,IFERROR(RANK(Valor_normalizado!G152,Valor_normalizado!G$130:G$161,0),"NA")) -> 31 | H154: =IF(Valor_normalizado!H152=0,32,IFERROR(RANK(Valor_normalizado!H152,Valor_normalizado!H$130:H$161,0),"NA")) -> 28 | I154: =IF(Valor_normalizado!I152=0,32,IFERROR(RANK(Valor_normalizado!I152,Valor_normalizado!I$130:I$161,0),"NA")) -> 29 | J154: =IF(Valor_normalizado!J152=0,32,IFERROR(RANK(Valor_normalizado!J152,Valor_normalizado!J$130:J$161,0),"NA")) -> 6 | ... Y154: =IF(Valor_normalizado!Y152=0,32,IFERROR(RANK(Valor_normalizado!Y152,Valor_normalizado!Y$130:Y$161,0),"NA")) -> 32
A155: San José del Guaviare | B155: 2023 | C155: =IF(Valor_normalizado!C155=0,32,IFERROR(RANK(Valor_normalizado!C155,Valor_normalizado!C$130:C$161,0),"NA")) -> 25 | D155: =IF(Valor_normalizado!D155=0,32,IFERROR(RANK(Valor_normalizado!D155,Valor_normalizado!D$130:D$161,0),"NA")) -> 30 | E155: =IF(Valor_normalizado!E155=0,32,IFERROR(RANK(Valor_normalizado!E155,Valor_normalizado!E$130:E$161,0),"NA")) -> 29 | F155: =IF(Valor_normalizado!F155=0,32,IFERROR(RANK(Valor_normalizado!F155,Valor_normalizado!F$130:F$161,0),"NA")) -> 19 | G155: =IF(Valor_normalizado!G155=0,32,IFERROR(RANK(Valor_normalizado!G155,Valor_normalizado!G$130:G$161,0),"NA")) -> 25 | H155: =IF(Valor_normalizado!H155=0,32,IFERROR(RANK(Valor_normalizado!H155,Valor_normalizado!H$130:H$161,0),"NA")) -> 18 | I155: =IF(Valor_normalizado!I155=0,32,IFERROR(RANK(Valor_normalizado!I155,Valor_normalizado!I$130:I$161,0),"NA")) -> 22 | J155: =IF(Valor_normalizado!J155=0,32,IFERROR(RANK(Valor_normalizado!J155,Valor_normalizado!J$130:J$161,0),"NA")) -> 22 | ... Y155: =IF(Valor_normalizado!Y155=0,32,IFERROR(RANK(Valor_normalizado!Y155,Valor_normalizado!Y$130:Y$161,0),"NA")) -> 25
A156: Mocoa | B156: 2023 | C156: =IF(Valor_normalizado!C145=0,32,IFERROR(RANK(Valor_normalizado!C145,Valor_normalizado!C$130:C$161,0),"NA")) -> 23 | D156: =IF(Valor_normalizado!D145=0,32,IFERROR(RANK(Valor_normalizado!D145,Valor_normalizado!D$130:D$161,0),"NA")) -> 16 | E156: =IF(Valor_normalizado!E145=0,32,IFERROR(RANK(Valor_normalizado!E145,Valor_normalizado!E$130:E$161,0),"NA")) -> 28 | F156: =IF(Valor_normalizado!F145=0,32,IFERROR(RANK(Valor_normalizado!F145,Valor_normalizado!F$130:F$161,0),"NA")) -> 27 | G156: =IF(Valor_normalizado!G145=0,32,IFERROR(RANK(Valor_normalizado!G145,Valor_normalizado!G$130:G$161,0),"NA")) -> 24 | H156: =IF(Valor_normalizado!H145=0,32,IFERROR(RANK(Valor_normalizado!H145,Valor_normalizado!H$130:H$161,0),"NA")) -> 12 | I156: =IF(Valor_normalizado!I145=0,32,IFERROR(RANK(Valor_normalizado!I145,Valor_normalizado!I$130:I$161,0),"NA")) -> 13 | J156: =IF(Valor_normalizado!J145=0,32,IFERROR(RANK(Valor_normalizado!J145,Valor_normalizado!J$130:J$161,0),"NA")) -> 26 | ... Y156: =IF(Valor_normalizado!Y145=0,32,IFERROR(RANK(Valor_normalizado!Y145,Valor_normalizado!Y$130:Y$161,0),"NA")) -> 18
A157: Inírida | B157: 2023 | C157: =IF(Valor_normalizado!C140=0,32,IFERROR(RANK(Valor_normalizado!C140,Valor_normalizado!C$130:C$161,0),"NA")) -> 5 | D157: =IF(Valor_normalizado!D140=0,32,IFERROR(RANK(Valor_normalizado!D140,Valor_normalizado!D$130:D$161,0),"NA")) -> 13 | E157: =IF(Valor_normalizado!E140=0,32,IFERROR(RANK(Valor_normalizado!E140,Valor_normalizado!E$130:E$161,0),"NA")) -> 8 | F157: =IF(Valor_normalizado!F140=0,32,IFERROR(RANK(Valor_normalizado!F140,Valor_normalizado!F$130:F$161,0),"NA")) -> 5 | G157: =IF(Valor_normalizado!G140=0,32,IFERROR(RANK(Valor_normalizado!G140,Valor_normalizado!G$130:G$161,0),"NA")) -> 6 | H157: =IF(Valor_normalizado!H140=0,32,IFERROR(RANK(Valor_normalizado!H140,Valor_normalizado!H$130:H$161,0),"NA")) -> 10 | I157: =IF(Valor_normalizado!I140=0,32,IFERROR(RANK(Valor_normalizado!I140,Valor_normalizado!I$130:I$161,0),"NA")) -> 7 | J157: =IF(Valor_normalizado!J140=0,32,IFERROR(RANK(Valor_normalizado!J140,Valor_normalizado!J$130:J$161,0),"NA")) -> 12 | ... Y157: =IF(Valor_normalizado!Y140=0,32,IFERROR(RANK(Valor_normalizado!Y140,Valor_normalizado!Y$130:Y$161,0),"NA")) -> 14
A158: Arauca | B158: 2023 | C158: =IF(Valor_normalizado!C130=0,32,IFERROR(RANK(Valor_normalizado!C130,Valor_normalizado!C$130:C$161,0),"NA")) -> 10 | D158: =IF(Valor_normalizado!D130=0,32,IFERROR(RANK(Valor_normalizado!D130,Valor_normalizado!D$130:D$161,0),"NA")) -> 7 | E158: =IF(Valor_normalizado!E130=0,32,IFERROR(RANK(Valor_normalizado!E130,Valor_normalizado!E$130:E$161,0),"NA")) -> 2 | F158: =IF(Valor_normalizado!F130=0,32,IFERROR(RANK(Valor_normalizado!F130,Valor_normalizado!F$130:F$161,0),"NA")) -> 7 | G158: =IF(Valor_normalizado!G130=0,32,IFERROR(RANK(Valor_normalizado!G130,Valor_normalizado!G$130:G$161,0),"NA")) -> 7 | H158: =IF(Valor_normalizado!H130=0,32,IFERROR(RANK(Valor_normalizado!H130,Valor_normalizado!H$130:H$161,0),"NA")) -> 6 | I158: =IF(Valor_normalizado!I130=0,32,IFERROR(RANK(Valor_normalizado!I130,Valor_normalizado!I$130:I$161,0),"NA")) -> 3 | J158: =IF(Valor_normalizado!J130=0,32,IFERROR(RANK(Valor_normalizado!J130,Valor_normalizado!J$130:J$161,0),"NA")) -> 3 | ... Y158: =IF(Valor_normalizado!Y130=0,32,IFERROR(RANK(Valor_normalizado!Y130,Valor_normalizado!Y$130:Y$161,0),"NA")) -> 5
A159: Puerto Carreño | B159: 2023 | C159: =IF(Valor_normalizado!C151=0,32,IFERROR(RANK(Valor_normalizado!C151,Valor_normalizado!C$130:C$161,0),"NA")) -> 15 | D159: =IF(Valor_normalizado!D151=0,32,IFERROR(RANK(Valor_normalizado!D151,Valor_normalizado!D$130:D$161,0),"NA")) -> 23 | E159: =IF(Valor_normalizado!E151=0,32,IFERROR(RANK(Valor_normalizado!E151,Valor_normalizado!E$130:E$161,0),"NA")) -> 17 | F159: =IF(Valor_normalizado!F151=0,32,IFERROR(RANK(Valor_normalizado!F151,Valor_normalizado!F$130:F$161,0),"NA")) -> 6 | G159: =IF(Valor_normalizado!G151=0,32,IFERROR(RANK(Valor_normalizado!G151,Valor_normalizado!G$130:G$161,0),"NA")) -> 16 | H159: =IF(Valor_normalizado!H151=0,32,IFERROR(RANK(Valor_normalizado!H151,Valor_normalizado!H$130:H$161,0),"NA")) -> 22 | I159: =IF(Valor_normalizado!I151=0,32,IFERROR(RANK(Valor_normalizado!I151,Valor_normalizado!I$130:I$161,0),"NA")) -> 15 | J159: =IF(Valor_normalizado!J151=0,32,IFERROR(RANK(Valor_normalizado!J151,Valor_normalizado!J$130:J$161,0),"NA")) -> 27 | ... Y159: =IF(Valor_normalizado!Y151=0,32,IFERROR(RANK(Valor_normalizado!Y151,Valor_normalizado!Y$130:Y$161,0),"NA")) -> 19
A160: Leticia | B160: 2023 | C160: =IF(Valor_normalizado!C141=0,32,IFERROR(RANK(Valor_normalizado!C141,Valor_normalizado!C$130:C$161,0),"NA")) -> 6 | D160: =IF(Valor_normalizado!D141=0,32,IFERROR(RANK(Valor_normalizado!D141,Valor_normalizado!D$130:D$161,0),"NA")) -> 22 | E160: =IF(Valor_normalizado!E141=0,32,IFERROR(RANK(Valor_normalizado!E141,Valor_normalizado!E$130:E$161,0),"NA")) -> 14 | F160: =IF(Valor_normalizado!F141=0,32,IFERROR(RANK(Valor_normalizado!F141,Valor_normalizado!F$130:F$161,0),"NA")) -> 16 | G160: =IF(Valor_normalizado!G141=0,32,IFERROR(RANK(Valor_normalizado!G141,Valor_normalizado!G$130:G$161,0),"NA")) -> 13 | H160: =IF(Valor_normalizado!H141=0,32,IFERROR(RANK(Valor_normalizado!H141,Valor_normalizado!H$130:H$161,0),"NA")) -> 11 | I160: =IF(Valor_normalizado!I141=0,32,IFERROR(RANK(Valor_normalizado!I141,Valor_normalizado!I$130:I$161,0),"NA")) -> 12 | J160: =IF(Valor_normalizado!J141=0,32,IFERROR(RANK(Valor_normalizado!J141,Valor_normalizado!J$130:J$161,0),"NA")) -> 21 | ... Y160: =IF(Valor_normalizado!Y141=0,32,IFERROR(RANK(Valor_normalizado!Y141,Valor_normalizado!Y$130:Y$161,0),"NA")) -> 12
A161: Mitú | B161: 2023 | C161: =IF(Valor_normalizado!C144=0,32,IFERROR(RANK(Valor_normalizado!C144,Valor_normalizado!C$130:C$161,0),"NA")) -> 11 | D161: =IF(Valor_normalizado!D144=0,32,IFERROR(RANK(Valor_normalizado!D144,Valor_normalizado!D$130:D$161,0),"NA")) -> 17 | E161: =IF(Valor_normalizado!E144=0,32,IFERROR(RANK(Valor_normalizado!E144,Valor_normalizado!E$130:E$161,0),"NA")) -> 9 | F161: =IF(Valor_normalizado!F144=0,32,IFERROR(RANK(Valor_normalizado!F144,Valor_normalizado!F$130:F$161,0),"NA")) -> 12 | G161: =IF(Valor_normalizado!G144=0,32,IFERROR(RANK(Valor_normalizado!G144,Valor_normalizado!G$130:G$161,0),"NA")) -> 12 | H161: =IF(Valor_normalizado!H144=0,32,IFERROR(RANK(Valor_normalizado!H144,Valor_normalizado!H$130:H$161,0),"NA")) -> 9 | I161: =IF(Valor_normalizado!I144=0,32,IFERROR(RANK(Valor_normalizado!I144,Valor_normalizado!I$130:I$161,0),"NA")) -> 8 | J161: =IF(Valor_normalizado!J144=0,32,IFERROR(RANK(Valor_normalizado!J144,Valor_normalizado!J$130:J$161,0),"NA")) -> 20 | ... Y161: =IF(Valor_normalizado!Y144=0,32,IFERROR(RANK(Valor_normalizado!Y144,Valor_normalizado!Y$130:Y$161,0),"NA")) -> 13
A162: Arauca | B162: 2024 | C162: =IF(Valor_normalizado!C162=0,32,IFERROR(RANK(Valor_normalizado!C162,Valor_normalizado!C$162:C$193,0),"NA")) -> 4 | D162: =IF(Valor_normalizado!D162=0,32,IFERROR(RANK(Valor_normalizado!D162,Valor_normalizado!D$162:D$193,0),"NA")) -> 5 | E162: =IF(Valor_normalizado!E162=0,32,IFERROR(RANK(Valor_normalizado!E162,Valor_normalizado!E$162:E$193,0),"NA")) -> 1 | F162: =IF(Valor_normalizado!F162=0,32,IFERROR(RANK(Valor_normalizado!F162,Valor_normalizado!F$162:F$193,0),"NA")) -> 4 | G162: =IF(Valor_normalizado!G162=0,32,IFERROR(RANK(Valor_normalizado!G162,Valor_normalizado!G$162:G$193,0),"NA")) -> 1 | H162: =IF(Valor_normalizado!H162=0,32,IFERROR(RANK(Valor_normalizado!H162,Valor_normalizado!H$162:H$193,0),"NA")) -> 1 | I162: =IF(Valor_normalizado!I162=0,32,IFERROR(RANK(Valor_normalizado!I162,Valor_normalizado!I$162:I$193,0),"NA")) -> 2 | J162: =IF(Valor_normalizado!J162=0,32,IFERROR(RANK(Valor_normalizado!J162,Valor_normalizado!J$162:J$193,0),"NA")) -> 2 | ... Y162: =IF(Valor_normalizado!Y162=0,32,IFERROR(RANK(Valor_normalizado!Y162,Valor_normalizado!Y$162:Y$193,0),"NA")) -> 1
A163: Armenia | B163: 2024 | C163: =IF(Valor_normalizado!C163=0,32,IFERROR(RANK(Valor_normalizado!C163,Valor_normalizado!C$162:C$193,0),"NA")) -> 5 | D163: =IF(Valor_normalizado!D163=0,32,IFERROR(RANK(Valor_normalizado!D163,Valor_normalizado!D$162:D$193,0),"NA")) -> 10 | E163: =IF(Valor_normalizado!E163=0,32,IFERROR(RANK(Valor_normalizado!E163,Valor_normalizado!E$162:E$193,0),"NA")) -> 3 | F163: =IF(Valor_normalizado!F163=0,32,IFERROR(RANK(Valor_normalizado!F163,Valor_normalizado!F$162:F$193,0),"NA")) -> 21 | G163: =IF(Valor_normalizado!G163=0,32,IFERROR(RANK(Valor_normalizado!G163,Valor_normalizado!G$162:G$193,0),"NA")) -> 8 | H163: =IF(Valor_normalizado!H163=0,32,IFERROR(RANK(Valor_normalizado!H163,Valor_normalizado!H$162:H$193,0),"NA")) -> 2 | I163: =IF(Valor_normalizado!I163=0,32,IFERROR(RANK(Valor_normalizado!I163,Valor_normalizado!I$162:I$193,0),"NA")) -> 1 | J163: =IF(Valor_normalizado!J163=0,32,IFERROR(RANK(Valor_normalizado!J163,Valor_normalizado!J$162:J$193,0),"NA")) -> 1 | ... Y163: =IF(Valor_normalizado!Y163=0,32,IFERROR(RANK(Valor_normalizado!Y163,Valor_normalizado!Y$162:Y$193,0),"NA")) -> 3
A164: Barranquilla AM | B164: 2024 | C164: =IF(Valor_normalizado!C164=0,32,IFERROR(RANK(Valor_normalizado!C164,Valor_normalizado!C$162:C$193,0),"NA")) -> 1 | D164: =IF(Valor_normalizado!D164=0,32,IFERROR(RANK(Valor_normalizado!D164,Valor_normalizado!D$162:D$193,0),"NA")) -> 1 | E164: =IF(Valor_normalizado!E164=0,32,IFERROR(RANK(Valor_normalizado!E164,Valor_normalizado!E$162:E$193,0),"NA")) -> 7 | F164: =IF(Valor_normalizado!F164=0,32,IFERROR(RANK(Valor_normalizado!F164,Valor_normalizado!F$162:F$193,0),"NA")) -> 5 | G164: =IF(Valor_normalizado!G164=0,32,IFERROR(RANK(Valor_normalizado!G164,Valor_normalizado!G$162:G$193,0),"NA")) -> 2 | H164: =IF(Valor_normalizado!H164=0,32,IFERROR(RANK(Valor_normalizado!H164,Valor_normalizado!H$162:H$193,0),"NA")) -> 8 | I164: =IF(Valor_normalizado!I164=0,32,IFERROR(RANK(Valor_normalizado!I164,Valor_normalizado!I$162:I$193,0),"NA")) -> 8 | J164: =IF(Valor_normalizado!J164=0,32,IFERROR(RANK(Valor_normalizado!J164,Valor_normalizado!J$162:J$193,0),"NA")) -> 3 | ... Y164: =IF(Valor_normalizado!Y164=0,32,IFERROR(RANK(Valor_normalizado!Y164,Valor_normalizado!Y$162:Y$193,0),"NA")) -> 2
A165: Bogotá D.C. | B165: 2024 | C165: =IF(Valor_normalizado!C165=0,32,IFERROR(RANK(Valor_normalizado!C165,Valor_normalizado!C$162:C$193,0),"NA")) -> 10 | D165: =IF(Valor_normalizado!D165=0,32,IFERROR(RANK(Valor_normalizado!D165,Valor_normalizado!D$162:D$193,0),"NA")) -> 3 | E165: =IF(Valor_normalizado!E165=0,32,IFERROR(RANK(Valor_normalizado!E165,Valor_normalizado!E$162:E$193,0),"NA")) -> 2 | F165: =IF(Valor_normalizado!F165=0,32,IFERROR(RANK(Valor_normalizado!F165,Valor_normalizado!F$162:F$193,0),"NA")) -> 8 | G165: =IF(Valor_normalizado!G165=0,32,IFERROR(RANK(Valor_normalizado!G165,Valor_normalizado!G$162:G$193,0),"NA")) -> 5 | H165: =IF(Valor_normalizado!H165=0,32,IFERROR(RANK(Valor_normalizado!H165,Valor_normalizado!H$162:H$193,0),"NA")) -> 6 | I165: =IF(Valor_normalizado!I165=0,32,IFERROR(RANK(Valor_normalizado!I165,Valor_normalizado!I$162:I$193,0),"NA")) -> 3 | J165: =IF(Valor_normalizado!J165=0,32,IFERROR(RANK(Valor_normalizado!J165,Valor_normalizado!J$162:J$193,0),"NA")) -> 4 | ... Y165: =IF(Valor_normalizado!Y165=0,32,IFERROR(RANK(Valor_normalizado!Y165,Valor_normalizado!Y$162:Y$193,0),"NA")) -> 5
A166: Bucaramanga AM | B166: 2024 | C166: =IF(Valor_normalizado!C166=0,32,IFERROR(RANK(Valor_normalizado!C166,Valor_normalizado!C$162:C$193,0),"NA")) -> 6 | D166: =IF(Valor_normalizado!D166=0,32,IFERROR(RANK(Valor_normalizado!D166,Valor_normalizado!D$162:D$193,0),"NA")) -> 2 | E166: =IF(Valor_normalizado!E166=0,32,IFERROR(RANK(Valor_normalizado!E166,Valor_normalizado!E$162:E$193,0),"NA")) -> 4 | F166: =IF(Valor_normalizado!F166=0,32,IFERROR(RANK(Valor_normalizado!F166,Valor_normalizado!F$162:F$193,0),"NA")) -> 7 | G166: =IF(Valor_normalizado!G166=0,32,IFERROR(RANK(Valor_normalizado!G166,Valor_normalizado!G$162:G$193,0),"NA")) -> 3 | H166: =IF(Valor_normalizado!H166=0,32,IFERROR(RANK(Valor_normalizado!H166,Valor_normalizado!H$162:H$193,0),"NA")) -> 5 | I166: =IF(Valor_normalizado!I166=0,32,IFERROR(RANK(Valor_normalizado!I166,Valor_normalizado!I$162:I$193,0),"NA")) -> 4 | J166: =IF(Valor_normalizado!J166=0,32,IFERROR(RANK(Valor_normalizado!J166,Valor_normalizado!J$162:J$193,0),"NA")) -> 17 | ... Y166: =IF(Valor_normalizado!Y166=0,32,IFERROR(RANK(Valor_normalizado!Y166,Valor_normalizado!Y$162:Y$193,0),"NA")) -> 7
A167: Cali AM | B167: 2024 | C167: =IF(Valor_normalizado!C167=0,32,IFERROR(RANK(Valor_normalizado!C167,Valor_normalizado!C$162:C$193,0),"NA")) -> 13 | D167: =IF(Valor_normalizado!D167=0,32,IFERROR(RANK(Valor_normalizado!D167,Valor_normalizado!D$162:D$193,0),"NA")) -> 9 | E167: =IF(Valor_normalizado!E167=0,32,IFERROR(RANK(Valor_normalizado!E167,Valor_normalizado!E$162:E$193,0),"NA")) -> 9 | F167: =IF(Valor_normalizado!F167=0,32,IFERROR(RANK(Valor_normalizado!F167,Valor_normalizado!F$162:F$193,0),"NA")) -> 14 | G167: =IF(Valor_normalizado!G167=0,32,IFERROR(RANK(Valor_normalizado!G167,Valor_normalizado!G$162:G$193,0),"NA")) -> 11 | H167: =IF(Valor_normalizado!H167=0,32,IFERROR(RANK(Valor_normalizado!H167,Valor_normalizado!H$162:H$193,0),"NA")) -> 3 | I167: =IF(Valor_normalizado!I167=0,32,IFERROR(RANK(Valor_normalizado!I167,Valor_normalizado!I$162:I$193,0),"NA")) -> 5 | J167: =IF(Valor_normalizado!J167=0,32,IFERROR(RANK(Valor_normalizado!J167,Valor_normalizado!J$162:J$193,0),"NA")) -> 12 | ... Y167: =IF(Valor_normalizado!Y167=0,32,IFERROR(RANK(Valor_normalizado!Y167,Valor_normalizado!Y$162:Y$193,0),"NA")) -> 9
A168: Cartagena | B168: 2024 | C168: =IF(Valor_normalizado!C168=0,32,IFERROR(RANK(Valor_normalizado!C168,Valor_normalizado!C$162:C$193,0),"NA")) -> 2 | D168: =IF(Valor_normalizado!D168=0,32,IFERROR(RANK(Valor_normalizado!D168,Valor_normalizado!D$162:D$193,0),"NA")) -> 7 | E168: =IF(Valor_normalizado!E168=0,32,IFERROR(RANK(Valor_normalizado!E168,Valor_normalizado!E$162:E$193,0),"NA")) -> 8 | F168: =IF(Valor_normalizado!F168=0,32,IFERROR(RANK(Valor_normalizado!F168,Valor_normalizado!F$162:F$193,0),"NA")) -> 9 | G168: =IF(Valor_normalizado!G168=0,32,IFERROR(RANK(Valor_normalizado!G168,Valor_normalizado!G$162:G$193,0),"NA")) -> 6 | H168: =IF(Valor_normalizado!H168=0,32,IFERROR(RANK(Valor_normalizado!H168,Valor_normalizado!H$162:H$193,0),"NA")) -> 4 | I168: =IF(Valor_normalizado!I168=0,32,IFERROR(RANK(Valor_normalizado!I168,Valor_normalizado!I$162:I$193,0),"NA")) -> 7 | J168: =IF(Valor_normalizado!J168=0,32,IFERROR(RANK(Valor_normalizado!J168,Valor_normalizado!J$162:J$193,0),"NA")) -> 22 | ... Y168: =IF(Valor_normalizado!Y168=0,32,IFERROR(RANK(Valor_normalizado!Y168,Valor_normalizado!Y$162:Y$193,0),"NA")) -> 10
A169: Cúcuta AM | B169: 2024 | C169: =IF(Valor_normalizado!C169=0,32,IFERROR(RANK(Valor_normalizado!C169,Valor_normalizado!C$162:C$193,0),"NA")) -> 7 | D169: =IF(Valor_normalizado!D169=0,32,IFERROR(RANK(Valor_normalizado!D169,Valor_normalizado!D$162:D$193,0),"NA")) -> 8 | E169: =IF(Valor_normalizado!E169=0,32,IFERROR(RANK(Valor_normalizado!E169,Valor_normalizado!E$162:E$193,0),"NA")) -> 6 | F169: =IF(Valor_normalizado!F169=0,32,IFERROR(RANK(Valor_normalizado!F169,Valor_normalizado!F$162:F$193,0),"NA")) -> 2 | G169: =IF(Valor_normalizado!G169=0,32,IFERROR(RANK(Valor_normalizado!G169,Valor_normalizado!G$162:G$193,0),"NA")) -> 4 | H169: =IF(Valor_normalizado!H169=0,32,IFERROR(RANK(Valor_normalizado!H169,Valor_normalizado!H$162:H$193,0),"NA")) -> 9 | I169: =IF(Valor_normalizado!I169=0,32,IFERROR(RANK(Valor_normalizado!I169,Valor_normalizado!I$162:I$193,0),"NA")) -> 11 | J169: =IF(Valor_normalizado!J169=0,32,IFERROR(RANK(Valor_normalizado!J169,Valor_normalizado!J$162:J$193,0),"NA")) -> 9 | ... Y169: =IF(Valor_normalizado!Y169=0,32,IFERROR(RANK(Valor_normalizado!Y169,Valor_normalizado!Y$162:Y$193,0),"NA")) -> 6
A170: Florencia | B170: 2024 | C170: =IF(Valor_normalizado!C170=0,32,IFERROR(RANK(Valor_normalizado!C170,Valor_normalizado!C$162:C$193,0),"NA")) -> 3 | D170: =IF(Valor_normalizado!D170=0,32,IFERROR(RANK(Valor_normalizado!D170,Valor_normalizado!D$162:D$193,0),"NA")) -> 20 | E170: =IF(Valor_normalizado!E170=0,32,IFERROR(RANK(Valor_normalizado!E170,Valor_normalizado!E$162:E$193,0),"NA")) -> 13 | F170: =IF(Valor_normalizado!F170=0,32,IFERROR(RANK(Valor_normalizado!F170,Valor_normalizado!F$162:F$193,0),"NA")) -> 10 | G170: =IF(Valor_normalizado!G170=0,32,IFERROR(RANK(Valor_normalizado!G170,Valor_normalizado!G$162:G$193,0),"NA")) -> 9 | H170: =IF(Valor_normalizado!H170=0,32,IFERROR(RANK(Valor_normalizado!H170,Valor_normalizado!H$162:H$193,0),"NA")) -> 11 | I170: =IF(Valor_normalizado!I170=0,32,IFERROR(RANK(Valor_normalizado!I170,Valor_normalizado!I$162:I$193,0),"NA")) -> 6 | J170: =IF(Valor_normalizado!J170=0,32,IFERROR(RANK(Valor_normalizado!J170,Valor_normalizado!J$162:J$193,0),"NA")) -> 15 | ... Y170: =IF(Valor_normalizado!Y170=0,32,IFERROR(RANK(Valor_normalizado!Y170,Valor_normalizado!Y$162:Y$193,0),"NA")) -> 13
A171: Ibagué | B171: 2024 | C171: =IF(Valor_normalizado!C171=0,32,IFERROR(RANK(Valor_normalizado!C171,Valor_normalizado!C$162:C$193,0),"NA")) -> 9 | D171: =IF(Valor_normalizado!D171=0,32,IFERROR(RANK(Valor_normalizado!D171,Valor_normalizado!D$162:D$193,0),"NA")) -> 11 | E171: =IF(Valor_normalizado!E171=0,32,IFERROR(RANK(Valor_normalizado!E171,Valor_normalizado!E$162:E$193,0),"NA")) -> 5 | F171: =IF(Valor_normalizado!F171=0,32,IFERROR(RANK(Valor_normalizado!F171,Valor_normalizado!F$162:F$193,0),"NA")) -> 3 | G171: =IF(Valor_normalizado!G171=0,32,IFERROR(RANK(Valor_normalizado!G171,Valor_normalizado!G$162:G$193,0),"NA")) -> 7 | H171: =IF(Valor_normalizado!H171=0,32,IFERROR(RANK(Valor_normalizado!H171,Valor_normalizado!H$162:H$193,0),"NA")) -> 14 | I171: =IF(Valor_normalizado!I171=0,32,IFERROR(RANK(Valor_normalizado!I171,Valor_normalizado!I$162:I$193,0),"NA")) -> 18 | J171: =IF(Valor_normalizado!J171=0,32,IFERROR(RANK(Valor_normalizado!J171,Valor_normalizado!J$162:J$193,0),"NA")) -> 6 | ... Y171: =IF(Valor_normalizado!Y171=0,32,IFERROR(RANK(Valor_normalizado!Y171,Valor_normalizado!Y$162:Y$193,0),"NA")) -> 4
A172: Inírida | B172: 2024 | C172: =IF(Valor_normalizado!C172=0,32,IFERROR(RANK(Valor_normalizado!C172,Valor_normalizado!C$162:C$193,0),"NA")) -> 8 | D172: =IF(Valor_normalizado!D172=0,32,IFERROR(RANK(Valor_normalizado!D172,Valor_normalizado!D$162:D$193,0),"NA")) -> 19 | E172: =IF(Valor_normalizado!E172=0,32,IFERROR(RANK(Valor_normalizado!E172,Valor_normalizado!E$162:E$193,0),"NA")) -> 11 | F172: =IF(Valor_normalizado!F172=0,32,IFERROR(RANK(Valor_normalizado!F172,Valor_normalizado!F$162:F$193,0),"NA")) -> 10 | G172: =IF(Valor_normalizado!G172=0,32,IFERROR(RANK(Valor_normalizado!G172,Valor_normalizado!G$162:G$193,0),"NA")) -> 12 | H172: =IF(Valor_normalizado!H172=0,32,IFERROR(RANK(Valor_normalizado!H172,Valor_normalizado!H$162:H$193,0),"NA")) -> 10 | I172: =IF(Valor_normalizado!I172=0,32,IFERROR(RANK(Valor_normalizado!I172,Valor_normalizado!I$162:I$193,0),"NA")) -> 10 | J172: =IF(Valor_normalizado!J172=0,32,IFERROR(RANK(Valor_normalizado!J172,Valor_normalizado!J$162:J$193,0),"NA")) -> 25 | ... Y172: =IF(Valor_normalizado!Y172=0,32,IFERROR(RANK(Valor_normalizado!Y172,Valor_normalizado!Y$162:Y$193,0),"NA")) -> 12
A173: Leticia | B173: 2024 | C173: =IF(Valor_normalizado!C173=0,32,IFERROR(RANK(Valor_normalizado!C173,Valor_normalizado!C$162:C$193,0),"NA")) -> 15 | D173: =IF(Valor_normalizado!D173=0,32,IFERROR(RANK(Valor_normalizado!D173,Valor_normalizado!D$162:D$193,0),"NA")) -> 22 | E173: =IF(Valor_normalizado!E173=0,32,IFERROR(RANK(Valor_normalizado!E173,Valor_normalizado!E$162:E$193,0),"NA")) -> 12 | F173: =IF(Valor_normalizado!F173=0,32,IFERROR(RANK(Valor_normalizado!F173,Valor_normalizado!F$162:F$193,0),"NA")) -> 12 | G173: =IF(Valor_normalizado!G173=0,32,IFERROR(RANK(Valor_normalizado!G173,Valor_normalizado!G$162:G$193,0),"NA")) -> 15 | H173: =IF(Valor_normalizado!H173=0,32,IFERROR(RANK(Valor_normalizado!H173,Valor_normalizado!H$162:H$193,0),"NA")) -> 13 | I173: =IF(Valor_normalizado!I173=0,32,IFERROR(RANK(Valor_normalizado!I173,Valor_normalizado!I$162:I$193,0),"NA")) -> 13 | J173: =IF(Valor_normalizado!J173=0,32,IFERROR(RANK(Valor_normalizado!J173,Valor_normalizado!J$162:J$193,0),"NA")) -> 5 | ... Y173: =IF(Valor_normalizado!Y173=0,32,IFERROR(RANK(Valor_normalizado!Y173,Valor_normalizado!Y$162:Y$193,0),"NA")) -> 8
... A193: Yopal | B193: 2024 | C193: =IF(Valor_normalizado!C193=0,32,IFERROR(RANK(Valor_normalizado!C193,Valor_normalizado!C$162:C$193,0),"NA")) -> 30 | D193: =IF(Valor_normalizado!D193=0,32,IFERROR(RANK(Valor_normalizado!D193,Valor_normalizado!D$162:D$193,0),"NA")) -> 31 | E193: =IF(Valor_normalizado!E193=0,32,IFERROR(RANK(Valor_normalizado!E193,Valor_normalizado!E$162:E$193,0),"NA")) -> 28 | F193: =IF(Valor_normalizado!F193=0,32,IFERROR(RANK(Valor_normalizado!F193,Valor_normalizado!F$162:F$193,0),"NA")) -> 32 | G193: =IF(Valor_normalizado!G193=0,32,IFERROR(RANK(Valor_normalizado!G193,Valor_normalizado!G$162:G$193,0),"NA")) -> 31 | H193: =IF(Valor_normalizado!H193=0,32,IFERROR(RANK(Valor_normalizado!H193,Valor_normalizado!H$162:H$193,0),"NA")) -> 29 | I193: =IF(Valor_normalizado!I193=0,32,IFERROR(RANK(Valor_normalizado!I193,Valor_normalizado!I$162:I$193,0),"NA")) -> 31 | J193: =IF(Valor_normalizado!J193=0,32,IFERROR(RANK(Valor_normalizado!J193,Valor_normalizado!J$162:J$193,0),"NA")) -> 27 | ... Y193: =IF(Valor_normalizado!Y193=0,32,IFERROR(RANK(Valor_normalizado!Y193,Valor_normalizado!Y$162:Y$193,0),"NA")) -> 29

Sheet Pivot Table 1

Sheet RESULTADOS INN
A1: CODIGO_MUN | B1: CATEGORIA_NUM | C1: CATEGORIA_POBLACION | D1: Ciudad o AM | E1: 2019 | F1: 2020 | G1: 2021 | H1: 2022
A2: 1 | B2: 0 | C2: Superior o igual a 500,001 | D2: Bogotá D.C. | E2: 5.7505142 | F2: 5.9627539 | G2: 5.661942 | H2: 5.7957711
A3: 2 | B3: 0 | C3: Superior o igual a 500,001 | D3: Medellín AM | E3: 5.0481983 | F3: 5.6021917 | G3: 5.3879465 | H3: 5.2502314
A4: 5 | B4: 0 | C4: Superior o igual a 500,001 | D4: Cali AM | E4: 3.5121944 | F4: 3.8157236 | G4: 3.6605373 | H4: 3.5978347 | K4: Metodología: Muestra aleatoria simple
A5: 6 | B5: 0 | C5: Superior o igual a 500,001 | D5: Bucaramanga AM | E5: 3.1460224 | F5: 3.5144939 | G5: 3.8438224 | H5: 4.605215 | K5: Alcance: acciones específicas que definen su resultado
A6: 9 | B6: 0 | C6: Superior o igual a 500,001 | D6: Barranquilla AM | E6: 2.7576208 | F6: 3.4042264 | G6: 3.2774324 | H6: 3.5672449 | K6: acciones puntuales:
A7: 18 | B7: 0 | C7: Superior o igual a 500,001 | D7: Cartagena | E7: 1.472329 | F7: 1.5274334 | G7: 1.7550461 | H7: 2.0203776 | K7: 1. Construcción de base de datos de sub-pilares
A8: 3 | B8: 1 | C8: Entre 100,001 y 500,000 | D8: Manizales AM | E8: 4.4144916 | F8: 5.3523852 | G8: 6.1777658 | H8: 5.9558071 | K8: 2. Investigación literaria de acciones
A9: 4 | B9: 1 | C9: Entre 100,001 y 500,000 | D9: Tunja | E9: 4.2368937 | F9: 4.7550686 | G9: 5.2393765 | H9: 5.0780044
A10: 7 | B10: 1 | C10: Entre 100,001 y 500,000 | D10: Pereira AM | E10: 3.1457079 | F10: 4.1147313 | G10: 3.6610302 | H10: 4.2218255
A11: 8 | B11: 1 | C11: Entre 100,001 y 500,000 | D11: Armenia | E11: 3.0740241 | F11: 3.8174754 | G11: 4.0743788 | H11: 3.9874121 | K11: OPCION 1:MUESTRA ALEATOROA
A12: 10 | B12: 1 | C12: Entre 100,001 y 500,000 | D12: Popayán | E12: 2.4565024 | F12: 3.3142518 | G12: 3.0340601 | H12: 3.7485782 | K12: =+RANDBETWEEN(1,32) -> 19 | L12: =+VLOOKUP(K12,$A$1:$H$33,4,FALSE) -> Valledupar
A13: 12 | B13: 1 | C13: Entre 100,001 y 500,000 | D13: Ibagué | E13: 2.2156719 | F13: 2.6554751 | G13: 3.3327188 | H13: 3.3510889 | K13: =+RANDBETWEEN(1,32) -> 31 | L13: =+VLOOKUP(K13,$A$1:$H$33,4,FALSE) -> Inírida
A14: 13 | B14: 1 | C14: Entre 100,001 y 500,000 | D14: Santa Marta | E14: 2.0211055 | F14: 2.3385658 | G14: 2.4325543 | H14: 2.4530454 | K14: =+RANDBETWEEN(1,32) -> 22 | L14: =+VLOOKUP(K14,$A$1:$H$33,4,FALSE) -> Florencia
A15: 15 | B15: 1 | C15: Entre 100,001 y 500,000 | D15: Montería | E15: 1.7584615 | F15: 1.8863903 | G15: 1.6130729 | H15: 1.9018698 | K15: =+RANDBETWEEN(1,32) -> 4 | L15: =+VLOOKUP(K15,$A$1:$H$33,4,FALSE) -> Tunja
A16: 16 | B16: 1 | C16: Entre 100,001 y 500,000 | D16: Cúcuta AM | E16: 1.7508051 | F16: 1.9842849 | G16: 1.786782 | H16: 2.0978382 | K16: =+RANDBETWEEN(1,32) -> 11 | L16: =+VLOOKUP(K16,$A$1:$H$33,4,FALSE) -> Leticia
A17: 19 | B17: 1 | C17: Entre 100,001 y 500,000 | D17: Valledupar | E17: 1.4180889 | F17: 1.4906426 | G17: 0.68018819 | H17: 1.0651636
A18: 20 | B18: 1 | C18: Entre 100,001 y 500,000 | D18: Villavicencio | E18: 1.3586295 | F18: 1.3948201 | G18: 1.2833103 | H18: 1.4217448 | K18: OPCION 2: POR CATEGORIA
A19: 21 | B19: 1 | C19: Entre 100,001 y 500,000 | D19: Pasto | E19: 1.3024909 | F19: 1.6008356 | G19: 1.7887987 | H19: 2.0739189 | K19: 0 | L19: 2 | M19: Medellín AM
A20: 27 | B20: 1 | C20: Entre 100,001 y 500,000 | D20: Yopal | E20: 0.1549755 | F20: 0.29305233 | G20: 0.3699513 | H20: 0.75826317 | K20: 1 | L20: 2 | M20: Tunja
A21: 14 | B21: 2 | C21: Entre 50,0001 y 100,000 | D21: Neiva | E21: 1.7663443 | F21: 2.132365 | G21: 2.4801848 | H21: 2.8888141 | K21: 2 | L21: 3 | M21: Sincelejo
A22: 22 | B22: 2 | C22: Entre 50,0001 y 100,000 | D22: Florencia | E22: 1.2337132 | F22: 1.2597402 | G22: 0.8993509 | H22: 1.1517249 | K22: 3 | M22: RIOHACHA
A23: 23 | B23: 2 | C23: Entre 50,0001 y 100,000 | D23: Sincelejo | E23: 1.1243652 | F23: 1.4354955 | G23: 1.4835937 | H23: 1.922708 | K23: 4 | L23: 2 | M23: San José del Guaviare
A24: 17 | B24: 3 | C24: Entre 30,001 y 50,000 | D24: Riohacha | E24: 1.5148174 | F24: 2.3982135 | G24: 2.0229893 | H24: 2.0671971 | K24: 5 | L24: 2 | M24: Leticia
A25: 29 | B25: 4 | C25: Entre 20,001 y 30,000 | D25: Arauca | E25: 0.037215485 | F25: 0.072885229 | G25: 0.078022584 | H25: 0.10767774 | K25: 6 | M25: MITU
A26: 30 | B26: 4 | C26: Entre 20,001 y 30,000 | D26: San José del Guaviare | E26: 0.0056369042 | F26: 0.10683475 | G26: 0.097824624 | H26: 0.027838679
A27: 31 | B27: 4 | C27: Entre 20,001 y 30,000 | D27: Inírida | E27: 0 | F27: 0.027335699 | G27: 0.043747883 | H27: 0.050976815
A28: 32 | B28: 4 | C28: Entre 20,001 y 30,000 | D28: Puerto Carreño | E28: 0 | F28: 0.039239157 | G28: 0.037648555 | H28: 0
A29: 25 | B29: 4 | C29: Entre 20,001 y 30,000 | D29: Quibdó | E29: 0.69262599 | F29: 0.86174518 | G29: 0.94205656 | H29: 0.85499707
A30: 28 | B30: 5 | C30: Entre 10,001 y 20,000 | D30: Mocoa | E30: 0.042230305 | F30: 0.056740662 | G30: 0.049489352 | H30: 0.056359641
A31: 11 | B31: 5 | C31: Entre 10,001 y 20,000 | D31: Leticia | E31: 2.3303395 | F31: 2.3595739 | G31: 1.6707721 | H31: 2.0715406
A32: 24 | B32: 5 | C32: Entre 10,001 y 20,000 | D32: San Andrés | E32: 0.8675873 | F32: 0.99588741 | G32: 0.69813748 | H32: 0.69728248
A33: 26 | B33: 6 | C33: Igual o inferior a 10,000 | D33: Mitú | E33: 0.4944254 | F33: 0 | G33: 0 | H33: 0.024871754

Sheet RESULTADOS TIC
A1: CODIGO_MUN | B1: MUNICIPIO | C1: 2019 | D1: 2020 | E1: 2021 | F1: 2022
A2: 15001 | B2: Tunja | C2: 7.0836114 | D2: 6.8338361 | E2: 6.7592073 | F2: 7.9234066
B3: Bogotá D.C. | C3: 6.3740046 | D3: 6.491802 | E3: 6.5982603 | F3: 7.4541617
B4: Manizales AM | C4: 6.0811554 | D4: 5.8474092 | E4: 5.943323 | F4: 6.3495655
B5: Pereira AM | C5: 5.5179088 | D5: 5.7982993 | E5: 5.9960114 | F5: 6.3031229
B6: Bucaramanga AM | C6: 5.5123864 | D6: 5.4910332 | E6: 5.5429966 | F6: 5.6381079
B7: Popayán | C7: 5.3127593 | D7: 5.4469282 | E7: 5.1642612 | F7: 5.4543238
B8: Ibagué | C8: 5.3007036 | D8: 5.0891385 | E8: 5.1209137 | F8: 5.3729308
B9: Medellín AM | C9: 5.2411787 | D9: 5.3476558 | E9: 5.5759795 | F9: 5.9847136
B10: Cali AM | C10: 4.7271391 | D10: 4.8058819 | E10: 4.8650817 | F10: 5.3298767
B11: Armenia | C11: 4.5134668 | D11: 4.6641785 | E11: 4.9692574 | F11: 5.4140015
B12: Barranquilla AM | C12: 4.4413489 | D12: 4.5642123 | E12: 4.6418925 | F12: 4.926613
B13: Pasto | C13: 4.2566217 | D13: 4.1620815 | E13: 4.3682499 | F13: 4.7221878
B14: Neiva | C14: 4.171931 | D14: 4.2956627 | E14: 4.3305934 | F14: 4.7306163
... B33: Mitú | C33: 0.46415887 | D33: 0.60428034 | E33: 0.58143566 | F33: 0.61933054

Sheet Gráficos
G4: Ciudad | H4: 2019 | I4: 2020 | J4: 2021 | K4: 2022 | L4: 2023
G5: =A5 -> Arauca | H5: =B5 | I5: =C5 | J5: =D5 | K5: =E5 | L5: =F5 | M5: 1
G6: =A6 -> Armenia | H6: =B6 | I6: =C6 | J6: =D6 | K6: =E6 | L6: =F6 | M6: 1
G7: =A7 -> Barranquilla AM | H7: =B7 | I7: =C7 | J7: =D7 | K7: =E7 | L7: =F7 | M7: 1
G8: =A8 -> Bogotá D.C. | H8: =B8 | I8: =C8 | J8: =D8 | K8: =E8 | L8: =F8 | M8: 1
G9: =A9 -> Bucaramanga AM | H9: =B9 | I9: =C9 | J9: =D9 | K9: =E9 | L9: =F9 | M9: 1
G10: =A10 -> Cali AM | H10: =B10 | I10: =C10 | J10: =D10 | K10: =E10 | L10: =F10 | M10: 1
G11: =A11 -> Cartagena | H11: =B11 | I11: =C11 | J11: =D11 | K11: =E11 | L11: =F11 | M11: 1
G12: =A12 -> Cúcuta AM | H12: =B12 | I12: =C12 | J12: =D12 | K12: =E12 | L12: =F12 | M12: 1
G13: =A13 -> Florencia | H13: =B13 | I13: =C13 | J13: =D13 | K13: =E13 | L13: =F13 | M13: 1
G14: =A14 -> Ibagué | H14: =B14 | I14: =C14 | J14: =D14 | K14: =E14 | L14: =F14 | M14: 1
G15: =A15 -> Inírida | H15: =B15 | I15: =C15 | J15: =D15 | K15: =E15 | L15: =F15 | M15: 1
G16: =A16 -> Leticia | H16: =B16 | I16: =C16 | J16: =D16 | K16: =E16 | L16: =F16 | M16: 1
... G36: =A36 -> Yopal | H36: =B36 | I36: =C36 | J36: =D36 | K36: =E36 | L36: =F36 | M36: 1
H38: 2019 | I38: 2020 | J38: 2021 | K38: 2022 | L38: 2023
G39: Máximo | H39: =MAX(H5:H36) -> 0 | I39: =MAX(I5:I36) -> 0 | J39: =MAX(J5:J36) -> 0 | K39: =MAX(K5:K36) -> 0 | L39: =MAX(L5:L36) -> 0
G40: Mínimo | H40: =MIN(H5:H36) -> 0 | I40: =MIN(I5:I36) -> 0 | J40: =MIN(J5:J36) -> 0 | K40: =MIN(K5:K36) -> 0 | L40: =MIN(L5:L36) -> 0
G41: Promedio | H41: =AVERAGE(H5:H36) -> #DIV/0! | I41: =AVERAGE(I5:I36) -> #DIV/0! | J41: =AVERAGE(J5:J36) -> #DIV/0! | K41: =AVERAGE(K5:K36) -> #DIV/0! | L41: =AVERAGE(L5:L36) -> #DIV/0!
G42: Desviación estándar | H42: =_xlfn.STDEV.P(H5:H36) -> #DIV/0! | I42: =_xlfn.STDEV.P(I5:I36) -> #DIV/0! | J42: =_xlfn.STDEV.P(J5:J36) -> #DIV/0! | K42: =_xlfn.STDEV.P(K5:K36) -> #DIV/0! | L42: =_xlfn.STDEV.P(L5:L36) -> #DIV/0!
